Workbook

Sheet TRACK_STD
I1: =SUBTOTAL(9,I3:I513) -> 28001 | U1: =SUBTOTAL(9,U3:U513) -> 33646.915 | V1: =SUBTOTAL(9,V3:V513) -> 1278.5828 | W1: =SUBTOTAL(9,W3:W513) -> 1682.3458
A2: PO Received Date | B2: Shipment Date | C2: Matalan Product PO# | D2: Supplier Name | E2: Factory Name | F2: Packaging Supplier Name | G2: eBiz Customer Reference # | H2: eBiz Sales Order # | I2: Carton QTY | J2: Carton Style | K2: FLUTE | L2: Carton Selection | M2: Length(mm) | N2: Width(mm) | O2: Height(mm) | P2: L | Q2: W | R2: Area(sqm) | S2: Carton's Unit Price (CNY,EXW w/VAT) | T2: Final Price, CNY/CTN | U2: Total Amount | V2: 4% for PACD | W2: Rebates for Matalan (Singles=5%) | X2: NOTE
A3: 46235 | B3: 46237 | D3: KDS IDR Ltd. | E3: KDS IDR Ltd. | F3: Transworld Packaging (BD) Ltd. | G3: B0496925 | H3: 7124457 | I3: 176 | J3: Standard Carton-Singles | K3: BC-Flute | L3: C1 | M3: {=IF(L3="",0,_xlfn.SWITCH(L3,"A1",495,"A2",495,"A3",495,"Custom",0,595))} -> 595 | N3: {=IF(L3="",0,_xlfn.SWITCH(L3,"C1",325,"C2",325,"C3",325,"D1",380,"D2",380,"D3",380,"Custom",0,285))} -> 325 | O3: =IF(L3="",0,_xlfn.SWITCH(L3,"A1",375,"B1",375,"C1",375,"D1",375,"A2",310,"B2",310,"C2",310,"D2",310,"Custom",0,260)) -> 375 | P3: =IFERROR(IF(OR(M3=0,N3=0),0,(M3+N3)*2+11),0) -> 1851 | Q3: =IFERROR(IF(OR(N3=0,O3=0),0,(N3+O3)-16),0) -> 684 | R3: =P3*Q3/1000000 -> 1.266084 | S3: =IFERROR(VLOOKUP(L3,'Carton Sizes Chart'!$A$4:$E$15,5,FALSE),0) -> 1.22 | T3: =S3 -> 1.22 | U3: =I3*T3 -> 214.72 | V3: =((T3*I3)-W3)*4% -> 8.15936 | W3: =S3*I3*5% -> 10.736
A4: 46235 | B4: 46237 | D4: KDS IDR Ltd. | E4: KDS IDR Ltd. | F4: Transworld Packaging (BD) Ltd. | G4: G0516728 | H4: 7125716 | I4: 131 | J4: Standard Carton-Singles | K4: BC-Flute | L4: D3 | M4: {=IF(L4="",0,_xlfn.SWITCH(L4,"A1",495,"A2",495,"A3",495,"Custom",0,595))} -> 595 | N4: {=IF(L4="",0,_xlfn.SWITCH(L4,"C1",325,"C2",325,"C3",325,"D1",380,"D2",380,"D3",380,"Custom",0,285))} -> 380 | O4: =IF(L4="",0,_xlfn.SWITCH(L4,"A1",375,"B1",375,"C1",375,"D1",375,"A2",310,"B2",310,"C2",310,"D2",310,"Custom",0,260)) -> 260 | P4: =IFERROR(IF(OR(M4=0,N4=0),0,(M4+N4)*2+11),0) -> 1961 | Q4: =IFERROR(IF(OR(N4=0,O4=0),0,(N4+O4)-16),0) -> 624 | R4: =P4*Q4/1000000 -> 1.223664 | S4: =IFERROR(VLOOKUP(L4,'Carton Sizes Chart'!$A$4:$E$15,5,FALSE),0) -> 1.18 | T4: =S4 -> 1.18 | U4: =I4*T4 -> 154.58 | V4: =((T4*I4)-W4)*4% -> 5.87404 | W4: =S4*I4*5% -> 7.729
A5: 46233 | B5: 46235 | D5: Appollo Fashion Ltd. | E5: Appollo Knit Wear (BD) Ltd. | F5: Transworld Packaging (BD) Ltd. | G5: ASW26TG41_900+73+74+75+7 | H5: 7126382 | I5: 43 | J5: Standard Carton-Singles | K5: BC-Flute | L5: C2 | M5: {=IF(L5="",0,_xlfn.SWITCH(L5,"A1",495,"A2",495,"A3",495,"Custom",0,595))} -> 595 | N5: {=IF(L5="",0,_xlfn.SWITCH(L5,"C1",325,"C2",325,"C3",325,"D1",380,"D2",380,"D3",380,"Custom",0,285))} -> 325 | O5: =IF(L5="",0,_xlfn.SWITCH(L5,"A1",375,"B1",375,"C1",375,"D1",375,"A2",310,"B2",310,"C2",310,"D2",310,"Custom",0,260)) -> 310 | P5: =IFERROR(IF(OR(M5=0,N5=0),0,(M5+N5)*2+11),0) -> 1851 | Q5: =IFERROR(IF(OR(N5=0,O5=0),0,(N5+O5)-16),0) -> 619 | R5: =P5*Q5/1000000 -> 1.145769 | S5: =IFERROR(VLOOKUP(L5,'Carton Sizes Chart'!$A$4:$E$15,5,FALSE),0) -> 1.1 | T5: =S5 -> 1.1 | U5: =I5*T5 -> 47.3 | V5: =((T5*I5)-W5)*4% -> 1.7974 | W5: =S5*I5*5% -> 2.365
A6: 46233 | B6: 46235 | D6: Appollo Fashion Ltd. | E6: Appollo Knit Wear (BD) Ltd. | F6: Transworld Packaging (BD) Ltd. | G6: ASW26TG41_900+73+74+75+7 | H6: 7126382 | I6: 62 | J6: Standard Carton-Singles | K6: BC-Flute | L6: D2 | M6: {=IF(L6="",0,_xlfn.SWITCH(L6,"A1",495,"A2",495,"A3",495,"Custom",0,595))} -> 595 | N6: {=IF(L6="",0,_xlfn.SWITCH(L6,"C1",325,"C2",325,"C3",325,"D1",380,"D2",380,"D3",380,"Custom",0,285))} -> 380 | O6: =IF(L6="",0,_xlfn.SWITCH(L6,"A1",375,"B1",375,"C1",375,"D1",375,"A2",310,"B2",310,"C2",310,"D2",310,"Custom",0,260)) -> 310 | P6: =IFERROR(IF(OR(M6=0,N6=0),0,(M6+N6)*2+11),0) -> 1961 | Q6: =IFERROR(IF(OR(N6=0,O6=0),0,(N6+O6)-16),0) -> 674 | R6: =P6*Q6/1000000 -> 1.321714 | S6: =IFERROR(VLOOKUP(L6,'Carton Sizes Chart'!$A$4:$E$15,5,FALSE),0) -> 1.27 | T6: =S6 -> 1.27 | U6: =I6*T6 -> 78.74 | V6: =((T6*I6)-W6)*4% -> 2.99212 | W6: =S6*I6*5% -> 3.937
A7: 46233 | B7: 46235 | D7: Lariz Fashion Ltd | E7: Lariz Fashion Ltd | F7: Transworld Packaging (BD) Ltd. | G7: C0998545 | H7: 7126761 | I7: 130 | J7: Standard Carton-Singles | K7: BC-Flute | L7: C2 | M7: {=IF(L7="",0,_xlfn.SWITCH(L7,"A1",495,"A2",495,"A3",495,"Custom",0,595))} -> 595 | N7: {=IF(L7="",0,_xlfn.SWITCH(L7,"C1",325,"C2",325,"C3",325,"D1",380,"D2",380,"D3",380,"Custom",0,285))} -> 325 | O7: =IF(L7="",0,_xlfn.SWITCH(L7,"A1",375,"B1",375,"C1",375,"D1",375,"A2",310,"B2",310,"C2",310,"D2",310,"Custom",0,260)) -> 310 | P7: =IFERROR(IF(OR(M7=0,N7=0),0,(M7+N7)*2+11),0) -> 1851 | Q7: =IFERROR(IF(OR(N7=0,O7=0),0,(N7+O7)-16),0) -> 619 | R7: =P7*Q7/1000000 -> 1.145769 | S7: =IFERROR(VLOOKUP(L7,'Carton Sizes Chart'!$A$4:$E$15,5,FALSE),0) -> 1.1 | T7: =S7 -> 1.1 | U7: =I7*T7 -> 143 | V7: =((T7*I7)-W7)*4% -> 5.434 | W7: =S7*I7*5% -> 7.15
A8: 46235 | B8: 46237 | D8: KDS IDR Ltd. | E8: KDS IDR Ltd. | F8: Transworld Packaging (BD) Ltd. | G8: B0496737 | H8: 7127600 | I8: 37 | J8: Standard Carton-Singles | K8: BC-Flute | L8: D1 | M8: {=IF(L8="",0,_xlfn.SWITCH(L8,"A1",495,"A2",495,"A3",495,"Custom",0,595))} -> 595 | N8: {=IF(L8="",0,_xlfn.SWITCH(L8,"C1",325,"C2",325,"C3",325,"D1",380,"D2",380,"D3",380,"Custom",0,285))} -> 380 | O8: =IF(L8="",0,_xlfn.SWITCH(L8,"A1",375,"B1",375,"C1",375,"D1",375,"A2",310,"B2",310,"C2",310,"D2",310,"Custom",0,260)) -> 375 | P8: =IFERROR(IF(OR(M8=0,N8=0),0,(M8+N8)*2+11),0) -> 1961 | Q8: =IFERROR(IF(OR(N8=0,O8=0),0,(N8+O8)-16),0) -> 739 | R8: =P8*Q8/1000000 -> 1.449179 | S8: =IFERROR(VLOOKUP(L8,'Carton Sizes Chart'!$A$4:$E$15,5,FALSE),0) -> 1.39 | T8: =S8 -> 1.39 | U8: =I8*T8 -> 51.43 | V8: =((T8*I8)-W8)*4% -> 1.95434 | W8: =S8*I8*5% -> 2.5715
A9: 46235 | B9: 46237 | D9: KDS IDR Ltd. | E9: KDS IDR Ltd. | F9: Transworld Packaging (BD) Ltd. | G9: G0516728 | H9: 7127890 | I9: 122 | J9: Standard Carton-Singles | K9: BC-Flute | L9: D3 | M9: {=IF(L9="",0,_xlfn.SWITCH(L9,"A1",495,"A2",495,"A3",495,"Custom",0,595))} -> 595 | N9: {=IF(L9="",0,_xlfn.SWITCH(L9,"C1",325,"C2",325,"C3",325,"D1",380,"D2",380,"D3",380,"Custom",0,285))} -> 380 | O9: =IF(L9="",0,_xlfn.SWITCH(L9,"A1",375,"B1",375,"C1",375,"D1",375,"A2",310,"B2",310,"C2",310,"D2",310,"Custom",0,260)) -> 260 | P9: =IFERROR(IF(OR(M9=0,N9=0),0,(M9+N9)*2+11),0) -> 1961 | Q9: =IFERROR(IF(OR(N9=0,O9=0),0,(N9+O9)-16),0) -> 624 | R9: =P9*Q9/1000000 -> 1.223664 | S9: =IFERROR(VLOOKUP(L9,'Carton Sizes Chart'!$A$4:$E$15,5,FALSE),0) -> 1.18 | T9: =S9 -> 1.18 | U9: =I9*T9 -> 143.96 | V9: =((T9*I9)-W9)*4% -> 5.47048 | W9: =S9*I9*5% -> 7.198
A10: 46236 | B10: 46238 | D10: CONCORD VENTURES EXPORTS LLC | E10: Dhaka Garments & Washing Ltd. | F10: Transworld Packaging (BD) Ltd. | G10: Relaxed Fit | H10: 7127958 | I10: 260 | J10: Standard Carton-Singles | K10: BC-Flute | L10: C1 | M10: {=IF(L10="",0,_xlfn.SWITCH(L10,"A1",495,"A2",495,"A3",495,"Custom",0,595))} -> 595 | N10: {=IF(L10="",0,_xlfn.SWITCH(L10,"C1",325,"C2",325,"C3",325,"D1",380,"D2",380,"D3",380,"Custom",0,285))} -> 325 | O10: =IF(L10="",0,_xlfn.SWITCH(L10,"A1",375,"B1",375,"C1",375,"D1",375,"A2",310,"B2",310,"C2",310,"D2",310,"Custom",0,260)) -> 375 | P10: =IFERROR(IF(OR(M10=0,N10=0),0,(M10+N10)*2+11),0) -> 1851 | Q10: =IFERROR(IF(OR(N10=0,O10=0),0,(N10+O10)-16),0) -> 684 | R10: =P10*Q10/1000000 -> 1.266084 | S10: =IFERROR(VLOOKUP(L10,'Carton Sizes Chart'!$A$4:$E$15,5,FALSE),0) -> 1.22 | T10: =S10 -> 1.22 | U10: =I10*T10 -> 317.2 | V10: =((T10*I10)-W10)*4% -> 12.0536 | W10: =S10*I10*5% -> 15.86
A11: 46240 | B11: 46243 | D11: KDS IDR Ltd. | E11: KDS IDR Ltd. | F11: Transworld Packaging (BD) Ltd. | G11: G0516742 | H11: 7130655 | I11: 156 | J11: Standard Carton-Singles | K11: BC-Flute | L11: D1 | M11: {=IF(L11="",0,_xlfn.SWITCH(L11,"A1",495,"A2",495,"A3",495,"Custom",0,595))} -> 595 | N11: {=IF(L11="",0,_xlfn.SWITCH(L11,"C1",325,"C2",325,"C3",325,"D1",380,"D2",380,"D3",380,"Custom",0,285))} -> 380 | O11: =IF(L11="",0,_xlfn.SWITCH(L11,"A1",375,"B1",375,"C1",375,"D1",375,"A2",310,"B2",310,"C2",310,"D2",310,"Custom",0,260)) -> 375 | P11: =IFERROR(IF(OR(M11=0,N11=0),0,(M11+N11)*2+11),0) -> 1961 | Q11: =IFERROR(IF(OR(N11=0,O11=0),0,(N11+O11)-16),0) -> 739 | R11: =P11*Q11/1000000 -> 1.449179 | S11: =IFERROR(VLOOKUP(L11,'Carton Sizes Chart'!$A$4:$E$15,5,FALSE),0) -> 1.39 | T11: =S11 -> 1.39 | U11: =I11*T11 -> 216.84 | V11: =((T11*I11)-W11)*4% -> 8.23992 | W11: =S11*I11*5% -> 10.842
A12: 46245 | B12: 46246 | D12: Grand Apparels Design | E12: Virtual Bottom | F12: Transworld Packaging (BD) Ltd. | G12: F3033105 | H12: 7133412 | I12: 30 | J12: Standard Carton-Singles | K12: BC-Flute | L12: D1 | M12: {=IF(L12="",0,_xlfn.SWITCH(L12,"A1",495,"A2",495,"A3",495,"Custom",0,595))} -> 595 | N12: {=IF(L12="",0,_xlfn.SWITCH(L12,"C1",325,"C2",325,"C3",325,"D1",380,"D2",380,"D3",380,"Custom",0,285))} -> 380 | O12: =IF(L12="",0,_xlfn.SWITCH(L12,"A1",375,"B1",375,"C1",375,"D1",375,"A2",310,"B2",310,"C2",310,"D2",310,"Custom",0,260)) -> 375 | P12: =IFERROR(IF(OR(M12=0,N12=0),0,(M12+N12)*2+11),0) -> 1961 | Q12: =IFERROR(IF(OR(N12=0,O12=0),0,(N12+O12)-16),0) -> 739 | R12: =P12*Q12/1000000 -> 1.449179 | S12: =IFERROR(VLOOKUP(L12,'Carton Sizes Chart'!$A$4:$E$15,5,FALSE),0) -> 1.39 | T12: =S12 -> 1.39 | U12: =I12*T12 -> 41.7 | V12: =((T12*I12)-W12)*4% -> 1.5846 | W12: =S12*I12*5% -> 2.085
A13: 46246 | B13: 46247 | D13: KDS IDR Ltd. | E13: KDS IDR Ltd. | F13: Transworld Packaging (BD) Ltd. | G13: G0516742 | H13: 7134357 | I13: 111 | J13: Standard Carton-Singles | K13: BC-Flute | L13: D1 | M13: {=IF(L13="",0,_xlfn.SWITCH(L13,"A1",495,"A2",495,"A3",495,"Custom",0,595))} -> 595 | N13: {=IF(L13="",0,_xlfn.SWITCH(L13,"C1",325,"C2",325,"C3",325,"D1",380,"D2",380,"D3",380,"Custom",0,285))} -> 380 | O13: =IF(L13="",0,_xlfn.SWITCH(L13,"A1",375,"B1",375,"C1",375,"D1",375,"A2",310,"B2",310,"C2",310,"D2",310,"Custom",0,260)) -> 375 | P13: =IFERROR(IF(OR(M13=0,N13=0),0,(M13+N13)*2+11),0) -> 1961 | Q13: =IFERROR(IF(OR(N13=0,O13=0),0,(N13+O13)-16),0) -> 739 | R13: =P13*Q13/1000000 -> 1.449179 | S13: =IFERROR(VLOOKUP(L13,'Carton Sizes Chart'!$A$4:$E$15,5,FALSE),0) -> 1.39 | T13: =S13 -> 1.39 | U13: =I13*T13 -> 154.29 | V13: =((T13*I13)-W13)*4% -> 5.86302 | W13: =S13*I13*5% -> 7.7145
A14: 46247 | B14: 46249 | D14: Grand Apparels Design | E14: Virtual Bottom | F14: Transworld Packaging (BD) Ltd. | G14: F3033032 | H14: 7134783 | I14: 15 | J14: Standard Carton-Singles | K14: BC-Flute | L14: D1 | M14: {=IF(L14="",0,_xlfn.SWITCH(L14,"A1",495,"A2",495,"A3",495,"Custom",0,595))} -> 595 | N14: {=IF(L14="",0,_xlfn.SWITCH(L14,"C1",325,"C2",325,"C3",325,"D1",380,"D2",380,"D3",380,"Custom",0,285))} -> 380 | O14: =IF(L14="",0,_xlfn.SWITCH(L14,"A1",375,"B1",375,"C1",375,"D1",375,"A2",310,"B2",310,"C2",310,"D2",310,"Custom",0,260)) -> 375 | P14: =IFERROR(IF(OR(M14=0,N14=0),0,(M14+N14)*2+11),0) -> 1961 | Q14: =IFERROR(IF(OR(N14=0,O14=0),0,(N14+O14)-16),0) -> 739 | R14: =P14*Q14/1000000 -> 1.449179 | S14: =IFERROR(VLOOKUP(L14,'Carton Sizes Chart'!$A$4:$E$15,5,FALSE),0) -> 1.39 | T14: =S14 -> 1.39 | U14: =I14*T14 -> 20.85 | V14: =((T14*I14)-W14)*4% -> 0.7923 | W14: =S14*I14*5% -> 1.0425
... A57: 46264 | B57: 46265 | D57: KDS IDR Ltd. | E57: KDS IDR Ltd. | F57: Transworld Packaging (BD) Ltd. | G57: C1018995 | H57: 7144726 | I57: 1219 | J57: Standard Carton-Singles | K57: BC-Flute | L57: B1 | M57: {=IF(L57="",0,_xlfn.SWITCH(L57,"A1",495,"A2",495,"A3",495,"Custom",0,595))} -> 595 | N57: {=IF(L57="",0,_xlfn.SWITCH(L57,"C1",325,"C2",325,"C3",325,"D1",380,"D2",380,"D3",380,"Custom",0,285))} -> 285 | O57: =IF(L57="",0,_xlfn.SWITCH(L57,"A1",375,"B1",375,"C1",375,"D1",375,"A2",310,"B2",310,"C2",310,"D2",310,"Custom",0,260)) -> 375 | P57: =IFERROR(IF(OR(M57=0,N57=0),0,(M57+N57)*2+11),0) -> 1771 | Q57: =IFERROR(IF(OR(N57=0,O57=0),0,(N57+O57)-16),0) -> 644 | R57: =P57*Q57/1000000 -> 1.140524 | S57: =IFERROR(VLOOKUP(L57,'Carton Sizes Chart'!$A$4:$E$15,5,FALSE),0) -> 1.1 | T57: =S57 -> 1.1 | U57: =I57*T57 -> 1340.9 | V57: =((T57*I57)-W57)*4% -> 50.9542 | W57: =S57*I57*5% -> 67.045
A58: 46232 | B58: 46235 | D58: Crown Exclusive Wears Ltd. | E58: Crown Exclusive Wears Ltd. | F58: Uniglory Packaging Industries Ltd. | G58: CHW26KN076 | H58: 7125575 | I58: 221 | J58: Standard Carton-Singles | K58: BC-Flute | L58: Custom | M58: 750 | N58: 560 | O58: 320 | P58: =IFERROR(IF(OR(M58=0,N58=0),0,(M58+N58)*2+11),0) -> 2631 | Q58: =IFERROR(IF(OR(N58=0,O58=0),0,(N58+O58)-16),0) -> 864 | R58: =P58*Q58/1000000 -> 2.273184 | S58: =IF(L58="Custom", R58*'[1]RFQ_Matalan Carton'!$M$40, IFERROR(VLOOKUP(L58,'[1]Carton Sizes Chart'!$A$4:$E$15,5,FALSE),0)) -> 2.1822566 | T58: =S58 -> 2.1822566 | U58: =I58*T58 -> 482.27872 | V58: =((T58*I58)-W58)*4% -> 18.326591 | W58: =S58*I58*5% -> 24.113936
A59: 46232 | B59: 46235 | D59: Crown Exclusive Wears Ltd. | E59: Crown Exclusive Wears Ltd. | F59: Uniglory Packaging Industries Ltd. | G59: CHW26KN076 | H59: 7125575 | I59: 329 | J59: Standard Carton-Singles | K59: BC-Flute | L59: Custom | M59: 770 | N59: 610 | O59: 320 | P59: =IFERROR(IF(OR(M59=0,N59=0),0,(M59+N59)*2+11),0) -> 2771 | Q59: =IFERROR(IF(OR(N59=0,O59=0),0,(N59+O59)-16),0) -> 914 | R59: =P59*Q59/1000000 -> 2.532694 | S59: =IF(L59="Custom", R59*'[1]RFQ_Matalan Carton'!$M$40, IFERROR(VLOOKUP(L59,'[1]Carton Sizes Chart'!$A$4:$E$15,5,FALSE),0)) -> 2.4313862 | T59: =S59 -> 2.4313862 | U59: =I59*T59 -> 799.92607 | V59: =((T59*I59)-W59)*4% -> 30.397191 | W59: =S59*I59*5% -> 39.996304
A60: 46232 | B60: 46235 | D60: Crown Exclusive Wears Ltd. | E60: Crown Exclusive Wears Ltd. | F60: Uniglory Packaging Industries Ltd. | G60: CHW26KN076 | H60: 7125575 | I60: 204 | J60: Standard Carton-Singles | K60: BC-Flute | L60: Custom | M60: 790 | N60: 660 | O60: 320 | P60: =IFERROR(IF(OR(M60=0,N60=0),0,(M60+N60)*2+11),0) -> 2911 | Q60: =IFERROR(IF(OR(N60=0,O60=0),0,(N60+O60)-16),0) -> 964 | R60: =P60*Q60/1000000 -> 2.806204 | S60: =IF(L60="Custom", R60*'[1]RFQ_Matalan Carton'!$M$40, IFERROR(VLOOKUP(L60,'[1]Carton Sizes Chart'!$A$4:$E$15,5,FALSE),0)) -> 2.6939558 | T60: =S60 -> 2.6939558 | U60: =I60*T60 -> 549.56699 | V60: =((T60*I60)-W60)*4% -> 20.883546 | W60: =S60*I60*5% -> 27.47835
A61: 46232 | B61: 46235 | D61: Crown Exclusive Wears Ltd. | E61: Crown Exclusive Wears Ltd. | F61: Uniglory Packaging Industries Ltd. | G61: CHW26KN076 | H61: 7125575 | I61: 71 | J61: Standard Carton-Singles | K61: BC-Flute | L61: Custom | M61: 810 | N61: 710 | O61: 320 | P61: =IFERROR(IF(OR(M61=0,N61=0),0,(M61+N61)*2+11),0) -> 3051 | Q61: =IFERROR(IF(OR(N61=0,O61=0),0,(N61+O61)-16),0) -> 1014 | R61: =P61*Q61/1000000 -> 3.093714 | S61: =IF(L61="Custom", R61*'[1]RFQ_Matalan Carton'!$M$40, IFERROR(VLOOKUP(L61,'[1]Carton Sizes Chart'!$A$4:$E$15,5,FALSE),0)) -> 2.9699654 | T61: =S61 -> 2.9699654 | U61: =I61*T61 -> 210.86755 | V61: =((T61*I61)-W61)*4% -> 8.0129668 | W61: =S61*I61*5% -> 10.543377
A62: 46232 | B62: 46235 | D62: Crown Exclusive Wears Ltd. | E62: Crown Exclusive Wears Ltd. | F62: Uniglory Packaging Industries Ltd. | G62: CHW26KN076 | H62: 7125575 | I62: 555 | J62: Standard Carton-Singles | K62: BC-Flute | L62: Custom | M62: 800 | N62: 620 | O62: 240 | P62: =IFERROR(IF(OR(M62=0,N62=0),0,(M62+N62)*2+11),0) -> 2851 | Q62: =IFERROR(IF(OR(N62=0,O62=0),0,(N62+O62)-16),0) -> 844 | R62: =P62*Q62/1000000 -> 2.406244 | S62: =IF(L62="Custom", R62*'[1]RFQ_Matalan Carton'!$M$40, IFERROR(VLOOKUP(L62,'[1]Carton Sizes Chart'!$A$4:$E$15,5,FALSE),0)) -> 2.3099942 | T62: =S62 -> 2.3099942 | U62: =I62*T62 -> 1282.0468 | V62: =((T62*I62)-W62)*4% -> 48.717779 | W62: =S62*I62*5% -> 64.10234
A63: 46232 | B63: 46235 | D63: Design ARC Asia | E63: Confidance Knitwear Ltd. | F63: Uniglory Packaging Industries Ltd. | G63: OB010 B0501578 | H63: 7126198 | I63: 179 | J63: Standard Carton-Singles | K63: BC-Flute | L63: C3 | M63: {=IF(L63="",0,_xlfn.SWITCH(L63,"A1",495,"A2",495,"A3",495,"Custom",0,595))} -> 595 | N63: {=IF(L63="",0,_xlfn.SWITCH(L63,"C1",325,"C2",325,"C3",325,"D1",380,"D2",380,"D3",380,"Custom",0,285))} -> 325 | O63: =IF(L63="",0,_xlfn.SWITCH(L63,"A1",375,"B1",375,"C1",375,"D1",375,"A2",310,"B2",310,"C2",310,"D2",310,"Custom",0,260)) -> 260 | P63: =IFERROR(IF(OR(M63=0,N63=0),0,(M63+N63)*2+11),0) -> 1851 | Q63: =IFERROR(IF(OR(N63=0,O63=0),0,(N63+O63)-16),0) -> 569 | R63: =P63*Q63/1000000 -> 1.053219 | S63: =IFERROR(VLOOKUP(L63,'Carton Sizes Chart'!$A$4:$E$15,5,FALSE),0) -> 1.02 | T63: =S63 -> 1.02 | U63: =I63*T63 -> 182.58 | V63: =((T63*I63)-W63)*4% -> 6.93804 | W63: =S63*I63*5% -> 9.129
A64: 46232 | B64: 46235 | D64: Design ARC Asia | E64: Confidance Knitwear Ltd. | F64: Uniglory Packaging Industries Ltd. | G64: OB010 B0501578 | H64: 7126198 | I64: 57 | J64: Standard Carton-Singles | K64: BC-Flute | L64: C2 | M64: {=IF(L64="",0,_xlfn.SWITCH(L64,"A1",495,"A2",495,"A3",495,"Custom",0,595))} -> 595 | N64: {=IF(L64="",0,_xlfn.SWITCH(L64,"C1",325,"C2",325,"C3",325,"D1",380,"D2",380,"D3",380,"Custom",0,285))} -> 325 | O64: =IF(L64="",0,_xlfn.SWITCH(L64,"A1",375,"B1",375,"C1",375,"D1",375,"A2",310,"B2",310,"C2",310,"D2",310,"Custom",0,260)) -> 310 | P64: =IFERROR(IF(OR(M64=0,N64=0),0,(M64+N64)*2+11),0) -> 1851 | Q64: =IFERROR(IF(OR(N64=0,O64=0),0,(N64+O64)-16),0) -> 619 | R64: =P64*Q64/1000000 -> 1.145769 | S64: =IFERROR(VLOOKUP(L64,'Carton Sizes Chart'!$A$4:$E$15,5,FALSE),0) -> 1.1 | T64: =S64 -> 1.1 | U64: =I64*T64 -> 62.7 | V64: =((T64*I64)-W64)*4% -> 2.3826 | W64: =S64*I64*5% -> 3.135
A65: 46236 | B65: 46236 | D65: Crown Exclusive Wears Ltd. | E65: Crown Exclusive Wears Ltd. | F65: Uniglory Packaging Industries Ltd. | G65: CHW26KN084 | H65: 7127907 | I65: 40 | J65: Standard Carton-Singles | K65: BC-Flute | L65: Custom | M65: 620 | N65: 420 | O65: 250 | P65: =IFERROR(IF(OR(M65=0,N65=0),0,(M65+N65)*2+11),0) -> 2091 | Q65: =IFERROR(IF(OR(N65=0,O65=0),0,(N65+O65)-16),0) -> 654 | R65: =P65*Q65/1000000 -> 1.367514 | S65: =IF(L65="Custom", R65*'[1]RFQ_Matalan Carton'!$M$40, IFERROR(VLOOKUP(L65,'[1]Carton Sizes Chart'!$A$4:$E$15,5,FALSE),0)) -> 1.3128134 | T65: =S65 -> 1.3128134 | U65: =I65*T65 -> 52.512538 | V65: =((T65*I65)-W65)*4% -> 1.9954764 | W65: =S65*I65*5% -> 2.6256269
A66: 46236 | B66: 46240 | D66: Design ARC Asia | E66: Confidance Knitwear Ltd. | F66: Uniglory Packaging Industries Ltd. | G66: TG03 | H66: 7128054 | I66: 148 | J66: Standard Carton-Singles | K66: BC-Flute | L66: C1 | M66: {=IF(L66="",0,_xlfn.SWITCH(L66,"A1",495,"A2",495,"A3",495,"Custom",0,595))} -> 595 | N66: {=IF(L66="",0,_xlfn.SWITCH(L66,"C1",325,"C2",325,"C3",325,"D1",380,"D2",380,"D3",380,"Custom",0,285))} -> 325 | O66: =IF(L66="",0,_xlfn.SWITCH(L66,"A1",375,"B1",375,"C1",375,"D1",375,"A2",310,"B2",310,"C2",310,"D2",310,"Custom",0,260)) -> 375 | P66: =IFERROR(IF(OR(M66=0,N66=0),0,(M66+N66)*2+11),0) -> 1851 | Q66: =IFERROR(IF(OR(N66=0,O66=0),0,(N66+O66)-16),0) -> 684 | R66: =P66*Q66/1000000 -> 1.266084 | S66: =IFERROR(VLOOKUP(L66,'Carton Sizes Chart'!$A$4:$E$15,5,FALSE),0) -> 1.22 | T66: =S66 -> 1.22 | U66: =I66*T66 -> 180.56 | V66: =((T66*I66)-W66)*4% -> 6.86128 | W66: =S66*I66*5% -> 9.028
A67: 46238 | B67: 46243 | D67: Design ARC Asia | E67: Confidance Knitwear Ltd. | F67: Uniglory Packaging Industries Ltd. | G67: TG01 | H67: 7129094 | I67: 44 | J67: Standard Carton-Singles | K67: BC-Flute | L67: C2 | M67: {=IF(L67="",0,_xlfn.SWITCH(L67,"A1",495,"A2",495,"A3",495,"Custom",0,595))} -> 595 | N67: {=IF(L67="",0,_xlfn.SWITCH(L67,"C1",325,"C2",325,"C3",325,"D1",380,"D2",380,"D3",380,"Custom",0,285))} -> 325 | O67: =IF(L67="",0,_xlfn.SWITCH(L67,"A1",375,"B1",375,"C1",375,"D1",375,"A2",310,"B2",310,"C2",310,"D2",310,"Custom",0,260)) -> 310 | P67: =IFERROR(IF(OR(M67=0,N67=0),0,(M67+N67)*2+11),0) -> 1851 | Q67: =IFERROR(IF(OR(N67=0,O67=0),0,(N67+O67)-16),0) -> 619 | R67: =P67*Q67/1000000 -> 1.145769 | S67: =IFERROR(VLOOKUP(L67,'Carton Sizes Chart'!$A$4:$E$15,5,FALSE),0) -> 1.1 | T67: =S67 -> 1.1 | U67: =I67*T67 -> 48.4 | V67: =((T67*I67)-W67)*4% -> 1.8392 | W67: =S67*I67*5% -> 2.42
A68: 46240 | B68: 46243 | D68: Design ARC Asia | E68: Confidance Knitwear Ltd. | F68: Uniglory Packaging Industries Ltd. | G68: OB01 | H68: 7130506 | I68: 158 | J68: Standard Carton-Singles | K68: BC-Flute | L68: C1 | M68: {=IF(L68="",0,_xlfn.SWITCH(L68,"A1",495,"A2",495,"A3",495,"Custom",0,595))} -> 595 | N68: {=IF(L68="",0,_xlfn.SWITCH(L68,"C1",325,"C2",325,"C3",325,"D1",380,"D2",380,"D3",380,"Custom",0,285))} -> 325 | O68: =IF(L68="",0,_xlfn.SWITCH(L68,"A1",375,"B1",375,"C1",375,"D1",375,"A2",310,"B2",310,"C2",310,"D2",310,"Custom",0,260)) -> 375 | P68: =IFERROR(IF(OR(M68=0,N68=0),0,(M68+N68)*2+11),0) -> 1851 | Q68: =IFERROR(IF(OR(N68=0,O68=0),0,(N68+O68)-16),0) -> 684 | R68: =P68*Q68/1000000 -> 1.266084 | S68: =IFERROR(VLOOKUP(L68,'Carton Sizes Chart'!$A$4:$E$15,5,FALSE),0) -> 1.22 | T68: =S68 -> 1.22 | U68: =I68*T68 -> 192.76 | V68: =((T68*I68)-W68)*4% -> 7.32488 | W68: =S68*I68*5% -> 9.638
A69: 46243 | B69: 46244 | D69: Design ARC Asia | E69: AR-Tex Composite Ltd. | F69: Uniglory Packaging Industries Ltd. | G69: F476035 | H69: 7132064 | I69: 1600 | J69: Standard Carton-Singles | K69: BC-Flute | L69: B1 | M69: {=IF(L69="",0,_xlfn.SWITCH(L69,"A1",495,"A2",495,"A3",495,"Custom",0,595))} -> 595 | N69: {=IF(L69="",0,_xlfn.SWITCH(L69,"C1",325,"C2",325,"C3",325,"D1",380,"D2",380,"D3",380,"Custom",0,285))} -> 285 | O69: =IF(L69="",0,_xlfn.SWITCH(L69,"A1",375,"B1",375,"C1",375,"D1",375,"A2",310,"B2",310,"C2",310,"D2",310,"Custom",0,260)) -> 375 | P69: =IFERROR(IF(OR(M69=0,N69=0),0,(M69+N69)*2+11),0) -> 1771 | Q69: =IFERROR(IF(OR(N69=0,O69=0),0,(N69+O69)-16),0) -> 644 | R69: =P69*Q69/1000000 -> 1.140524 | S69: =IFERROR(VLOOKUP(L69,'Carton Sizes Chart'!$A$4:$E$15,5,FALSE),0) -> 1.1 | T69: =S69 -> 1.1 | U69: =I69*T69 -> 1760 | V69: =((T69*I69)-W69)*4% -> 66.88 | W69: =S69*I69*5% -> 88
A70: 46246 | B70: 46247 | D70: KESKAN FZC | E70: H.B Knittex Ltd. | F70: Uniglory Packaging Industries Ltd. | G70: GCW26SE19AB | H70: 7132988 | I70: 21 | J70: Standard Carton-Singles | K70: BC-Flute | L70: C3 | M70: {=IF(L70="",0,_xlfn.SWITCH(L70,"A1",495,"A2",495,"A3",495,"Custom",0,595))} -> 595 | N70: {=IF(L70="",0,_xlfn.SWITCH(L70,"C1",325,"C2",325,"C3",325,"D1",380,"D2",380,"D3",380,"Custom",0,285))} -> 325 | O70: =IF(L70="",0,_xlfn.SWITCH(L70,"A1",375,"B1",375,"C1",375,"D1",375,"A2",310,"B2",310,"C2",310,"D2",310,"Custom",0,260)) -> 260 | P70: =IFERROR(IF(OR(M70=0,N70=0),0,(M70+N70)*2+11),0) -> 1851 | Q70: =IFERROR(IF(OR(N70=0,O70=0),0,(N70+O70)-16),0) -> 569 | R70: =P70*Q70/1000000 -> 1.053219 | S70: =IFERROR(VLOOKUP(L70,'Carton Sizes Chart'!$A$4:$E$15,5,FALSE),0) -> 1.02 | T70: =S70 -> 1.02 | U70: =I70*T70 -> 21.42 | V70: =((T70*I70)-W70)*4% -> 0.81396 | W70: =S70*I70*5% -> 1.071 | X70: Revise
A71: 46246 | B71: 46247 | D71: KESKAN FZC | E71: H.B Knittex Ltd. | F71: Uniglory Packaging Industries Ltd. | G71: GCW26SE19AB | H71: 7132988 | I71: 75 | J71: Standard Carton-Singles | K71: BC-Flute | L71: D3 | M71: {=IF(L71="",0,_xlfn.SWITCH(L71,"A1",495,"A2",495,"A3",495,"Custom",0,595))} -> 595 | N71: {=IF(L71="",0,_xlfn.SWITCH(L71,"C1",325,"C2",325,"C3",325,"D1",380,"D2",380,"D3",380,"Custom",0,285))} -> 380 | O71: =IF(L71="",0,_xlfn.SWITCH(L71,"A1",375,"B1",375,"C1",375,"D1",375,"A2",310,"B2",310,"C2",310,"D2",310,"Custom",0,260)) -> 260 | P71: =IFERROR(IF(OR(M71=0,N71=0),0,(M71+N71)*2+11),0) -> 1961 | Q71: =IFERROR(IF(OR(N71=0,O71=0),0,(N71+O71)-16),0) -> 624 | R71: =P71*Q71/1000000 -> 1.223664 | S71: =IFERROR(VLOOKUP(L71,'Carton Sizes Chart'!$A$4:$E$15,5,FALSE),0) -> 1.18 | T71: =S71 -> 1.18 | U71: =I71*T71 -> 88.5 | V71: =((T71*I71)-W71)*4% -> 3.363 | W71: =S71*I71*5% -> 4.425
A72: 46246 | B72: 46247 | D72: KESKAN FZC | E72: Desh Garments Ltd. | F72: Uniglory Packaging Industries Ltd. | G72: GCW26SH02AB | H72: 7134301 | I72: 15 | J72: Standard Carton-Singles | K72: BC-Flute | L72: C3 | M72: {=IF(L72="",0,_xlfn.SWITCH(L72,"A1",495,"A2",495,"A3",495,"Custom",0,595))} -> 595 | N72: {=IF(L72="",0,_xlfn.SWITCH(L72,"C1",325,"C2",325,"C3",325,"D1",380,"D2",380,"D3",380,"Custom",0,285))} -> 325 | O72: =IF(L72="",0,_xlfn.SWITCH(L72,"A1",375,"B1",375,"C1",375,"D1",375,"A2",310,"B2",310,"C2",310,"D2",310,"Custom",0,260)) -> 260 | P72: =IFERROR(IF(OR(M72=0,N72=0),0,(M72+N72)*2+11),0) -> 1851 | Q72: =IFERROR(IF(OR(N72=0,O72=0),0,(N72+O72)-16),0) -> 569 | R72: =P72*Q72/1000000 -> 1.053219 | S72: =IFERROR(VLOOKUP(L72,'Carton Sizes Chart'!$A$4:$E$15,5,FALSE),0) -> 1.02 | T72: =S72 -> 1.02 | U72: =I72*T72 -> 15.3 | V72: =((T72*I72)-W72)*4% -> 0.5814 | W72: =S72*I72*5% -> 0.765
A73: 46246 | B73: 46247 | D73: KESKAN FZC | E73: Desh Garments Ltd. | F73: Uniglory Packaging Industries Ltd. | G73: GCW26SH02AB | H73: 7134301 | I73: 62 | J73: Standard Carton-Singles | K73: BC-Flute | L73: D3 | M73: {=IF(L73="",0,_xlfn.SWITCH(L73,"A1",495,"A2",495,"A3",495,"Custom",0,595))} -> 595 | N73: {=IF(L73="",0,_xlfn.SWITCH(L73,"C1",325,"C2",325,"C3",325,"D1",380,"D2",380,"D3",380,"Custom",0,285))} -> 380 | O73: =IF(L73="",0,_xlfn.SWITCH(L73,"A1",375,"B1",375,"C1",375,"D1",375,"A2",310,"B2",310,"C2",310,"D2",310,"Custom",0,260)) -> 260 | P73: =IFERROR(IF(OR(M73=0,N73=0),0,(M73+N73)*2+11),0) -> 1961 | Q73: =IFERROR(IF(OR(N73=0,O73=0),0,(N73+O73)-16),0) -> 624 | R73: =P73*Q73/1000000 -> 1.223664 | S73: =IFERROR(VLOOKUP(L73,'Carton Sizes Chart'!$A$4:$E$15,5,FALSE),0) -> 1.18 | T73: =S73 -> 1.18 | U73: =I73*T73 -> 73.16 | V73: =((T73*I73)-W73)*4% -> 2.78008 | W73: =S73*I73*5% -> 3.658
A74: 46247 | B74: 46250 | D74: Design ARC Asia | E74: Confidance Knitwear Ltd. | F74: Uniglory Packaging Industries Ltd. | G74: TDS02 | H74: 7135089 | I74: 15 | J74: Standard Carton-Singles | K74: BC-Flute | L74: C2 | M74: {=IF(L74="",0,_xlfn.SWITCH(L74,"A1",495,"A2",495,"A3",495,"Custom",0,595))} -> 595 | N74: {=IF(L74="",0,_xlfn.SWITCH(L74,"C1",325,"C2",325,"C3",325,"D1",380,"D2",380,"D3",380,"Custom",0,285))} -> 325 | O74: =IF(L74="",0,_xlfn.SWITCH(L74,"A1",375,"B1",375,"C1",375,"D1",375,"A2",310,"B2",310,"C2",310,"D2",310,"Custom",0,260)) -> 310 | P74: =IFERROR(IF(OR(M74=0,N74=0),0,(M74+N74)*2+11),0) -> 1851 | Q74: =IFERROR(IF(OR(N74=0,O74=0),0,(N74+O74)-16),0) -> 619 | R74: =P74*Q74/1000000 -> 1.145769 | S74: =IFERROR(VLOOKUP(L74,'Carton Sizes Chart'!$A$4:$E$15,5,FALSE),0) -> 1.1 | T74: =S74 -> 1.1 | U74: =I74*T74 -> 16.5 | V74: =((T74*I74)-W74)*4% -> 0.627 | W74: =S74*I74*5% -> 0.825
A75: 46247 | B75: 46250 | D75: Design ARC Asia | E75: Confidance Knitwear Ltd. | F75: Uniglory Packaging Industries Ltd. | G75: TDS02 | H75: 7135089 | I75: 47 | J75: Standard Carton-Singles | K75: BC-Flute | L75: C1 | M75: {=IF(L75="",0,_xlfn.SWITCH(L75,"A1",495,"A2",495,"A3",495,"Custom",0,595))} -> 595 | N75: {=IF(L75="",0,_xlfn.SWITCH(L75,"C1",325,"C2",325,"C3",325,"D1",380,"D2",380,"D3",380,"Custom",0,285))} -> 325 | O75: =IF(L75="",0,_xlfn.SWITCH(L75,"A1",375,"B1",375,"C1",375,"D1",375,"A2",310,"B2",310,"C2",310,"D2",310,"Custom",0,260)) -> 375 | P75: =IFERROR(IF(OR(M75=0,N75=0),0,(M75+N75)*2+11),0) -> 1851 | Q75: =IFERROR(IF(OR(N75=0,O75=0),0,(N75+O75)-16),0) -> 684 | R75: =P75*Q75/1000000 -> 1.266084 | S75: =IFERROR(VLOOKUP(L75,'Carton Sizes Chart'!$A$4:$E$15,5,FALSE),0) -> 1.22 | T75: =S75 -> 1.22 | U75: =I75*T75 -> 57.34 | V75: =((T75*I75)-W75)*4% -> 2.17892 | W75: =S75*I75*5% -> 2.867
A76: 46247 | B76: 46250 | D76: Design ARC Asia | E76: Confidance Knitwear Ltd. | F76: Uniglory Packaging Industries Ltd. | G76: TDS02 | H76: 7135089 | I76: 31 | J76: Standard Carton-Singles | K76: BC-Flute | L76: D1 | M76: {=IF(L76="",0,_xlfn.SWITCH(L76,"A1",495,"A2",495,"A3",495,"Custom",0,595))} -> 595 | N76: {=IF(L76="",0,_xlfn.SWITCH(L76,"C1",325,"C2",325,"C3",325,"D1",380,"D2",380,"D3",380,"Custom",0,285))} -> 380 | O76: =IF(L76="",0,_xlfn.SWITCH(L76,"A1",375,"B1",375,"C1",375,"D1",375,"A2",310,"B2",310,"C2",310,"D2",310,"Custom",0,260)) -> 375 | P76: =IFERROR(IF(OR(M76=0,N76=0),0,(M76+N76)*2+11),0) -> 1961 | Q76: =IFERROR(IF(OR(N76=0,O76=0),0,(N76+O76)-16),0) -> 739 | R76: =P76*Q76/1000000 -> 1.449179 | S76: =IFERROR(VLOOKUP(L76,'Carton Sizes Chart'!$A$4:$E$15,5,FALSE),0) -> 1.39 | T76: =S76 -> 1.39 | U76: =I76*T76 -> 43.09 | V76: =((T76*I76)-W76)*4% -> 1.63742 | W76: =S76*I76*5% -> 2.1545
A77: 46247 | B77: 46249 | D77: Design ARC Asia | E77: Confidance Knitwear Ltd. | F77: Uniglory Packaging Industries Ltd. | G77: BTS02 | H77: 7135275 | I77: 41 | J77: Standard Carton-Singles | K77: BC-Flute | L77: C1 | M77: {=IF(L77="",0,_xlfn.SWITCH(L77,"A1",495,"A2",495,"A3",495,"Custom",0,595))} -> 595 | N77: {=IF(L77="",0,_xlfn.SWITCH(L77,"C1",325,"C2",325,"C3",325,"D1",380,"D2",380,"D3",380,"Custom",0,285))} -> 325 | O77: =IF(L77="",0,_xlfn.SWITCH(L77,"A1",375,"B1",375,"C1",375,"D1",375,"A2",310,"B2",310,"C2",310,"D2",310,"Custom",0,260)) -> 375 | P77: =IFERROR(IF(OR(M77=0,N77=0),0,(M77+N77)*2+11),0) -> 1851 | Q77: =IFERROR(IF(OR(N77=0,O77=0),0,(N77+O77)-16),0) -> 684 | R77: =P77*Q77/1000000 -> 1.266084 | S77: =IFERROR(VLOOKUP(L77,'Carton Sizes Chart'!$A$4:$E$15,5,FALSE),0) -> 1.22 | T77: =S77 -> 1.22 | U77: =I77*T77 -> 50.02 | V77: =((T77*I77)-W77)*4% -> 1.90076 | W77: =S77*I77*5% -> 2.501
A78: 46247 | B78: 46249 | D78: Design ARC Asia | E78: Confidance Knitwear Ltd. | F78: Uniglory Packaging Industries Ltd. | G78: BTS02 | H78: 7135275 | I78: 17 | J78: Standard Carton-Singles | K78: BC-Flute | L78: D1 | M78: {=IF(L78="",0,_xlfn.SWITCH(L78,"A1",495,"A2",495,"A3",495,"Custom",0,595))} -> 595 | N78: {=IF(L78="",0,_xlfn.SWITCH(L78,"C1",325,"C2",325,"C3",325,"D1",380,"D2",380,"D3",380,"Custom",0,285))} -> 380 | O78: =IF(L78="",0,_xlfn.SWITCH(L78,"A1",375,"B1",375,"C1",375,"D1",375,"A2",310,"B2",310,"C2",310,"D2",310,"Custom",0,260)) -> 375 | P78: =IFERROR(IF(OR(M78=0,N78=0),0,(M78+N78)*2+11),0) -> 1961 | Q78: =IFERROR(IF(OR(N78=0,O78=0),0,(N78+O78)-16),0) -> 739 | R78: =P78*Q78/1000000 -> 1.449179 | S78: =IFERROR(VLOOKUP(L78,'Carton Sizes Chart'!$A$4:$E$15,5,FALSE),0) -> 1.39 | T78: =S78 -> 1.39 | U78: =I78*T78 -> 23.63 | V78: =((T78*I78)-W78)*4% -> 0.89794 | W78: =S78*I78*5% -> 1.1815
A79: 46249 | B79: 46254 | D79: Design ARC Asia | E79: Confidance Knitwear Ltd. | F79: Uniglory Packaging Industries Ltd. | G79: BTS02 | H79: 7136111 | I79: 70 | J79: Standard Carton-Singles | K79: BC-Flute | L79: C1 | M79: {=IF(L79="",0,_xlfn.SWITCH(L79,"A1",495,"A2",495,"A3",495,"Custom",0,595))} -> 595 | N79: {=IF(L79="",0,_xlfn.SWITCH(L79,"C1",325,"C2",325,"C3",325,"D1",380,"D2",380,"D3",380,"Custom",0,285))} -> 325 | O79: =IF(L79="",0,_xlfn.SWITCH(L79,"A1",375,"B1",375,"C1",375,"D1",375,"A2",310,"B2",310,"C2",310,"D2",310,"Custom",0,260)) -> 375 | P79: =IFERROR(IF(OR(M79=0,N79=0),0,(M79+N79)*2+11),0) -> 1851 | Q79: =IFERROR(IF(OR(N79=0,O79=0),0,(N79+O79)-16),0) -> 684 | R79: =P79*Q79/1000000 -> 1.266084 | S79: =IFERROR(VLOOKUP(L79,'Carton Sizes Chart'!$A$4:$E$15,5,FALSE),0) -> 1.22 | T79: =S79 -> 1.22 | U79: =I79*T79 -> 85.4 | V79: =((T79*I79)-W79)*4% -> 3.2452 | W79: =S79*I79*5% -> 4.27
A80: 46249 | B80: 46254 | D80: Design ARC Asia | E80: Confidance Knitwear Ltd. | F80: Uniglory Packaging Industries Ltd. | G80: BTS02 | H80: 7136111 | I80: 27 | J80: Standard Carton-Singles | K80: BC-Flute | L80: D1 | M80: {=IF(L80="",0,_xlfn.SWITCH(L80,"A1",495,"A2",495,"A3",495,"Custom",0,595))} -> 595 | N80: {=IF(L80="",0,_xlfn.SWITCH(L80,"C1",325,"C2",325,"C3",325,"D1",380,"D2",380,"D3",380,"Custom",0,285))} -> 380 | O80: =IF(L80="",0,_xlfn.SWITCH(L80,"A1",375,"B1",375,"C1",375,"D1",375,"A2",310,"B2",310,"C2",310,"D2",310,"Custom",0,260)) -> 375 | P80: =IFERROR(IF(OR(M80=0,N80=0),0,(M80+N80)*2+11),0) -> 1961 | Q80: =IFERROR(IF(OR(N80=0,O80=0),0,(N80+O80)-16),0) -> 739 | R80: =P80*Q80/1000000 -> 1.449179 | S80: =IFERROR(VLOOKUP(L80,'Carton Sizes Chart'!$A$4:$E$15,5,FALSE),0) -> 1.39 | T80: =S80 -> 1.39 | U80: =I80*T80 -> 37.53 | V80: =((T80*I80)-W80)*4% -> 1.42614 | W80: =S80*I80*5% -> 1.8765
A81: 46249 | B81: 46254 | D81: Design ARC Asia | E81: Confidance Knitwear Ltd. | F81: Uniglory Packaging Industries Ltd. | G81: TS02 | H81: 7136184 | I81: 16 | J81: Standard Carton-Singles | K81: BC-Flute | L81: C1 | M81: {=IF(L81="",0,_xlfn.SWITCH(L81,"A1",495,"A2",495,"A3",495,"Custom",0,595))} -> 595 | N81: {=IF(L81="",0,_xlfn.SWITCH(L81,"C1",325,"C2",325,"C3",325,"D1",380,"D2",380,"D3",380,"Custom",0,285))} -> 325 | O81: =IF(L81="",0,_xlfn.SWITCH(L81,"A1",375,"B1",375,"C1",375,"D1",375,"A2",310,"B2",310,"C2",310,"D2",310,"Custom",0,260)) -> 375 | P81: =IFERROR(IF(OR(M81=0,N81=0),0,(M81+N81)*2+11),0) -> 1851 | Q81: =IFERROR(IF(OR(N81=0,O81=0),0,(N81+O81)-16),0) -> 684 | R81: =P81*Q81/1000000 -> 1.266084 | S81: =IFERROR(VLOOKUP(L81,'Carton Sizes Chart'!$A$4:$E$15,5,FALSE),0) -> 1.22 | T81: =S81 -> 1.22 | U81: =I81*T81 -> 19.52 | V81: =((T81*I81)-W81)*4% -> 0.74176 | W81: =S81*I81*5% -> 0.976
A82: 46249 | B82: 46254 | D82: Design ARC Asia | E82: Confidance Knitwear Ltd. | F82: Uniglory Packaging Industries Ltd. | G82: TS02 | H82: 7136184 | I82: 9 | J82: Standard Carton-Singles | K82: BC-Flute | L82: D1 | M82: {=IF(L82="",0,_xlfn.SWITCH(L82,"A1",495,"A2",495,"A3",495,"Custom",0,595))} -> 595 | N82: {=IF(L82="",0,_xlfn.SWITCH(L82,"C1",325,"C2",325,"C3",325,"D1",380,"D2",380,"D3",380,"Custom",0,285))} -> 380 | O82: =IF(L82="",0,_xlfn.SWITCH(L82,"A1",375,"B1",375,"C1",375,"D1",375,"A2",310,"B2",310,"C2",310,"D2",310,"Custom",0,260)) -> 375 | P82: =IFERROR(IF(OR(M82=0,N82=0),0,(M82+N82)*2+11),0) -> 1961 | Q82: =IFERROR(IF(OR(N82=0,O82=0),0,(N82+O82)-16),0) -> 739 | R82: =P82*Q82/1000000 -> 1.449179 | S82: =IFERROR(VLOOKUP(L82,'Carton Sizes Chart'!$A$4:$E$15,5,FALSE),0) -> 1.39 | T82: =S82 -> 1.39 | U82: =I82*T82 -> 12.51 | V82: =((T82*I82)-W82)*4% -> 0.47538 | W82: =S82*I82*5% -> 0.6255
... A89: 46259 | B89: 46263 | D89: Design ARC Asia | E89: Confidance Knitwear Ltd. | F89: Uniglory Packaging Industries Ltd. | G89: PT02 | H89: 7142671 | I89: 29 | J89: Standard Carton-Singles | K89: BC-Flute | L89: C1 | M89: {=IF(L89="",0,_xlfn.SWITCH(L89,"A1",495,"A2",495,"A3",495,"Custom",0,595))} -> 595 | N89: {=IF(L89="",0,_xlfn.SWITCH(L89,"C1",325,"C2",325,"C3",325,"D1",380,"D2",380,"D3",380,"Custom",0,285))} -> 325 | O89: =IF(L89="",0,_xlfn.SWITCH(L89,"A1",375,"B1",375,"C1",375,"D1",375,"A2",310,"B2",310,"C2",310,"D2",310,"Custom",0,260)) -> 375 | P89: =IFERROR(IF(OR(M89=0,N89=0),0,(M89+N89)*2+11),0) -> 1851 | Q89: =IFERROR(IF(OR(N89=0,O89=0),0,(N89+O89)-16),0) -> 684 | R89: =P89*Q89/1000000 -> 1.266084 | S89: =IFERROR(VLOOKUP(L89,'Carton Sizes Chart'!$A$4:$E$15,5,FALSE),0) -> 1.22 | T89: =S89 -> 1.22 | U89: =I89*T89 -> 35.38 | V89: =((T89*I89)-W89)*4% -> 1.34444 | W89: =S89*I89*5% -> 1.769
A90: 46261 | B90: 46261 | D90: Crown Exclusive Wears Ltd. | E90: Crown Exclusive Wears Ltd. | F90: Uniglory Packaging Industries Ltd. | G90: CHW26KN013 | H90: 7143645 | I90: 12 | J90: Standard Carton-Singles | K90: BC-Flute | L90: Custom | M90: 550 | N90: 420 | O90: 350 | P90: =IFERROR(IF(OR(M90=0,N90=0),0,(M90+N90)*2+11),0) -> 1951 | Q90: =IFERROR(IF(OR(N90=0,O90=0),0,(N90+O90)-16),0) -> 754 | R90: =P90*Q90/1000000 -> 1.471054 | S90: =IF(L90="Custom", R90*'[1]RFQ_Matalan Carton'!$M$40, IFERROR(VLOOKUP(L90,'[1]Carton Sizes Chart'!$A$4:$E$15,5,FALSE),0)) -> 1.4122118 | T90: =S90 -> 1.4122118 | U90: =I90*T90 -> 16.946542 | V90: =((T90*I90)-W90)*4% -> 0.6439686 | W90: =S90*I90*5% -> 0.8473271
J91: Standard Carton-Singles | K91: BC-Flute | L91: Custom | M91: {=IF(L91="",0,_xlfn.SWITCH(L91,"A1",495,"A2",495,"A3",495,"Custom",0,595))} -> 0 | N91: {=IF(L91="",0,_xlfn.SWITCH(L91,"C1",325,"C2",325,"C3",325,"D1",380,"D2",380,"D3",380,"Custom",0,285))} -> 0 | O91: =IF(L91="",0,_xlfn.SWITCH(L91,"A1",375,"B1",375,"C1",375,"D1",375,"A2",310,"B2",310,"C2",310,"D2",310,"Custom",0,260)) -> 0 | P91: =IFERROR(IF(OR(M91=0,N91=0),0,(M91+N91)*2+11),0) -> 0 | Q91: =IFERROR(IF(OR(N91=0,O91=0),0,(N91+O91)-16),0) -> 0 | R91: =P91*Q91/1000000 -> 0 | S91: =IFERROR(VLOOKUP(L91,'Carton Sizes Chart'!$A$4:$E$15,5,FALSE),0) -> 0 | T91: =S91 -> 0 | U91: =I91*T91 -> 0 | V91: =((T91*I91)-W91)*4% -> 0 | W91: =S91*I91*5% -> 0
J92: Standard Carton-Singles | K92: BC-Flute | L92: Custom | M92: {=IF(L92="",0,_xlfn.SWITCH(L92,"A1",495,"A2",495,"A3",495,"Custom",0,595))} -> 0 | N92: {=IF(L92="",0,_xlfn.SWITCH(L92,"C1",325,"C2",325,"C3",325,"D1",380,"D2",380,"D3",380,"Custom",0,285))} -> 0 | O92: =IF(L92="",0,_xlfn.SWITCH(L92,"A1",375,"B1",375,"C1",375,"D1",375,"A2",310,"B2",310,"C2",310,"D2",310,"Custom",0,260)) -> 0 | P92: =IFERROR(IF(OR(M92=0,N92=0),0,(M92+N92)*2+11),0) -> 0 | Q92: =IFERROR(IF(OR(N92=0,O92=0),0,(N92+O92)-16),0) -> 0 | R92: =P92*Q92/1000000 -> 0 | S92: =IFERROR(VLOOKUP(L92,'Carton Sizes Chart'!$A$4:$E$15,5,FALSE),0) -> 0 | T92: =S92 -> 0 | U92: =I92*T92 -> 0 | V92: =((T92*I92)-W92)*4% -> 0 | W92: =S92*I92*5% -> 0
J93: Standard Carton-Singles | K93: BC-Flute | L93: Custom | M93: {=IF(L93="",0,_xlfn.SWITCH(L93,"A1",495,"A2",495,"A3",495,"Custom",0,595))} -> 0 | N93: {=IF(L93="",0,_xlfn.SWITCH(L93,"C1",325,"C2",325,"C3",325,"D1",380,"D2",380,"D3",380,"Custom",0,285))} -> 0 | O93: =IF(L93="",0,_xlfn.SWITCH(L93,"A1",375,"B1",375,"C1",375,"D1",375,"A2",310,"B2",310,"C2",310,"D2",310,"Custom",0,260)) -> 0 | P93: =IFERROR(IF(OR(M93=0,N93=0),0,(M93+N93)*2+11),0) -> 0 | Q93: =IFERROR(IF(OR(N93=0,O93=0),0,(N93+O93)-16),0) -> 0 | R93: =P93*Q93/1000000 -> 0 | S93: =IFERROR(VLOOKUP(L93,'Carton Sizes Chart'!$A$4:$E$15,5,FALSE),0) -> 0 | T93: =S93 -> 0 | U93: =I93*T93 -> 0 | V93: =((T93*I93)-W93)*4% -> 0 | W93: =S93*I93*5% -> 0
J94: Standard Carton-Singles | K94: BC-Flute | L94: Custom | M94: {=IF(L94="",0,_xlfn.SWITCH(L94,"A1",495,"A2",495,"A3",495,"Custom",0,595))} -> 0 | N94: {=IF(L94="",0,_xlfn.SWITCH(L94,"C1",325,"C2",325,"C3",325,"D1",380,"D2",380,"D3",380,"Custom",0,285))} -> 0 | O94: =IF(L94="",0,_xlfn.SWITCH(L94,"A1",375,"B1",375,"C1",375,"D1",375,"A2",310,"B2",310,"C2",310,"D2",310,"Custom",0,260)) -> 0 | P94: =IFERROR(IF(OR(M94=0,N94=0),0,(M94+N94)*2+11),0) -> 0 | Q94: =IFERROR(IF(OR(N94=0,O94=0),0,(N94+O94)-16),0) -> 0 | R94: =P94*Q94/1000000 -> 0 | S94: =IFERROR(VLOOKUP(L94,'Carton Sizes Chart'!$A$4:$E$15,5,FALSE),0) -> 0 | T94: =S94 -> 0 | U94: =I94*T94 -> 0 | V94: =((T94*I94)-W94)*4% -> 0 | W94: =S94*I94*5% -> 0
J95: Standard Carton-Singles | K95: BC-Flute | L95: Custom | M95: {=IF(L95="",0,_xlfn.SWITCH(L95,"A1",495,"A2",495,"A3",495,"Custom",0,595))} -> 0 | N95: {=IF(L95="",0,_xlfn.SWITCH(L95,"C1",325,"C2",325,"C3",325,"D1",380,"D2",380,"D3",380,"Custom",0,285))} -> 0 | O95: =IF(L95="",0,_xlfn.SWITCH(L95,"A1",375,"B1",375,"C1",375,"D1",375,"A2",310,"B2",310,"C2",310,"D2",310,"Custom",0,260)) -> 0 | P95: =IFERROR(IF(OR(M95=0,N95=0),0,(M95+N95)*2+11),0) -> 0 | Q95: =IFERROR(IF(OR(N95=0,O95=0),0,(N95+O95)-16),0) -> 0 | R95: =P95*Q95/1000000 -> 0 | S95: =IFERROR(VLOOKUP(L95,'Carton Sizes Chart'!$A$4:$E$15,5,FALSE),0) -> 0 | T95: =S95 -> 0 | U95: =I95*T95 -> 0 | V95: =((T95*I95)-W95)*4% -> 0 | W95: =S95*I95*5% -> 0
J96: Standard Carton-Singles | K96: BC-Flute | L96: Custom | M96: {=IF(L96="",0,_xlfn.SWITCH(L96,"A1",495,"A2",495,"A3",495,"Custom",0,595))} -> 0 | N96: {=IF(L96="",0,_xlfn.SWITCH(L96,"C1",325,"C2",325,"C3",325,"D1",380,"D2",380,"D3",380,"Custom",0,285))} -> 0 | O96: =IF(L96="",0,_xlfn.SWITCH(L96,"A1",375,"B1",375,"C1",375,"D1",375,"A2",310,"B2",310,"C2",310,"D2",310,"Custom",0,260)) -> 0 | P96: =IFERROR(IF(OR(M96=0,N96=0),0,(M96+N96)*2+11),0) -> 0 | Q96: =IFERROR(IF(OR(N96=0,O96=0),0,(N96+O96)-16),0) -> 0 | R96: =P96*Q96/1000000 -> 0 | S96: =IFERROR(VLOOKUP(L96,'Carton Sizes Chart'!$A$4:$E$15,5,FALSE),0) -> 0 | T96: =S96 -> 0 | U96: =I96*T96 -> 0 | V96: =((T96*I96)-W96)*4% -> 0 | W96: =S96*I96*5% -> 0
J97: Standard Carton-Singles | K97: BC-Flute | L97: Custom | M97: {=IF(L97="",0,_xlfn.SWITCH(L97,"A1",495,"A2",495,"A3",495,"Custom",0,595))} -> 0 | N97: {=IF(L97="",0,_xlfn.SWITCH(L97,"C1",325,"C2",325,"C3",325,"D1",380,"D2",380,"D3",380,"Custom",0,285))} -> 0 | O97: =IF(L97="",0,_xlfn.SWITCH(L97,"A1",375,"B1",375,"C1",375,"D1",375,"A2",310,"B2",310,"C2",310,"D2",310,"Custom",0,260)) -> 0 | P97: =IFERROR(IF(OR(M97=0,N97=0),0,(M97+N97)*2+11),0) -> 0 | Q97: =IFERROR(IF(OR(N97=0,O97=0),0,(N97+O97)-16),0) -> 0 | R97: =P97*Q97/1000000 -> 0 | S97: =IFERROR(VLOOKUP(L97,'Carton Sizes Chart'!$A$4:$E$15,5,FALSE),0) -> 0 | T97: =S97 -> 0 | U97: =I97*T97 -> 0 | V97: =((T97*I97)-W97)*4% -> 0 | W97: =S97*I97*5% -> 0
J98: Standard Carton-Singles | K98: BC-Flute | L98: Custom | M98: {=IF(L98="",0,_xlfn.SWITCH(L98,"A1",495,"A2",495,"A3",495,"Custom",0,595))} -> 0 | N98: {=IF(L98="",0,_xlfn.SWITCH(L98,"C1",325,"C2",325,"C3",325,"D1",380,"D2",380,"D3",380,"Custom",0,285))} -> 0 | O98: =IF(L98="",0,_xlfn.SWITCH(L98,"A1",375,"B1",375,"C1",375,"D1",375,"A2",310,"B2",310,"C2",310,"D2",310,"Custom",0,260)) -> 0 | P98: =IFERROR(IF(OR(M98=0,N98=0),0,(M98+N98)*2+11),0) -> 0 | Q98: =IFERROR(IF(OR(N98=0,O98=0),0,(N98+O98)-16),0) -> 0 | R98: =P98*Q98/1000000 -> 0 | S98: =IFERROR(VLOOKUP(L98,'Carton Sizes Chart'!$A$4:$E$15,5,FALSE),0) -> 0 | T98: =S98 -> 0 | U98: =I98*T98 -> 0 | V98: =((T98*I98)-W98)*4% -> 0 | W98: =S98*I98*5% -> 0 | X98: 20pcs, 29.10
J99: Standard Carton-Singles | K99: BC-Flute | L99: Custom | M99: {=IF(L99="",0,_xlfn.SWITCH(L99,"A1",495,"A2",495,"A3",495,"Custom",0,595))} -> 0 | N99: {=IF(L99="",0,_xlfn.SWITCH(L99,"C1",325,"C2",325,"C3",325,"D1",380,"D2",380,"D3",380,"Custom",0,285))} -> 0 | O99: =IF(L99="",0,_xlfn.SWITCH(L99,"A1",375,"B1",375,"C1",375,"D1",375,"A2",310,"B2",310,"C2",310,"D2",310,"Custom",0,260)) -> 0 | P99: =IFERROR(IF(OR(M99=0,N99=0),0,(M99+N99)*2+11),0) -> 0 | Q99: =IFERROR(IF(OR(N99=0,O99=0),0,(N99+O99)-16),0) -> 0 | R99: =P99*Q99/1000000 -> 0 | S99: =IFERROR(VLOOKUP(L99,'Carton Sizes Chart'!$A$4:$E$15,5,FALSE),0) -> 0 | T99: =S99 -> 0 | U99: =I99*T99 -> 0 | V99: =((T99*I99)-W99)*4% -> 0 | W99: =S99*I99*5% -> 0
J100: Standard Carton-Singles | K100: BC-Flute | L100: Custom | M100: {=IF(L100="",0,_xlfn.SWITCH(L100,"A1",495,"A2",495,"A3",495,"Custom",0,595))} -> 0 | N100: {=IF(L100="",0,_xlfn.SWITCH(L100,"C1",325,"C2",325,"C3",325,"D1",380,"D2",380,"D3",380,"Custom",0,285))} -> 0 | O100: =IF(L100="",0,_xlfn.SWITCH(L100,"A1",375,"B1",375,"C1",375,"D1",375,"A2",310,"B2",310,"C2",310,"D2",310,"Custom",0,260)) -> 0 | P100: =IFERROR(IF(OR(M100=0,N100=0),0,(M100+N100)*2+11),0) -> 0 | Q100: =IFERROR(IF(OR(N100=0,O100=0),0,(N100+O100)-16),0) -> 0 | R100: =P100*Q100/1000000 -> 0 | S100: =IFERROR(VLOOKUP(L100,'Carton Sizes Chart'!$A$4:$E$15,5,FALSE),0) -> 0 | T100: =S100 -> 0 | U100: =I100*T100 -> 0 | V100: =((T100*I100)-W100)*4% -> 0 | W100: =S100*I100*5% -> 0
J101: Standard Carton-Singles | K101: BC-Flute | L101: Custom | M101: {=IF(L101="",0,_xlfn.SWITCH(L101,"A1",495,"A2",495,"A3",495,"Custom",0,595))} -> 0 | N101: {=IF(L101="",0,_xlfn.SWITCH(L101,"C1",325,"C2",325,"C3",325,"D1",380,"D2",380,"D3",380,"Custom",0,285))} -> 0 | O101: =IF(L101="",0,_xlfn.SWITCH(L101,"A1",375,"B1",375,"C1",375,"D1",375,"A2",310,"B2",310,"C2",310,"D2",310,"Custom",0,260)) -> 0 | P101: =IFERROR(IF(OR(M101=0,N101=0),0,(M101+N101)*2+11),0) -> 0 | Q101: =IFERROR(IF(OR(N101=0,O101=0),0,(N101+O101)-16),0) -> 0 | R101: =P101*Q101/1000000 -> 0 | S101: =IFERROR(VLOOKUP(L101,'Carton Sizes Chart'!$A$4:$E$15,5,FALSE),0) -> 0 | T101: =S101 -> 0 | U101: =I101*T101 -> 0 | V101: =((T101*I101)-W101)*4% -> 0 | W101: =S101*I101*5% -> 0
J102: Standard Carton-Singles | K102: BC-Flute | L102: Custom | M102: {=IF(L102="",0,_xlfn.SWITCH(L102,"A1",495,"A2",495,"A3",495,"Custom",0,595))} -> 0 | N102: {=IF(L102="",0,_xlfn.SWITCH(L102,"C1",325,"C2",325,"C3",325,"D1",380,"D2",380,"D3",380,"Custom",0,285))} -> 0 | O102: =IF(L102="",0,_xlfn.SWITCH(L102,"A1",375,"B1",375,"C1",375,"D1",375,"A2",310,"B2",310,"C2",310,"D2",310,"Custom",0,260)) -> 0 | P102: =IFERROR(IF(OR(M102=0,N102=0),0,(M102+N102)*2+11),0) -> 0 | Q102: =IFERROR(IF(OR(N102=0,O102=0),0,(N102+O102)-16),0) -> 0 | R102: =P102*Q102/1000000 -> 0 | S102: =IFERROR(VLOOKUP(L102,'Carton Sizes Chart'!$A$4:$E$15,5,FALSE),0) -> 0 | T102: =S102 -> 0 | U102: =I102*T102 -> 0 | V102: =((T102*I102)-W102)*4% -> 0 | W102: =S102*I102*5% -> 0
J103: Standard Carton-Singles | K103: BC-Flute | L103: Custom | M103: {=IF(L103="",0,_xlfn.SWITCH(L103,"A1",495,"A2",495,"A3",495,"Custom",0,595))} -> 0 | N103: {=IF(L103="",0,_xlfn.SWITCH(L103,"C1",325,"C2",325,"C3",325,"D1",380,"D2",380,"D3",380,"Custom",0,285))} -> 0 | O103: =IF(L103="",0,_xlfn.SWITCH(L103,"A1",375,"B1",375,"C1",375,"D1",375,"A2",310,"B2",310,"C2",310,"D2",310,"Custom",0,260)) -> 0 | P103: =IFERROR(IF(OR(M103=0,N103=0),0,(M103+N103)*2+11),0) -> 0 | Q103: =IFERROR(IF(OR(N103=0,O103=0),0,(N103+O103)-16),0) -> 0 | R103: =P103*Q103/1000000 -> 0 | S103: =IFERROR(VLOOKUP(L103,'Carton Sizes Chart'!$A$4:$E$15,5,FALSE),0) -> 0 | T103: =S103 -> 0 | U103: =I103*T103 -> 0 | V103: =((T103*I103)-W103)*4% -> 0 | W103: =S103*I103*5% -> 0
J104: Standard Carton-Singles | K104: BC-Flute | L104: Custom | M104: {=IF(L104="",0,_xlfn.SWITCH(L104,"A1",495,"A2",495,"A3",495,"Custom",0,595))} -> 0 | N104: {=IF(L104="",0,_xlfn.SWITCH(L104,"C1",325,"C2",325,"C3",325,"D1",380,"D2",380,"D3",380,"Custom",0,285))} -> 0 | O104: =IF(L104="",0,_xlfn.SWITCH(L104,"A1",375,"B1",375,"C1",375,"D1",375,"A2",310,"B2",310,"C2",310,"D2",310,"Custom",0,260)) -> 0 | P104: =IFERROR(IF(OR(M104=0,N104=0),0,(M104+N104)*2+11),0) -> 0 | Q104: =IFERROR(IF(OR(N104=0,O104=0),0,(N104+O104)-16),0) -> 0 | R104: =P104*Q104/1000000 -> 0 | S104: =IFERROR(VLOOKUP(L104,'Carton Sizes Chart'!$A$4:$E$15,5,FALSE),0) -> 0 | T104: =S104 -> 0 | U104: =I104*T104 -> 0 | V104: =((T104*I104)-W104)*4% -> 0 | W104: =S104*I104*5% -> 0
J105: Standard Carton-Singles | K105: BC-Flute | L105: Custom | M105: {=IF(L105="",0,_xlfn.SWITCH(L105,"A1",495,"A2",495,"A3",495,"Custom",0,595))} -> 0 | N105: {=IF(L105="",0,_xlfn.SWITCH(L105,"C1",325,"C2",325,"C3",325,"D1",380,"D2",380,"D3",380,"Custom",0,285))} -> 0 | O105: =IF(L105="",0,_xlfn.SWITCH(L105,"A1",375,"B1",375,"C1",375,"D1",375,"A2",310,"B2",310,"C2",310,"D2",310,"Custom",0,260)) -> 0 | P105: =IFERROR(IF(OR(M105=0,N105=0),0,(M105+N105)*2+11),0) -> 0 | Q105: =IFERROR(IF(OR(N105=0,O105=0),0,(N105+O105)-16),0) -> 0 | R105: =P105*Q105/1000000 -> 0 | S105: =IFERROR(VLOOKUP(L105,'Carton Sizes Chart'!$A$4:$E$15,5,FALSE),0) -> 0 | T105: =S105 -> 0 | U105: =I105*T105 -> 0 | V105: =((T105*I105)-W105)*4% -> 0 | W105: =S105*I105*5% -> 0
J106: Standard Carton-Singles | K106: BC-Flute | L106: Custom | M106: {=IF(L106="",0,_xlfn.SWITCH(L106,"A1",495,"A2",495,"A3",495,"Custom",0,595))} -> 0 | N106: {=IF(L106="",0,_xlfn.SWITCH(L106,"C1",325,"C2",325,"C3",325,"D1",380,"D2",380,"D3",380,"Custom",0,285))} -> 0 | O106: =IF(L106="",0,_xlfn.SWITCH(L106,"A1",375,"B1",375,"C1",375,"D1",375,"A2",310,"B2",310,"C2",310,"D2",310,"Custom",0,260)) -> 0 | P106: =IFERROR(IF(OR(M106=0,N106=0),0,(M106+N106)*2+11),0) -> 0 | Q106: =IFERROR(IF(OR(N106=0,O106=0),0,(N106+O106)-16),0) -> 0 | R106: =P106*Q106/1000000 -> 0 | S106: =IFERROR(VLOOKUP(L106,'Carton Sizes Chart'!$A$4:$E$15,5,FALSE),0) -> 0 | T106: =S106 -> 0 | U106: =I106*T106 -> 0 | V106: =((T106*I106)-W106)*4% -> 0 | W106: =S106*I106*5% -> 0
J107: Standard Carton-Singles | K107: BC-Flute | L107: Custom | M107: {=IF(L107="",0,_xlfn.SWITCH(L107,"A1",495,"A2",495,"A3",495,"Custom",0,595))} -> 0 | N107: {=IF(L107="",0,_xlfn.SWITCH(L107,"C1",325,"C2",325,"C3",325,"D1",380,"D2",380,"D3",380,"Custom",0,285))} -> 0 | O107: =IF(L107="",0,_xlfn.SWITCH(L107,"A1",375,"B1",375,"C1",375,"D1",375,"A2",310,"B2",310,"C2",310,"D2",310,"Custom",0,260)) -> 0 | P107: =IFERROR(IF(OR(M107=0,N107=0),0,(M107+N107)*2+11),0) -> 0 | Q107: =IFERROR(IF(OR(N107=0,O107=0),0,(N107+O107)-16),0) -> 0 | R107: =P107*Q107/1000000 -> 0 | S107: =IFERROR(VLOOKUP(L107,'Carton Sizes Chart'!$A$4:$E$15,5,FALSE),0) -> 0 | T107: =S107 -> 0 | U107: =I107*T107 -> 0 | V107: =((T107*I107)-W107)*4% -> 0 | W107: =S107*I107*5% -> 0
J108: Standard Carton-Singles | K108: BC-Flute | L108: Custom | M108: {=IF(L108="",0,_xlfn.SWITCH(L108,"A1",495,"A2",495,"A3",495,"Custom",0,595))} -> 0 | N108: {=IF(L108="",0,_xlfn.SWITCH(L108,"C1",325,"C2",325,"C3",325,"D1",380,"D2",380,"D3",380,"Custom",0,285))} -> 0 | O108: =IF(L108="",0,_xlfn.SWITCH(L108,"A1",375,"B1",375,"C1",375,"D1",375,"A2",310,"B2",310,"C2",310,"D2",310,"Custom",0,260)) -> 0 | P108: =IFERROR(IF(OR(M108=0,N108=0),0,(M108+N108)*2+11),0) -> 0 | Q108: =IFERROR(IF(OR(N108=0,O108=0),0,(N108+O108)-16),0) -> 0 | R108: =P108*Q108/1000000 -> 0 | S108: =IFERROR(VLOOKUP(L108,'Carton Sizes Chart'!$A$4:$E$15,5,FALSE),0) -> 0 | T108: =S108 -> 0 | U108: =I108*T108 -> 0 | V108: =((T108*I108)-W108)*4% -> 0 | W108: =S108*I108*5% -> 0
J109: Standard Carton-Singles | K109: BC-Flute | L109: Custom | M109: {=IF(L109="",0,_xlfn.SWITCH(L109,"A1",495,"A2",495,"A3",495,"Custom",0,595))} -> 0 | N109: {=IF(L109="",0,_xlfn.SWITCH(L109,"C1",325,"C2",325,"C3",325,"D1",380,"D2",380,"D3",380,"Custom",0,285))} -> 0 | O109: =IF(L109="",0,_xlfn.SWITCH(L109,"A1",375,"B1",375,"C1",375,"D1",375,"A2",310,"B2",310,"C2",310,"D2",310,"Custom",0,260)) -> 0 | P109: =IFERROR(IF(OR(M109=0,N109=0),0,(M109+N109)*2+11),0) -> 0 | Q109: =IFERROR(IF(OR(N109=0,O109=0),0,(N109+O109)-16),0) -> 0 | R109: =P109*Q109/1000000 -> 0 | S109: =IFERROR(VLOOKUP(L109,'Carton Sizes Chart'!$A$4:$E$15,5,FALSE),0) -> 0 | T109: =S109 -> 0 | U109: =I109*T109 -> 0 | V109: =((T109*I109)-W109)*4% -> 0 | W109: =S109*I109*5% -> 0
J110: Standard Carton-Singles | K110: BC-Flute | L110: Custom | M110: {=IF(L110="",0,_xlfn.SWITCH(L110,"A1",495,"A2",495,"A3",495,"Custom",0,595))} -> 0 | N110: {=IF(L110="",0,_xlfn.SWITCH(L110,"C1",325,"C2",325,"C3",325,"D1",380,"D2",380,"D3",380,"Custom",0,285))} -> 0 | O110: =IF(L110="",0,_xlfn.SWITCH(L110,"A1",375,"B1",375,"C1",375,"D1",375,"A2",310,"B2",310,"C2",310,"D2",310,"Custom",0,260)) -> 0 | P110: =IFERROR(IF(OR(M110=0,N110=0),0,(M110+N110)*2+11),0) -> 0 | Q110: =IFERROR(IF(OR(N110=0,O110=0),0,(N110+O110)-16),0) -> 0 | R110: =P110*Q110/1000000 -> 0 | S110: =IF(L110="Custom", R110*'[2]RFQ_Matalan Carton'!$M$40, IFERROR(VLOOKUP(L110,'[2]Carton Sizes Chart'!$A$4:$E$15,5,FALSE),0)) -> 0 | T110: =S110 -> 0 | U110: =I110*T110 -> 0 | V110: =((T110*I110)-W110)*4% -> 0 | W110: =S110*I110*5% -> 0
J111: Standard Carton-Singles | K111: BC-Flute | L111: Custom | M111: {=IF(L111="",0,_xlfn.SWITCH(L111,"A1",495,"A2",495,"A3",495,"Custom",0,595))} -> 0 | N111: {=IF(L111="",0,_xlfn.SWITCH(L111,"C1",325,"C2",325,"C3",325,"D1",380,"D2",380,"D3",380,"Custom",0,285))} -> 0 | O111: =IF(L111="",0,_xlfn.SWITCH(L111,"A1",375,"B1",375,"C1",375,"D1",375,"A2",310,"B2",310,"C2",310,"D2",310,"Custom",0,260)) -> 0 | P111: =IFERROR(IF(OR(M111=0,N111=0),0,(M111+N111)*2+11),0) -> 0 | Q111: =IFERROR(IF(OR(N111=0,O111=0),0,(N111+O111)-16),0) -> 0 | R111: =P111*Q111/1000000 -> 0 | S111: =IF(L111="Custom", R111*'[2]RFQ_Matalan Carton'!$M$40, IFERROR(VLOOKUP(L111,'[2]Carton Sizes Chart'!$A$4:$E$15,5,FALSE),0)) -> 0 | T111: =S111 -> 0 | U111: =I111*T111 -> 0 | V111: =((T111*I111)-W111)*4% -> 0 | W111: =S111*I111*5% -> 0
J112: Standard Carton-Singles | K112: BC-Flute | L112: Custom | M112: {=IF(L112="",0,_xlfn.SWITCH(L112,"A1",495,"A2",495,"A3",495,"Custom",0,595))} -> 0 | N112: {=IF(L112="",0,_xlfn.SWITCH(L112,"C1",325,"C2",325,"C3",325,"D1",380,"D2",380,"D3",380,"Custom",0,285))} -> 0 | O112: =IF(L112="",0,_xlfn.SWITCH(L112,"A1",375,"B1",375,"C1",375,"D1",375,"A2",310,"B2",310,"C2",310,"D2",310,"Custom",0,260)) -> 0 | P112: =IFERROR(IF(OR(M112=0,N112=0),0,(M112+N112)*2+11),0) -> 0 | Q112: =IFERROR(IF(OR(N112=0,O112=0),0,(N112+O112)-16),0) -> 0 | R112: =P112*Q112/1000000 -> 0 | S112: =IFERROR(VLOOKUP(L112,'Carton Sizes Chart'!$A$4:$E$15,5,FALSE),0) -> 0 | T112: =S112 -> 0 | U112: =I112*T112 -> 0 | V112: =((T112*I112)-W112)*4% -> 0 | W112: =S112*I112*5% -> 0
J113: Standard Carton-Singles | K113: BC-Flute | L113: Custom | M113: {=IF(L113="",0,_xlfn.SWITCH(L113,"A1",495,"A2",495,"A3",495,"Custom",0,595))} -> 0 | N113: {=IF(L113="",0,_xlfn.SWITCH(L113,"C1",325,"C2",325,"C3",325,"D1",380,"D2",380,"D3",380,"Custom",0,285))} -> 0 | O113: =IF(L113="",0,_xlfn.SWITCH(L113,"A1",375,"B1",375,"C1",375,"D1",375,"A2",310,"B2",310,"C2",310,"D2",310,"Custom",0,260)) -> 0 | P113: =IFERROR(IF(OR(M113=0,N113=0),0,(M113+N113)*2+11),0) -> 0 | Q113: =IFERROR(IF(OR(N113=0,O113=0),0,(N113+O113)-16),0) -> 0 | R113: =P113*Q113/1000000 -> 0 | S113: =IF(L113="Custom", R113*'[2]RFQ_Matalan Carton'!$M$40, IFERROR(VLOOKUP(L113,'[2]Carton Sizes Chart'!$A$4:$E$15,5,FALSE),0)) -> 0 | T113: =S113 -> 0 | U113: =I113*T113 -> 0 | V113: =((T113*I113)-W113)*4% -> 0 | W113: =S113*I113*5% -> 0 | X113: Revise
J114: Standard Carton-Singles | K114: BC-Flute | L114: Custom | M114: {=IF(L114="",0,_xlfn.SWITCH(L114,"A1",495,"A2",495,"A3",495,"Custom",0,595))} -> 0 | N114: {=IF(L114="",0,_xlfn.SWITCH(L114,"C1",325,"C2",325,"C3",325,"D1",380,"D2",380,"D3",380,"Custom",0,285))} -> 0 | O114: =IF(L114="",0,_xlfn.SWITCH(L114,"A1",375,"B1",375,"C1",375,"D1",375,"A2",310,"B2",310,"C2",310,"D2",310,"Custom",0,260)) -> 0 | P114: =IFERROR(IF(OR(M114=0,N114=0),0,(M114+N114)*2+11),0) -> 0 | Q114: =IFERROR(IF(OR(N114=0,O114=0),0,(N114+O114)-16),0) -> 0 | R114: =P114*Q114/1000000 -> 0 | S114: =IF(L114="Custom", R114*'[2]RFQ_Matalan Carton'!$M$40, IFERROR(VLOOKUP(L114,'[2]Carton Sizes Chart'!$A$4:$E$15,5,FALSE),0)) -> 0 | T114: =S114 -> 0 | U114: =I114*T114 -> 0 | V114: =((T114*I114)-W114)*4% -> 0 | W114: =S114*I114*5% -> 0
J115: Standard Carton-Singles | K115: BC-Flute | L115: Custom | M115: {=IF(L115="",0,_xlfn.SWITCH(L115,"A1",495,"A2",495,"A3",495,"Custom",0,595))} -> 0 | N115: {=IF(L115="",0,_xlfn.SWITCH(L115,"C1",325,"C2",325,"C3",325,"D1",380,"D2",380,"D3",380,"Custom",0,285))} -> 0 | O115: =IF(L115="",0,_xlfn.SWITCH(L115,"A1",375,"B1",375,"C1",375,"D1",375,"A2",310,"B2",310,"C2",310,"D2",310,"Custom",0,260)) -> 0 | P115: =IFERROR(IF(OR(M115=0,N115=0),0,(M115+N115)*2+11),0) -> 0 | Q115: =IFERROR(IF(OR(N115=0,O115=0),0,(N115+O115)-16),0) -> 0 | R115: =P115*Q115/1000000 -> 0 | S115: =IF(L115="Custom", R115*'[2]RFQ_Matalan Carton'!$M$40, IFERROR(VLOOKUP(L115,'[2]Carton Sizes Chart'!$A$4:$E$15,5,FALSE),0)) -> 0 | T115: =S115 -> 0 | U115: =I115*T115 -> 0 | V115: =((T115*I115)-W115)*4% -> 0 | W115: =S115*I115*5% -> 0
J116: Standard Carton-Singles | K116: BC-Flute | L116: Custom | M116: {=IF(L116="",0,_xlfn.SWITCH(L116,"A1",495,"A2",495,"A3",495,"Custom",0,595))} -> 0 | N116: {=IF(L116="",0,_xlfn.SWITCH(L116,"C1",325,"C2",325,"C3",325,"D1",380,"D2",380,"D3",380,"Custom",0,285))} -> 0 | O116: =IF(L116="",0,_xlfn.SWITCH(L116,"A1",375,"B1",375,"C1",375,"D1",375,"A2",310,"B2",310,"C2",310,"D2",310,"Custom",0,260)) -> 0 | P116: =IFERROR(IF(OR(M116=0,N116=0),0,(M116+N116)*2+11),0) -> 0 | Q116: =IFERROR(IF(OR(N116=0,O116=0),0,(N116+O116)-16),0) -> 0 | R116: =P116*Q116/1000000 -> 0 | S116: =IF(L116="Custom", R116*'[2]RFQ_Matalan Carton'!$M$40, IFERROR(VLOOKUP(L116,'[2]Carton Sizes Chart'!$A$4:$E$15,5,FALSE),0)) -> 0 | T116: =S116 -> 0 | U116: =I116*T116 -> 0 | V116: =((T116*I116)-W116)*4% -> 0 | W116: =S116*I116*5% -> 0
J117: Standard Carton-Singles | K117: BC-Flute | L117: Custom | M117: {=IF(L117="",0,_xlfn.SWITCH(L117,"A1",495,"A2",495,"A3",495,"Custom",0,595))} -> 0 | N117: {=IF(L117="",0,_xlfn.SWITCH(L117,"C1",325,"C2",325,"C3",325,"D1",380,"D2",380,"D3",380,"Custom",0,285))} -> 0 | O117: =IF(L117="",0,_xlfn.SWITCH(L117,"A1",375,"B1",375,"C1",375,"D1",375,"A2",310,"B2",310,"C2",310,"D2",310,"Custom",0,260)) -> 0 | P117: =IFERROR(IF(OR(M117=0,N117=0),0,(M117+N117)*2+11),0) -> 0 | Q117: =IFERROR(IF(OR(N117=0,O117=0),0,(N117+O117)-16),0) -> 0 | R117: =P117*Q117/1000000 -> 0 | S117: =IF(L117="Custom", R117*'[2]RFQ_Matalan Carton'!$M$40, IFERROR(VLOOKUP(L117,'[2]Carton Sizes Chart'!$A$4:$E$15,5,FALSE),0)) -> 0 | T117: =S117 -> 0 | U117: =I117*T117 -> 0 | V117: =((T117*I117)-W117)*4% -> 0 | W117: =S117*I117*5% -> 0
J118: Standard Carton-Singles | K118: BC-Flute | L118: Custom | M118: {=IF(L118="",0,_xlfn.SWITCH(L118,"A1",495,"A2",495,"A3",495,"Custom",0,595))} -> 0 | N118: {=IF(L118="",0,_xlfn.SWITCH(L118,"C1",325,"C2",325,"C3",325,"D1",380,"D2",380,"D3",380,"Custom",0,285))} -> 0 | O118: =IF(L118="",0,_xlfn.SWITCH(L118,"A1",375,"B1",375,"C1",375,"D1",375,"A2",310,"B2",310,"C2",310,"D2",310,"Custom",0,260)) -> 0 | P118: =IFERROR(IF(OR(M118=0,N118=0),0,(M118+N118)*2+11),0) -> 0 | Q118: =IFERROR(IF(OR(N118=0,O118=0),0,(N118+O118)-16),0) -> 0 | R118: =P118*Q118/1000000 -> 0 | S118: =IF(L118="Custom", R118*'[2]RFQ_Matalan Carton'!$M$40, IFERROR(VLOOKUP(L118,'[2]Carton Sizes Chart'!$A$4:$E$15,5,FALSE),0)) -> 0 | T118: =S118 -> 0 | U118: =I118*T118 -> 0 | V118: =((T118*I118)-W118)*4% -> 0 | W118: =S118*I118*5% -> 0
J119: Standard Carton-Singles | K119: BC-Flute | L119: Custom | M119: {=IF(L119="",0,_xlfn.SWITCH(L119,"A1",495,"A2",495,"A3",495,"Custom",0,595))} -> 0 | N119: {=IF(L119="",0,_xlfn.SWITCH(L119,"C1",325,"C2",325,"C3",325,"D1",380,"D2",380,"D3",380,"Custom",0,285))} -> 0 | O119: =IF(L119="",0,_xlfn.SWITCH(L119,"A1",375,"B1",375,"C1",375,"D1",375,"A2",310,"B2",310,"C2",310,"D2",310,"Custom",0,260)) -> 0 | P119: =IFERROR(IF(OR(M119=0,N119=0),0,(M119+N119)*2+11),0) -> 0 | Q119: =IFERROR(IF(OR(N119=0,O119=0),0,(N119+O119)-16),0) -> 0 | R119: =P119*Q119/1000000 -> 0 | S119: =IF(L119="Custom", R119*'[2]RFQ_Matalan Carton'!$M$40, IFERROR(VLOOKUP(L119,'[2]Carton Sizes Chart'!$A$4:$E$15,5,FALSE),0)) -> 0 | T119: =S119 -> 0 | U119: =I119*T119 -> 0 | V119: =((T119*I119)-W119)*4% -> 0 | W119: =S119*I119*5% -> 0
J120: Standard Carton-Singles | K120: BC-Flute | L120: Custom | M120: {=IF(L120="",0,_xlfn.SWITCH(L120,"A1",495,"A2",495,"A3",495,"Custom",0,595))} -> 0 | N120: {=IF(L120="",0,_xlfn.SWITCH(L120,"C1",325,"C2",325,"C3",325,"D1",380,"D2",380,"D3",380,"Custom",0,285))} -> 0 | O120: =IF(L120="",0,_xlfn.SWITCH(L120,"A1",375,"B1",375,"C1",375,"D1",375,"A2",310,"B2",310,"C2",310,"D2",310,"Custom",0,260)) -> 0 | P120: =IFERROR(IF(OR(M120=0,N120=0),0,(M120+N120)*2+11),0) -> 0 | Q120: =IFERROR(IF(OR(N120=0,O120=0),0,(N120+O120)-16),0) -> 0 | R120: =P120*Q120/1000000 -> 0 | S120: =IF(L120="Custom", R120*'[2]RFQ_Matalan Carton'!$M$40, IFERROR(VLOOKUP(L120,'[2]Carton Sizes Chart'!$A$4:$E$15,5,FALSE),0)) -> 0 | T120: =S120 -> 0 | U120: =I120*T120 -> 0 | V120: =((T120*I120)-W120)*4% -> 0 | W120: =S120*I120*5% -> 0
J121: Standard Carton-Singles | K121: BC-Flute | L121: Custom | M121: {=IF(L121="",0,_xlfn.SWITCH(L121,"A1",495,"A2",495,"A3",495,"Custom",0,595))} -> 0 | N121: {=IF(L121="",0,_xlfn.SWITCH(L121,"C1",325,"C2",325,"C3",325,"D1",380,"D2",380,"D3",380,"Custom",0,285))} -> 0 | O121: =IF(L121="",0,_xlfn.SWITCH(L121,"A1",375,"B1",375,"C1",375,"D1",375,"A2",310,"B2",310,"C2",310,"D2",310,"Custom",0,260)) -> 0 | P121: =IFERROR(IF(OR(M121=0,N121=0),0,(M121+N121)*2+11),0) -> 0 | Q121: =IFERROR(IF(OR(N121=0,O121=0),0,(N121+O121)-16),0) -> 0 | R121: =P121*Q121/1000000 -> 0 | S121: =IFERROR(VLOOKUP(L121,'Carton Sizes Chart'!$A$4:$E$15,5,FALSE),0) -> 0 | T121: =S121 -> 0 | U121: =I121*T121 -> 0 | V121: =((T121*I121)-W121)*4% -> 0 | W121: =S121*I121*5% -> 0
J122: Standard Carton-Singles | K122: BC-Flute | L122: Custom | M122: {=IF(L122="",0,_xlfn.SWITCH(L122,"A1",495,"A2",495,"A3",495,"Custom",0,595))} -> 0 | N122: {=IF(L122="",0,_xlfn.SWITCH(L122,"C1",325,"C2",325,"C3",325,"D1",380,"D2",380,"D3",380,"Custom",0,285))} -> 0 | O122: =IF(L122="",0,_xlfn.SWITCH(L122,"A1",375,"B1",375,"C1",375,"D1",375,"A2",310,"B2",310,"C2",310,"D2",310,"Custom",0,260)) -> 0 | P122: =IFERROR(IF(OR(M122=0,N122=0),0,(M122+N122)*2+11),0) -> 0 | Q122: =IFERROR(IF(OR(N122=0,O122=0),0,(N122+O122)-16),0) -> 0 | R122: =P122*Q122/1000000 -> 0 | S122: =IFERROR(VLOOKUP(L122,'Carton Sizes Chart'!$A$4:$E$15,5,FALSE),0) -> 0 | T122: =S122 -> 0 | U122: =I122*T122 -> 0 | V122: =((T122*I122)-W122)*4% -> 0 | W122: =S122*I122*5% -> 0
J123: Standard Carton-Singles | K123: BC-Flute | L123: Custom | M123: {=IF(L123="",0,_xlfn.SWITCH(L123,"A1",495,"A2",495,"A3",495,"Custom",0,595))} -> 0 | N123: {=IF(L123="",0,_xlfn.SWITCH(L123,"C1",325,"C2",325,"C3",325,"D1",380,"D2",380,"D3",380,"Custom",0,285))} -> 0 | O123: =IF(L123="",0,_xlfn.SWITCH(L123,"A1",375,"B1",375,"C1",375,"D1",375,"A2",310,"B2",310,"C2",310,"D2",310,"Custom",0,260)) -> 0 | P123: =IFERROR(IF(OR(M123=0,N123=0),0,(M123+N123)*2+11),0) -> 0 | Q123: =IFERROR(IF(OR(N123=0,O123=0),0,(N123+O123)-16),0) -> 0 | R123: =P123*Q123/1000000 -> 0 | S123: =IF(L123="Custom", R123*'[1]RFQ_Matalan Carton'!$M$40, IFERROR(VLOOKUP(L123,'[1]Carton Sizes Chart'!$A$4:$E$15,5,FALSE),0)) -> 0 | T123: =S123 -> 0 | U123: =I123*T123 -> 0 | V123: =((T123*I123)-W123)*4% -> 0 | W123: =S123*I123*5% -> 0
J124: Standard Carton-Singles | K124: BC-Flute | L124: Custom | M124: {=IF(L124="",0,_xlfn.SWITCH(L124,"A1",495,"A2",495,"A3",495,"Custom",0,595))} -> 0 | N124: {=IF(L124="",0,_xlfn.SWITCH(L124,"C1",325,"C2",325,"C3",325,"D1",380,"D2",380,"D3",380,"Custom",0,285))} -> 0 | O124: =IF(L124="",0,_xlfn.SWITCH(L124,"A1",375,"B1",375,"C1",375,"D1",375,"A2",310,"B2",310,"C2",310,"D2",310,"Custom",0,260)) -> 0 | P124: =IFERROR(IF(OR(M124=0,N124=0),0,(M124+N124)*2+11),0) -> 0 | Q124: =IFERROR(IF(OR(N124=0,O124=0),0,(N124+O124)-16),0) -> 0 | R124: =P124*Q124/1000000 -> 0 | S124: =IFERROR(VLOOKUP(L124,'Carton Sizes Chart'!$A$4:$E$15,5,FALSE),0) -> 0 | T124: =S124 -> 0 | U124: =I124*T124 -> 0 | V124: =((T124*I124)-W124)*4% -> 0 | W124: =S124*I124*5% -> 0
J125: Standard Carton-Singles | K125: BC-Flute | L125: Custom | M125: {=IF(L125="",0,_xlfn.SWITCH(L125,"A1",495,"A2",495,"A3",495,"Custom",0,595))} -> 0 | N125: {=IF(L125="",0,_xlfn.SWITCH(L125,"C1",325,"C2",325,"C3",325,"D1",380,"D2",380,"D3",380,"Custom",0,285))} -> 0 | O125: =IF(L125="",0,_xlfn.SWITCH(L125,"A1",375,"B1",375,"C1",375,"D1",375,"A2",310,"B2",310,"C2",310,"D2",310,"Custom",0,260)) -> 0 | P125: =IFERROR(IF(OR(M125=0,N125=0),0,(M125+N125)*2+11),0) -> 0 | Q125: =IFERROR(IF(OR(N125=0,O125=0),0,(N125+O125)-16),0) -> 0 | R125: =P125*Q125/1000000 -> 0 | S125: =IFERROR(VLOOKUP(L125,'Carton Sizes Chart'!$A$4:$E$15,5,FALSE),0) -> 0 | T125: =S125 -> 0 | U125: =I125*T125 -> 0 | V125: =((T125*I125)-W125)*4% -> 0 | W125: =S125*I125*5% -> 0
J126: Standard Carton-Singles | K126: BC-Flute | L126: Custom | M126: {=IF(L126="",0,_xlfn.SWITCH(L126,"A1",495,"A2",495,"A3",495,"Custom",0,595))} -> 0 | N126: {=IF(L126="",0,_xlfn.SWITCH(L126,"C1",325,"C2",325,"C3",325,"D1",380,"D2",380,"D3",380,"Custom",0,285))} -> 0 | O126: =IF(L126="",0,_xlfn.SWITCH(L126,"A1",375,"B1",375,"C1",375,"D1",375,"A2",310,"B2",310,"C2",310,"D2",310,"Custom",0,260)) -> 0 | P126: =IFERROR(IF(OR(M126=0,N126=0),0,(M126+N126)*2+11),0) -> 0 | Q126: =IFERROR(IF(OR(N126=0,O126=0),0,(N126+O126)-16),0) -> 0 | R126: =P126*Q126/1000000 -> 0 | S126: =IFERROR(VLOOKUP(L126,'Carton Sizes Chart'!$A$4:$E$15,5,FALSE),0) -> 0 | T126: =S126 -> 0 | U126: =I126*T126 -> 0 | V126: =((T126*I126)-W126)*4% -> 0 | W126: =S126*I126*5% -> 0
J127: Standard Carton-Singles | K127: BC-Flute | L127: Custom | M127: {=IF(L127="",0,_xlfn.SWITCH(L127,"A1",495,"A2",495,"A3",495,"Custom",0,595))} -> 0 | N127: {=IF(L127="",0,_xlfn.SWITCH(L127,"C1",325,"C2",325,"C3",325,"D1",380,"D2",380,"D3",380,"Custom",0,285))} -> 0 | O127: =IF(L127="",0,_xlfn.SWITCH(L127,"A1",375,"B1",375,"C1",375,"D1",375,"A2",310,"B2",310,"C2",310,"D2",310,"Custom",0,260)) -> 0 | P127: =IFERROR(IF(OR(M127=0,N127=0),0,(M127+N127)*2+11),0) -> 0 | Q127: =IFERROR(IF(OR(N127=0,O127=0),0,(N127+O127)-16),0) -> 0 | R127: =P127*Q127/1000000 -> 0 | S127: =IFERROR(VLOOKUP(L127,'Carton Sizes Chart'!$A$4:$E$15,5,FALSE),0) -> 0 | T127: =S127 -> 0 | U127: =I127*T127 -> 0 | V127: =((T127*I127)-W127)*4% -> 0 | W127: =S127*I127*5% -> 0
J128: Standard Carton-Singles | K128: BC-Flute | L128: Custom | M128: {=IF(L128="",0,_xlfn.SWITCH(L128,"A1",495,"A2",495,"A3",495,"Custom",0,595))} -> 0 | N128: {=IF(L128="",0,_xlfn.SWITCH(L128,"C1",325,"C2",325,"C3",325,"D1",380,"D2",380,"D3",380,"Custom",0,285))} -> 0 | O128: =IF(L128="",0,_xlfn.SWITCH(L128,"A1",375,"B1",375,"C1",375,"D1",375,"A2",310,"B2",310,"C2",310,"D2",310,"Custom",0,260)) -> 0 | P128: =IFERROR(IF(OR(M128=0,N128=0),0,(M128+N128)*2+11),0) -> 0 | Q128: =IFERROR(IF(OR(N128=0,O128=0),0,(N128+O128)-16),0) -> 0 | R128: =P128*Q128/1000000 -> 0 | S128: =IF(L128="Custom", R128*'[2]RFQ_Matalan Carton'!$M$40, IFERROR(VLOOKUP(L128,'[2]Carton Sizes Chart'!$A$4:$E$15,5,FALSE),0)) -> 0 | T128: =S128 -> 0 | U128: =I128*T128 -> 0 | V128: =((T128*I128)-W128)*4% -> 0 | W128: =S128*I128*5% -> 0
J129: Standard Carton-Singles | K129: BC-Flute | L129: Custom | M129: {=IF(L129="",0,_xlfn.SWITCH(L129,"A1",495,"A2",495,"A3",495,"Custom",0,595))} -> 0 | N129: {=IF(L129="",0,_xlfn.SWITCH(L129,"C1",325,"C2",325,"C3",325,"D1",380,"D2",380,"D3",380,"Custom",0,285))} -> 0 | O129: =IF(L129="",0,_xlfn.SWITCH(L129,"A1",375,"B1",375,"C1",375,"D1",375,"A2",310,"B2",310,"C2",310,"D2",310,"Custom",0,260)) -> 0 | P129: =IFERROR(IF(OR(M129=0,N129=0),0,(M129+N129)*2+11),0) -> 0 | Q129: =IFERROR(IF(OR(N129=0,O129=0),0,(N129+O129)-16),0) -> 0 | R129: =P129*Q129/1000000 -> 0 | S129: =IF(L129="Custom", R129*'[2]RFQ_Matalan Carton'!$M$40, IFERROR(VLOOKUP(L129,'[2]Carton Sizes Chart'!$A$4:$E$15,5,FALSE),0)) -> 0 | T129: =S129 -> 0 | U129: =I129*T129 -> 0 | V129: =((T129*I129)-W129)*4% -> 0 | W129: =S129*I129*5% -> 0
J130: Standard Carton-Singles | K130: BC-Flute | L130: Custom | M130: {=IF(L130="",0,_xlfn.SWITCH(L130,"A1",495,"A2",495,"A3",495,"Custom",0,595))} -> 0 | N130: {=IF(L130="",0,_xlfn.SWITCH(L130,"C1",325,"C2",325,"C3",325,"D1",380,"D2",380,"D3",380,"Custom",0,285))} -> 0 | O130: =IF(L130="",0,_xlfn.SWITCH(L130,"A1",375,"B1",375,"C1",375,"D1",375,"A2",310,"B2",310,"C2",310,"D2",310,"Custom",0,260)) -> 0 | P130: =IFERROR(IF(OR(M130=0,N130=0),0,(M130+N130)*2+11),0) -> 0 | Q130: =IFERROR(IF(OR(N130=0,O130=0),0,(N130+O130)-16),0) -> 0 | R130: =P130*Q130/1000000 -> 0 | S130: =IF(L130="Custom", R130*'[2]RFQ_Matalan Carton'!$M$40, IFERROR(VLOOKUP(L130,'[2]Carton Sizes Chart'!$A$4:$E$15,5,FALSE),0)) -> 0 | T130: =S130 -> 0 | U130: =I130*T130 -> 0 | V130: =((T130*I130)-W130)*4% -> 0 | W130: =S130*I130*5% -> 0
J131: Standard Carton-Singles | K131: BC-Flute | L131: Custom | M131: {=IF(L131="",0,_xlfn.SWITCH(L131,"A1",495,"A2",495,"A3",495,"Custom",0,595))} -> 0 | N131: {=IF(L131="",0,_xlfn.SWITCH(L131,"C1",325,"C2",325,"C3",325,"D1",380,"D2",380,"D3",380,"Custom",0,285))} -> 0 | O131: =IF(L131="",0,_xlfn.SWITCH(L131,"A1",375,"B1",375,"C1",375,"D1",375,"A2",310,"B2",310,"C2",310,"D2",310,"Custom",0,260)) -> 0 | P131: =IFERROR(IF(OR(M131=0,N131=0),0,(M131+N131)*2+11),0) -> 0 | Q131: =IFERROR(IF(OR(N131=0,O131=0),0,(N131+O131)-16),0) -> 0 | R131: =P131*Q131/1000000 -> 0 | S131: =IF(L131="Custom", R131*'[2]RFQ_Matalan Carton'!$M$40, IFERROR(VLOOKUP(L131,'[2]Carton Sizes Chart'!$A$4:$E$15,5,FALSE),0)) -> 0 | T131: =S131 -> 0 | U131: =I131*T131 -> 0 | V131: =((T131*I131)-W131)*4% -> 0 | W131: =S131*I131*5% -> 0
J132: Standard Carton-Singles | K132: BC-Flute | L132: Custom | M132: {=IF(L132="",0,_xlfn.SWITCH(L132,"A1",495,"A2",495,"A3",495,"Custom",0,595))} -> 0 | N132: {=IF(L132="",0,_xlfn.SWITCH(L132,"C1",325,"C2",325,"C3",325,"D1",380,"D2",380,"D3",380,"Custom",0,285))} -> 0 | O132: =IF(L132="",0,_xlfn.SWITCH(L132,"A1",375,"B1",375,"C1",375,"D1",375,"A2",310,"B2",310,"C2",310,"D2",310,"Custom",0,260)) -> 0 | P132: =IFERROR(IF(OR(M132=0,N132=0),0,(M132+N132)*2+11),0) -> 0 | Q132: =IFERROR(IF(OR(N132=0,O132=0),0,(N132+O132)-16),0) -> 0 | R132: =P132*Q132/1000000 -> 0 | S132: =IF(L132="Custom", R132*'[2]RFQ_Matalan Carton'!$M$40, IFERROR(VLOOKUP(L132,'[2]Carton Sizes Chart'!$A$4:$E$15,5,FALSE),0)) -> 0 | T132: =S132 -> 0 | U132: =I132*T132 -> 0 | V132: =((T132*I132)-W132)*4% -> 0 | W132: =S132*I132*5% -> 0
J133: Standard Carton-Singles | K133: BC-Flute | L133: Custom | M133: {=IF(L133="",0,_xlfn.SWITCH(L133,"A1",495,"A2",495,"A3",495,"Custom",0,595))} -> 0 | N133: {=IF(L133="",0,_xlfn.SWITCH(L133,"C1",325,"C2",325,"C3",325,"D1",380,"D2",380,"D3",380,"Custom",0,285))} -> 0 | O133: =IF(L133="",0,_xlfn.SWITCH(L133,"A1",375,"B1",375,"C1",375,"D1",375,"A2",310,"B2",310,"C2",310,"D2",310,"Custom",0,260)) -> 0 | P133: =IFERROR(IF(OR(M133=0,N133=0),0,(M133+N133)*2+11),0) -> 0 | Q133: =IFERROR(IF(OR(N133=0,O133=0),0,(N133+O133)-16),0) -> 0 | R133: =P133*Q133/1000000 -> 0 | S133: =IF(L133="Custom", R133*'[2]RFQ_Matalan Carton'!$M$40, IFERROR(VLOOKUP(L133,'[2]Carton Sizes Chart'!$A$4:$E$15,5,FALSE),0)) -> 0 | T133: =S133 -> 0 | U133: =I133*T133 -> 0 | V133: =((T133*I133)-W133)*4% -> 0 | W133: =S133*I133*5% -> 0
J134: Standard Carton-Singles | K134: BC-Flute | L134: Custom | M134: {=IF(L134="",0,_xlfn.SWITCH(L134,"A1",495,"A2",495,"A3",495,"Custom",0,595))} -> 0 | N134: {=IF(L134="",0,_xlfn.SWITCH(L134,"C1",325,"C2",325,"C3",325,"D1",380,"D2",380,"D3",380,"Custom",0,285))} -> 0 | O134: =IF(L134="",0,_xlfn.SWITCH(L134,"A1",375,"B1",375,"C1",375,"D1",375,"A2",310,"B2",310,"C2",310,"D2",310,"Custom",0,260)) -> 0 | P134: =IFERROR(IF(OR(M134=0,N134=0),0,(M134+N134)*2+11),0) -> 0 | Q134: =IFERROR(IF(OR(N134=0,O134=0),0,(N134+O134)-16),0) -> 0 | R134: =P134*Q134/1000000 -> 0 | S134: =IF(L134="Custom", R134*'[2]RFQ_Matalan Carton'!$M$40, IFERROR(VLOOKUP(L134,'[2]Carton Sizes Chart'!$A$4:$E$15,5,FALSE),0)) -> 0 | T134: =S134 -> 0 | U134: =I134*T134 -> 0 | V134: =((T134*I134)-W134)*4% -> 0 | W134: =S134*I134*5% -> 0
J135: Standard Carton-Singles | K135: BC-Flute | L135: Custom | M135: {=IF(L135="",0,_xlfn.SWITCH(L135,"A1",495,"A2",495,"A3",495,"Custom",0,595))} -> 0 | N135: {=IF(L135="",0,_xlfn.SWITCH(L135,"C1",325,"C2",325,"C3",325,"D1",380,"D2",380,"D3",380,"Custom",0,285))} -> 0 | O135: =IF(L135="",0,_xlfn.SWITCH(L135,"A1",375,"B1",375,"C1",375,"D1",375,"A2",310,"B2",310,"C2",310,"D2",310,"Custom",0,260)) -> 0 | P135: =IFERROR(IF(OR(M135=0,N135=0),0,(M135+N135)*2+11),0) -> 0 | Q135: =IFERROR(IF(OR(N135=0,O135=0),0,(N135+O135)-16),0) -> 0 | R135: =P135*Q135/1000000 -> 0 | S135: =IF(L135="Custom", R135*'[2]RFQ_Matalan Carton'!$M$40, IFERROR(VLOOKUP(L135,'[2]Carton Sizes Chart'!$A$4:$E$15,5,FALSE),0)) -> 0 | T135: =S135 -> 0 | U135: =I135*T135 -> 0 | V135: =((T135*I135)-W135)*4% -> 0 | W135: =S135*I135*5% -> 0
J136: Standard Carton-Singles | K136: BC-Flute | L136: Custom | M136: {=IF(L136="",0,_xlfn.SWITCH(L136,"A1",495,"A2",495,"A3",495,"Custom",0,595))} -> 0 | N136: {=IF(L136="",0,_xlfn.SWITCH(L136,"C1",325,"C2",325,"C3",325,"D1",380,"D2",380,"D3",380,"Custom",0,285))} -> 0 | O136: =IF(L136="",0,_xlfn.SWITCH(L136,"A1",375,"B1",375,"C1",375,"D1",375,"A2",310,"B2",310,"C2",310,"D2",310,"Custom",0,260)) -> 0 | P136: =IFERROR(IF(OR(M136=0,N136=0),0,(M136+N136)*2+11),0) -> 0 | Q136: =IFERROR(IF(OR(N136=0,O136=0),0,(N136+O136)-16),0) -> 0 | R136: =P136*Q136/1000000 -> 0 | S136: =IF(L136="Custom", R136*'[2]RFQ_Matalan Carton'!$M$40, IFERROR(VLOOKUP(L136,'[2]Carton Sizes Chart'!$A$4:$E$15,5,FALSE),0)) -> 0 | T136: =S136 -> 0 | U136: =I136*T136 -> 0 | V136: =((T136*I136)-W136)*4% -> 0 | W136: =S136*I136*5% -> 0
J137: Standard Carton-Singles | K137: BC-Flute | L137: Custom | M137: {=IF(L137="",0,_xlfn.SWITCH(L137,"A1",495,"A2",495,"A3",495,"Custom",0,595))} -> 0 | N137: {=IF(L137="",0,_xlfn.SWITCH(L137,"C1",325,"C2",325,"C3",325,"D1",380,"D2",380,"D3",380,"Custom",0,285))} -> 0 | O137: =IF(L137="",0,_xlfn.SWITCH(L137,"A1",375,"B1",375,"C1",375,"D1",375,"A2",310,"B2",310,"C2",310,"D2",310,"Custom",0,260)) -> 0 | P137: =IFERROR(IF(OR(M137=0,N137=0),0,(M137+N137)*2+11),0) -> 0 | Q137: =IFERROR(IF(OR(N137=0,O137=0),0,(N137+O137)-16),0) -> 0 | R137: =P137*Q137/1000000 -> 0 | S137: =IF(L137="Custom", R137*'[2]RFQ_Matalan Carton'!$M$40, IFERROR(VLOOKUP(L137,'[2]Carton Sizes Chart'!$A$4:$E$15,5,FALSE),0)) -> 0 | T137: =S137 -> 0 | U137: =I137*T137 -> 0 | V137: =((T137*I137)-W137)*4% -> 0 | W137: =S137*I137*5% -> 0
J138: Standard Carton-Singles | K138: BC-Flute | L138: Custom | M138: {=IF(L138="",0,_xlfn.SWITCH(L138,"A1",495,"A2",495,"A3",495,"Custom",0,595))} -> 0 | N138: {=IF(L138="",0,_xlfn.SWITCH(L138,"C1",325,"C2",325,"C3",325,"D1",380,"D2",380,"D3",380,"Custom",0,285))} -> 0 | O138: =IF(L138="",0,_xlfn.SWITCH(L138,"A1",375,"B1",375,"C1",375,"D1",375,"A2",310,"B2",310,"C2",310,"D2",310,"Custom",0,260)) -> 0 | P138: =IFERROR(IF(OR(M138=0,N138=0),0,(M138+N138)*2+11),0) -> 0 | Q138: =IFERROR(IF(OR(N138=0,O138=0),0,(N138+O138)-16),0) -> 0 | R138: =P138*Q138/1000000 -> 0 | S138: =IF(L138="Custom", R138*'[2]RFQ_Matalan Carton'!$M$40, IFERROR(VLOOKUP(L138,'[2]Carton Sizes Chart'!$A$4:$E$15,5,FALSE),0)) -> 0 | T138: =S138 -> 0 | U138: =I138*T138 -> 0 | V138: =((T138*I138)-W138)*4% -> 0 | W138: =S138*I138*5% -> 0
J139: Standard Carton-Singles | K139: BC-Flute | L139: Custom | M139: {=IF(L139="",0,_xlfn.SWITCH(L139,"A1",495,"A2",495,"A3",495,"Custom",0,595))} -> 0 | N139: {=IF(L139="",0,_xlfn.SWITCH(L139,"C1",325,"C2",325,"C3",325,"D1",380,"D2",380,"D3",380,"Custom",0,285))} -> 0 | O139: =IF(L139="",0,_xlfn.SWITCH(L139,"A1",375,"B1",375,"C1",375,"D1",375,"A2",310,"B2",310,"C2",310,"D2",310,"Custom",0,260)) -> 0 | P139: =IFERROR(IF(OR(M139=0,N139=0),0,(M139+N139)*2+11),0) -> 0 | Q139: =IFERROR(IF(OR(N139=0,O139=0),0,(N139+O139)-16),0) -> 0 | R139: =P139*Q139/1000000 -> 0 | S139: =IF(L139="Custom", R139*'[2]RFQ_Matalan Carton'!$M$40, IFERROR(VLOOKUP(L139,'[2]Carton Sizes Chart'!$A$4:$E$15,5,FALSE),0)) -> 0 | T139: =S139 -> 0 | U139: =I139*T139 -> 0 | V139: =((T139*I139)-W139)*4% -> 0 | W139: =S139*I139*5% -> 0
J140: Standard Carton-Singles | K140: BC-Flute | L140: Custom | M140: {=IF(L140="",0,_xlfn.SWITCH(L140,"A1",495,"A2",495,"A3",495,"Custom",0,595))} -> 0 | N140: {=IF(L140="",0,_xlfn.SWITCH(L140,"C1",325,"C2",325,"C3",325,"D1",380,"D2",380,"D3",380,"Custom",0,285))} -> 0 | O140: =IF(L140="",0,_xlfn.SWITCH(L140,"A1",375,"B1",375,"C1",375,"D1",375,"A2",310,"B2",310,"C2",310,"D2",310,"Custom",0,260)) -> 0 | P140: =IFERROR(IF(OR(M140=0,N140=0),0,(M140+N140)*2+11),0) -> 0 | Q140: =IFERROR(IF(OR(N140=0,O140=0),0,(N140+O140)-16),0) -> 0 | R140: =P140*Q140/1000000 -> 0 | S140: =IFERROR(VLOOKUP(L140,'Carton Sizes Chart'!$A$4:$E$15,5,FALSE),0) -> 0 | T140: =S140 -> 0 | U140: =I140*T140 -> 0 | V140: =((T140*I140)-W140)*4% -> 0 | W140: =S140*I140*5% -> 0
J141: Standard Carton-Singles | K141: BC-Flute | L141: Custom | M141: {=IF(L141="",0,_xlfn.SWITCH(L141,"A1",495,"A2",495,"A3",495,"Custom",0,595))} -> 0 | N141: {=IF(L141="",0,_xlfn.SWITCH(L141,"C1",325,"C2",325,"C3",325,"D1",380,"D2",380,"D3",380,"Custom",0,285))} -> 0 | O141: =IF(L141="",0,_xlfn.SWITCH(L141,"A1",375,"B1",375,"C1",375,"D1",375,"A2",310,"B2",310,"C2",310,"D2",310,"Custom",0,260)) -> 0 | P141: =IFERROR(IF(OR(M141=0,N141=0),0,(M141+N141)*2+11),0) -> 0 | Q141: =IFERROR(IF(OR(N141=0,O141=0),0,(N141+O141)-16),0) -> 0 | R141: =P141*Q141/1000000 -> 0 | S141: =IFERROR(VLOOKUP(L141,'Carton Sizes Chart'!$A$4:$E$15,5,FALSE),0) -> 0 | T141: =S141 -> 0 | U141: =I141*T141 -> 0 | V141: =((T141*I141)-W141)*4% -> 0 | W141: =S141*I141*5% -> 0
J142: Standard Carton-Singles | K142: BC-Flute | L142: Custom | M142: {=IF(L142="",0,_xlfn.SWITCH(L142,"A1",495,"A2",495,"A3",495,"Custom",0,595))} -> 0 | N142: {=IF(L142="",0,_xlfn.SWITCH(L142,"C1",325,"C2",325,"C3",325,"D1",380,"D2",380,"D3",380,"Custom",0,285))} -> 0 | O142: =IF(L142="",0,_xlfn.SWITCH(L142,"A1",375,"B1",375,"C1",375,"D1",375,"A2",310,"B2",310,"C2",310,"D2",310,"Custom",0,260)) -> 0 | P142: =IFERROR(IF(OR(M142=0,N142=0),0,(M142+N142)*2+11),0) -> 0 | Q142: =IFERROR(IF(OR(N142=0,O142=0),0,(N142+O142)-16),0) -> 0 | R142: =P142*Q142/1000000 -> 0 | S142: =IF(L142="Custom", R142*'[2]RFQ_Matalan Carton'!$M$40, IFERROR(VLOOKUP(L142,'[2]Carton Sizes Chart'!$A$4:$E$15,5,FALSE),0)) -> 0 | T142: =S142 -> 0 | U142: =I142*T142 -> 0 | V142: =((T142*I142)-W142)*4% -> 0 | W142: =S142*I142*5% -> 0
J143: Standard Carton-Singles | K143: BC-Flute | L143: Custom | M143: {=IF(L143="",0,_xlfn.SWITCH(L143,"A1",495,"A2",495,"A3",495,"Custom",0,595))} -> 0 | N143: {=IF(L143="",0,_xlfn.SWITCH(L143,"C1",325,"C2",325,"C3",325,"D1",380,"D2",380,"D3",380,"Custom",0,285))} -> 0 | O143: =IF(L143="",0,_xlfn.SWITCH(L143,"A1",375,"B1",375,"C1",375,"D1",375,"A2",310,"B2",310,"C2",310,"D2",310,"Custom",0,260)) -> 0 | P143: =IFERROR(IF(OR(M143=0,N143=0),0,(M143+N143)*2+11),0) -> 0 | Q143: =IFERROR(IF(OR(N143=0,O143=0),0,(N143+O143)-16),0) -> 0 | R143: =P143*Q143/1000000 -> 0 | S143: =IF(L143="Custom", R143*'[2]RFQ_Matalan Carton'!$M$40, IFERROR(VLOOKUP(L143,'[2]Carton Sizes Chart'!$A$4:$E$15,5,FALSE),0)) -> 0 | T143: =S143 -> 0 | U143: =I143*T143 -> 0 | V143: =((T143*I143)-W143)*4% -> 0 | W143: =S143*I143*5% -> 0
J144: Standard Carton-Singles | K144: BC-Flute | L144: Custom | M144: {=IF(L144="",0,_xlfn.SWITCH(L144,"A1",495,"A2",495,"A3",495,"Custom",0,595))} -> 0 | N144: {=IF(L144="",0,_xlfn.SWITCH(L144,"C1",325,"C2",325,"C3",325,"D1",380,"D2",380,"D3",380,"Custom",0,285))} -> 0 | O144: =IF(L144="",0,_xlfn.SWITCH(L144,"A1",375,"B1",375,"C1",375,"D1",375,"A2",310,"B2",310,"C2",310,"D2",310,"Custom",0,260)) -> 0 | P144: =IFERROR(IF(OR(M144=0,N144=0),0,(M144+N144)*2+11),0) -> 0 | Q144: =IFERROR(IF(OR(N144=0,O144=0),0,(N144+O144)-16),0) -> 0 | R144: =P144*Q144/1000000 -> 0 | S144: =IF(L144="Custom", R144*'[2]RFQ_Matalan Carton'!$M$40, IFERROR(VLOOKUP(L144,'[2]Carton Sizes Chart'!$A$4:$E$15,5,FALSE),0)) -> 0 | T144: =S144 -> 0 | U144: =I144*T144 -> 0 | V144: =((T144*I144)-W144)*4% -> 0 | W144: =S144*I144*5% -> 0
J145: Standard Carton-Singles | K145: BC-Flute | L145: Custom | M145: {=IF(L145="",0,_xlfn.SWITCH(L145,"A1",495,"A2",495,"A3",495,"Custom",0,595))} -> 0 | N145: {=IF(L145="",0,_xlfn.SWITCH(L145,"C1",325,"C2",325,"C3",325,"D1",380,"D2",380,"D3",380,"Custom",0,285))} -> 0 | O145: =IF(L145="",0,_xlfn.SWITCH(L145,"A1",375,"B1",375,"C1",375,"D1",375,"A2",310,"B2",310,"C2",310,"D2",310,"Custom",0,260)) -> 0 | P145: =IFERROR(IF(OR(M145=0,N145=0),0,(M145+N145)*2+11),0) -> 0 | Q145: =IFERROR(IF(OR(N145=0,O145=0),0,(N145+O145)-16),0) -> 0 | R145: =P145*Q145/1000000 -> 0 | S145: =IF(L145="Custom", R145*'[2]RFQ_Matalan Carton'!$M$40, IFERROR(VLOOKUP(L145,'[2]Carton Sizes Chart'!$A$4:$E$15,5,FALSE),0)) -> 0 | T145: =S145 -> 0 | U145: =I145*T145 -> 0 | V145: =((T145*I145)-W145)*4% -> 0 | W145: =S145*I145*5% -> 0
J146: Standard Carton-Singles | K146: BC-Flute | L146: Custom | M146: {=IF(L146="",0,_xlfn.SWITCH(L146,"A1",495,"A2",495,"A3",495,"Custom",0,595))} -> 0 | N146: {=IF(L146="",0,_xlfn.SWITCH(L146,"C1",325,"C2",325,"C3",325,"D1",380,"D2",380,"D3",380,"Custom",0,285))} -> 0 | O146: =IF(L146="",0,_xlfn.SWITCH(L146,"A1",375,"B1",375,"C1",375,"D1",375,"A2",310,"B2",310,"C2",310,"D2",310,"Custom",0,260)) -> 0 | P146: =IFERROR(IF(OR(M146=0,N146=0),0,(M146+N146)*2+11),0) -> 0 | Q146: =IFERROR(IF(OR(N146=0,O146=0),0,(N146+O146)-16),0) -> 0 | R146: =P146*Q146/1000000 -> 0 | S146: =IF(L146="Custom", R146*'[2]RFQ_Matalan Carton'!$M$40, IFERROR(VLOOKUP(L146,'[2]Carton Sizes Chart'!$A$4:$E$15,5,FALSE),0)) -> 0 | T146: =S146 -> 0 | U146: =I146*T146 -> 0 | V146: =((T146*I146)-W146)*4% -> 0 | W146: =S146*I146*5% -> 0
J147: Standard Carton-Singles | K147: BC-Flute | L147: Custom | M147: {=IF(L147="",0,_xlfn.SWITCH(L147,"A1",495,"A2",495,"A3",495,"Custom",0,595))} -> 0 | N147: {=IF(L147="",0,_xlfn.SWITCH(L147,"C1",325,"C2",325,"C3",325,"D1",380,"D2",380,"D3",380,"Custom",0,285))} -> 0 | O147: =IF(L147="",0,_xlfn.SWITCH(L147,"A1",375,"B1",375,"C1",375,"D1",375,"A2",310,"B2",310,"C2",310,"D2",310,"Custom",0,260)) -> 0 | P147: =IFERROR(IF(OR(M147=0,N147=0),0,(M147+N147)*2+11),0) -> 0 | Q147: =IFERROR(IF(OR(N147=0,O147=0),0,(N147+O147)-16),0) -> 0 | R147: =P147*Q147/1000000 -> 0 | S147: =IF(L147="Custom", R147*'[2]RFQ_Matalan Carton'!$M$40, IFERROR(VLOOKUP(L147,'[2]Carton Sizes Chart'!$A$4:$E$15,5,FALSE),0)) -> 0 | T147: =S147 -> 0 | U147: =I147*T147 -> 0 | V147: =((T147*I147)-W147)*4% -> 0 | W147: =S147*I147*5% -> 0
J148: Standard Carton-Singles | K148: BC-Flute | L148: Custom | M148: {=IF(L148="",0,_xlfn.SWITCH(L148,"A1",495,"A2",495,"A3",495,"Custom",0,595))} -> 0 | N148: {=IF(L148="",0,_xlfn.SWITCH(L148,"C1",325,"C2",325,"C3",325,"D1",380,"D2",380,"D3",380,"Custom",0,285))} -> 0 | O148: =IF(L148="",0,_xlfn.SWITCH(L148,"A1",375,"B1",375,"C1",375,"D1",375,"A2",310,"B2",310,"C2",310,"D2",310,"Custom",0,260)) -> 0 | P148: =IFERROR(IF(OR(M148=0,N148=0),0,(M148+N148)*2+11),0) -> 0 | Q148: =IFERROR(IF(OR(N148=0,O148=0),0,(N148+O148)-16),0) -> 0 | R148: =P148*Q148/1000000 -> 0 | S148: =IF(L148="Custom", R148*'[2]RFQ_Matalan Carton'!$M$40, IFERROR(VLOOKUP(L148,'[2]Carton Sizes Chart'!$A$4:$E$15,5,FALSE),0)) -> 0 | T148: =S148 -> 0 | U148: =I148*T148 -> 0 | V148: =((T148*I148)-W148)*4% -> 0 | W148: =S148*I148*5% -> 0
...

Sheet TRACK_CUS
I1: =SUBTOTAL(9,I3:I446) -> 31386 | U1: =SUBTOTAL(9,U3:U446) -> 27383.781 | V1: =SUBTOTAL(9,V3:V446) -> 1848.4052 | W1: =SUBTOTAL(9,W3:W446) -> 2738.3781
A2: PO Received Date | B2: Shipment Date | C2: Matalan Product PO# | D2: Supplier Name | E2: Factory Name | F2: Packaging Supplier Name | G2: eBiz Customer Reference # | H2: eBiz Sales Order # | I2: Carton QTY | J2: Carton Style | K2: FLUTE | L2: Carton Selection | M2: Length(mm) | N2: Width(mm) | O2: Height(mm) | P2: L | Q2: W | R2: Area(sqm) | S2: Carton's Unit Price (CNY,EXW w/VAT) | T2: Final Price, CNY/CTN | U2: Total Amount | V2: 7.5% for PACD | W2: Rebates for Matalan (Ratio&Custom=10%) | X2: NOTE
A3: 46235 | B3: 46237 | D3: KDS IDR Ltd. | E3: KDS IDR Ltd. | F3: Transworld Packaging (BD) Ltd. | G3: B0496925 | H3: 7124457 | I3: 190 | J3: Ratio Carton | K3: C-Flute | L3: R-FPC | M3: {=IFERROR(_xlfn.SWITCH(L3,"R-FPA",495,"R-FPB",595,"R-FPC",595,"R-FPD",595,"Custom Carton","input L"),0)} -> 595 | N3: {=IFERROR(_xlfn.SWITCH(L3,"R-FPA",285,"R-FPB",285,"R-FPC",325,"R-FPD",380,"Custom Carton","input W"),0)} -> 325 | O3: 100 | P3: =IFERROR(IF(K3="",0,(M3+N3)*2+15),0) -> 1855 | Q3: =IFERROR(IF(K3="",0,(N3+O3)-10),0) -> 415 | R3: =P3 * Q3 * (1 + 2.5%) / 1000000 -> 0.78907062 | S3: =R3*'RFQ_Matalan Carton'!$M$32 -> 0.81274274 | T3: =S3 -> 0.81274274 | U3: =I3*T3 -> 154.42112 | V3: =((T3*I3)-W3)*7.5% -> 10.423426 | W3: =S3*I3*10% -> 15.442112
A4: 46235 | B4: 46237 | D4: KDS IDR Ltd. | E4: KDS IDR Ltd. | F4: Transworld Packaging (BD) Ltd. | G4: B0496925 | H4: 7124457 | I4: 190 | J4: Ratio Carton | K4: C-Flute | L4: R-FPC | M4: {=IFERROR(_xlfn.SWITCH(L4,"R-FPA",495,"R-FPB",595,"R-FPC",595,"R-FPD",595,"Custom Carton","input L"),0)} -> 595 | N4: {=IFERROR(_xlfn.SWITCH(L4,"R-FPA",285,"R-FPB",285,"R-FPC",325,"R-FPD",380,"Custom Carton","input W"),0)} -> 325 | O4: 230 | P4: =IFERROR(IF(K4="",0,(M4+N4)*2+15),0) -> 1855 | Q4: =IFERROR(IF(K4="",0,(N4+O4)-10),0) -> 545 | R4: =P4 * Q4 * (1 + 2.5%) / 1000000 -> 1.0362494 | S4: =R4*'RFQ_Matalan Carton'!$M$32 -> 1.0673369 | T4: =S4 -> 1.0673369 | U4: =I4*T4 -> 202.794 | V4: =((T4*I4)-W4)*7.5% -> 13.688595 | W4: =S4*I4*10% -> 20.2794
A5: 46235 | B5: 46237 | D5: KDS IDR Ltd. | E5: KDS IDR Ltd. | F5: Transworld Packaging (BD) Ltd. | G5: G0516728 | H5: 7125716 | I5: 525 | J5: Ratio Carton | K5: C-Flute | L5: R-FPD | M5: {=IFERROR(_xlfn.SWITCH(L5,"R-FPA",495,"R-FPB",595,"R-FPC",595,"R-FPD",595,"Custom Carton","input L"),0)} -> 595 | N5: {=IFERROR(_xlfn.SWITCH(L5,"R-FPA",285,"R-FPB",285,"R-FPC",325,"R-FPD",380,"Custom Carton","input W"),0)} -> 380 | O5: 120 | P5: =IFERROR(IF(K5="",0,(M5+N5)*2+15),0) -> 1965 | Q5: =IFERROR(IF(K5="",0,(N5+O5)-10),0) -> 490 | R5: =P5 * Q5 * (1 + 2.5%) / 1000000 -> 0.98692125 | S5: =R5*'RFQ_Matalan Carton'!$M$32 -> 1.0165289 | T5: =S5 -> 1.0165289 | U5: =I5*T5 -> 533.67767 | V5: =((T5*I5)-W5)*7.5% -> 36.023242 | W5: =S5*I5*10% -> 53.367767
A6: 46233 | B6: 46235 | D6: Design ARC Asia | E6: N.A.Z Bangladesh Ltd. | F6: Transworld Packaging (BD) Ltd. | G6: B0497801 | H6: 7126668 | I6: 338 | J6: Ratio Carton | K6: C-Flute | L6: Custom Carton | M6: 420 | N6: 360 | O6: 100 | P6: =IFERROR(IF(K6="",0,(M6+N6)*2+15),0) -> 1575 | Q6: =IFERROR(IF(K6="",0,(N6+O6)-10),0) -> 450 | R6: =P6 * Q6 * (1 + 2.5%) / 1000000 -> 0.72646875 | S6: =R6*'RFQ_Matalan Carton'!$M$32 -> 0.74826281 | T6: =S6 -> 0.74826281 | U6: =I6*T6 -> 252.91283 | V6: =((T6*I6)-W6)*7.5% -> 17.071616 | W6: =S6*I6*10% -> 25.291283
A7: 46233 | B7: 46235 | D7: Design ARC Asia | E7: N.A.Z Bangladesh Ltd. | F7: Transworld Packaging (BD) Ltd. | G7: B0497801 | H7: 7126668 | I7: 327 | J7: Ratio Carton | K7: C-Flute | L7: Custom Carton | M7: 520 | N7: 400 | O7: 110 | P7: =IFERROR(IF(K7="",0,(M7+N7)*2+15),0) -> 1855 | Q7: =IFERROR(IF(K7="",0,(N7+O7)-10),0) -> 500 | R7: =P7 * Q7 * (1 + 2.5%) / 1000000 -> 0.9506875 | S7: =R7*'RFQ_Matalan Carton'!$M$32 -> 0.97920812 | T7: =S7 -> 0.97920812 | U7: =I7*T7 -> 320.20106 | V7: =((T7*I7)-W7)*7.5% -> 21.613571 | W7: =S7*I7*10% -> 32.020106
A8: 46236 | B8: 46238 | D8: Design ARC Asia | E8: N.A.Z Bangladesh Ltd. | F8: Transworld Packaging (BD) Ltd. | G8: B0493982 | H8: 7127937 | I8: 279 | J8: Ratio Carton | K8: C-Flute | L8: Custom Carton | M8: 420 | N8: 360 | O8: 100 | P8: =IFERROR(IF(K8="",0,(M8+N8)*2+15),0) -> 1575 | Q8: =IFERROR(IF(K8="",0,(N8+O8)-10),0) -> 450 | R8: =P8 * Q8 * (1 + 2.5%) / 1000000 -> 0.72646875 | S8: =R8*'RFQ_Matalan Carton'!$M$32 -> 0.74826281 | T8: =S8 -> 0.74826281 | U8: =I8*T8 -> 208.76532 | V8: =((T8*I8)-W8)*7.5% -> 14.091659 | W8: =S8*I8*10% -> 20.876532
A9: 46236 | B9: 46238 | D9: Design ARC Asia | E9: N.A.Z Bangladesh Ltd. | F9: Transworld Packaging (BD) Ltd. | G9: B0493982 | H9: 7127937 | I9: 279 | J9: Ratio Carton | K9: C-Flute | L9: Custom Carton | M9: 520 | N9: 400 | O9: 120 | P9: =IFERROR(IF(K9="",0,(M9+N9)*2+15),0) -> 1855 | Q9: =IFERROR(IF(K9="",0,(N9+O9)-10),0) -> 510 | R9: =P9 * Q9 * (1 + 2.5%) / 1000000 -> 0.96970125 | S9: =R9*'RFQ_Matalan Carton'!$M$32 -> 0.99879229 | T9: =S9 -> 0.99879229 | U9: =I9*T9 -> 278.66305 | V9: =((T9*I9)-W9)*7.5% -> 18.809756 | W9: =S9*I9*10% -> 27.866305
A10: 46236 | B10: 46238 | D10: Design ARC Asia | E10: N.A.Z Bangladesh Ltd. | F10: Transworld Packaging (BD) Ltd. | G10: B0493982 | H10: 7127937 | I10: 4 | J10: Ratio Carton | K10: C-Flute | L10: Custom Carton | M10: 420 | N10: 300 | O10: 190 | P10: =IFERROR(IF(K10="",0,(M10+N10)*2+15),0) -> 1455 | Q10: =IFERROR(IF(K10="",0,(N10+O10)-10),0) -> 480 | R10: =P10 * Q10 * (1 + 2.5%) / 1000000 -> 0.71586 | S10: =R10*'RFQ_Matalan Carton'!$M$32 -> 0.7373358 | T10: =S10 -> 0.7373358 | U10: =I10*T10 -> 2.9493432 | V10: =((T10*I10)-W10)*7.5% -> 0.19908067 | W10: =S10*I10*10% -> 0.29493432
A11: 46236 | B11: 46238 | D11: Design ARC Asia | E11: N.A.Z Bangladesh Ltd. | F11: Transworld Packaging (BD) Ltd. | G11: B0498084 | H11: 7127940 | I11: 314 | J11: Ratio Carton | K11: C-Flute | L11: Custom Carton | M11: 380 | N11: 300 | O11: 100 | P11: =IFERROR(IF(K11="",0,(M11+N11)*2+15),0) -> 1375 | Q11: =IFERROR(IF(K11="",0,(N11+O11)-10),0) -> 390 | R11: =P11 * Q11 * (1 + 2.5%) / 1000000 -> 0.54965625 | S11: =R11*'RFQ_Matalan Carton'!$M$32 -> 0.56614594 | T11: =S11 -> 0.56614594 | U11: =I11*T11 -> 177.76982 | V11: =((T11*I11)-W11)*7.5% -> 11.999463 | W11: =S11*I11*10% -> 17.776982
A12: 46236 | B12: 46238 | D12: Design ARC Asia | E12: N.A.Z Bangladesh Ltd. | F12: Transworld Packaging (BD) Ltd. | G12: B0498084 | H12: 7127940 | I12: 314 | J12: Ratio Carton | K12: C-Flute | L12: Custom Carton | M12: 420 | N12: 300 | O12: 190 | P12: =IFERROR(IF(K12="",0,(M12+N12)*2+15),0) -> 1455 | Q12: =IFERROR(IF(K12="",0,(N12+O12)-10),0) -> 480 | R12: =P12 * Q12 * (1 + 2.5%) / 1000000 -> 0.71586 | S12: =R12*'RFQ_Matalan Carton'!$M$32 -> 0.7373358 | T12: =S12 -> 0.7373358 | U12: =I12*T12 -> 231.52344 | V12: =((T12*I12)-W12)*7.5% -> 15.627832 | W12: =S12*I12*10% -> 23.152344
A13: 46236 | B13: 46238 | D13: Design ARC Asia | E13: N.A.Z Bangladesh Ltd. | F13: Transworld Packaging (BD) Ltd. | G13: B0498016 | H13: 7127943 | I13: 320 | J13: Ratio Carton | K13: C-Flute | L13: Custom Carton | M13: 300 | N13: 250 | O13: 100 | P13: =IFERROR(IF(K13="",0,(M13+N13)*2+15),0) -> 1115 | Q13: =IFERROR(IF(K13="",0,(N13+O13)-10),0) -> 340 | R13: =P13 * Q13 * (1 + 2.5%) / 1000000 -> 0.3885775 | S13: =R13*'RFQ_Matalan Carton'!$M$32 -> 0.40023482 | T13: =S13 -> 0.40023482 | U13: =I13*T13 -> 128.07514 | V13: =((T13*I13)-W13)*7.5% -> 8.6450722 | W13: =S13*I13*10% -> 12.807514
A14: 46236 | B14: 46238 | D14: Design ARC Asia | E14: N.A.Z Bangladesh Ltd. | F14: Transworld Packaging (BD) Ltd. | G14: B0498016 | H14: 7127943 | I14: 314 | J14: Ratio Carton | K14: C-Flute | L14: Custom Carton | M14: 490 | N14: 300 | O14: 120 | P14: =IFERROR(IF(K14="",0,(M14+N14)*2+15),0) -> 1595 | Q14: =IFERROR(IF(K14="",0,(N14+O14)-10),0) -> 410 | R14: =P14 * Q14 * (1 + 2.5%) / 1000000 -> 0.67029875 | S14: =R14*'RFQ_Matalan Carton'!$M$32 -> 0.69040771 | T14: =S14 -> 0.69040771 | U14: =I14*T14 -> 216.78802 | V14: =((T14*I14)-W14)*7.5% -> 14.633191 | W14: =S14*I14*10% -> 21.678802
A15: 46236 | B15: 46238 | D15: Design ARC Asia | E15: N.A.Z Bangladesh Ltd. | F15: Transworld Packaging (BD) Ltd. | G15: C0992251 | H15: 7127946 | I15: 224 | J15: Ratio Carton | K15: C-Flute | L15: Custom Carton | M15: 460 | N15: 320 | O15: 100 | P15: =IFERROR(IF(K15="",0,(M15+N15)*2+15),0) -> 1575 | Q15: =IFERROR(IF(K15="",0,(N15+O15)-10),0) -> 410 | R15: =P15 * Q15 * (1 + 2.5%) / 1000000 -> 0.66189375 | S15: =R15*'RFQ_Matalan Carton'!$M$32 -> 0.68175056 | T15: =S15 -> 0.68175056 | U15: =I15*T15 -> 152.71213 | V15: =((T15*I15)-W15)*7.5% -> 10.308069 | W15: =S15*I15*10% -> 15.271213
A16: 46236 | B16: 46238 | D16: Design ARC Asia | E16: N.A.Z Bangladesh Ltd. | F16: Transworld Packaging (BD) Ltd. | G16: C0992251 | H16: 7127946 | I16: 224 | J16: Ratio Carton | K16: C-Flute | L16: Custom Carton | M16: 540 | N16: 380 | O16: 100 | P16: =IFERROR(IF(K16="",0,(M16+N16)*2+15),0) -> 1855 | Q16: =IFERROR(IF(K16="",0,(N16+O16)-10),0) -> 470 | R16: =P16 * Q16 * (1 + 2.5%) / 1000000 -> 0.89364625 | S16: =R16*'RFQ_Matalan Carton'!$M$32 -> 0.92045564 | T16: =S16 -> 0.92045564 | U16: =I16*T16 -> 206.18206 | V16: =((T16*I16)-W16)*7.5% -> 13.917289 | W16: =S16*I16*10% -> 20.618206
A17: 46236 | B17: 46238 | D17: Design ARC Asia | E17: N.A.Z Bangladesh Ltd. | F17: Transworld Packaging (BD) Ltd. | G17: C1002485 | H17: 7127949 | I17: 130 | J17: Ratio Carton | K17: C-Flute | L17: Custom Carton | M17: 420 | N17: 350 | O17: 100 | P17: =IFERROR(IF(K17="",0,(M17+N17)*2+15),0) -> 1555 | Q17: =IFERROR(IF(K17="",0,(N17+O17)-10),0) -> 440 | R17: =P17 * Q17 * (1 + 2.5%) / 1000000 -> 0.701305 | S17: =R17*'RFQ_Matalan Carton'!$M$32 -> 0.72234415 | T17: =S17 -> 0.72234415 | U17: =I17*T17 -> 93.904739 | V17: =((T17*I17)-W17)*7.5% -> 6.3385699 | W17: =S17*I17*10% -> 9.3904739
A18: 46236 | B18: 46238 | D18: Design ARC Asia | E18: N.A.Z Bangladesh Ltd. | F18: Transworld Packaging (BD) Ltd. | G18: C1002485 | H18: 7127949 | I18: 125 | J18: Ratio Carton | K18: C-Flute | L18: Custom Carton | M18: 450 | N18: 380 | O18: 140 | P18: =IFERROR(IF(K18="",0,(M18+N18)*2+15),0) -> 1675 | Q18: =IFERROR(IF(K18="",0,(N18+O18)-10),0) -> 510 | R18: =P18 * Q18 * (1 + 2.5%) / 1000000 -> 0.87560625 | S18: =R18*'RFQ_Matalan Carton'!$M$32 -> 0.90187444 | T18: =S18 -> 0.90187444 | U18: =I18*T18 -> 112.7343 | V18: =((T18*I18)-W18)*7.5% -> 7.6095656 | W18: =S18*I18*10% -> 11.27343
A19: 46240 | B19: 46243 | D19: KDS IDR Ltd. | E19: KDS IDR Ltd. | F19: Transworld Packaging (BD) Ltd. | G19: G0516742 | H19: 7130655 | I19: 145 | J19: Ratio Carton | K19: C-Flute | L19: R-FPD | M19: {=IFERROR(_xlfn.SWITCH(L19,"R-FPA",495,"R-FPB",595,"R-FPC",595,"R-FPD",595,"Custom Carton","input L"),0)} -> 595 | N19: {=IFERROR(_xlfn.SWITCH(L19,"R-FPA",285,"R-FPB",285,"R-FPC",325,"R-FPD",380,"Custom Carton","input W"),0)} -> 380 | O19: 180 | P19: =IFERROR(IF(K19="",0,(M19+N19)*2+15),0) -> 1965 | Q19: =IFERROR(IF(K19="",0,(N19+O19)-10),0) -> 550 | R19: =P19 * Q19 * (1 + 2.5%) / 1000000 -> 1.1077687 | S19: =R19*'RFQ_Matalan Carton'!$M$32 -> 1.1410018 | T19: =S19 -> 1.1410018 | U19: =I19*T19 -> 165.44526 | V19: =((T19*I19)-W19)*7.5% -> 11.167555 | W19: =S19*I19*10% -> 16.544526
A20: 46240 | B20: 46243 | D20: KDS IDR Ltd. | E20: KDS IDR Ltd. | F20: Transworld Packaging (BD) Ltd. | G20: G0516742 | H20: 7130655 | I20: 145 | J20: Ratio Carton | K20: C-Flute | L20: R-FPD | M20: {=IFERROR(_xlfn.SWITCH(L20,"R-FPA",495,"R-FPB",595,"R-FPC",595,"R-FPD",595,"Custom Carton","input L"),0)} -> 595 | N20: {=IFERROR(_xlfn.SWITCH(L20,"R-FPA",285,"R-FPB",285,"R-FPC",325,"R-FPD",380,"Custom Carton","input W"),0)} -> 380 | O20: 220 | P20: =IFERROR(IF(K20="",0,(M20+N20)*2+15),0) -> 1965 | Q20: =IFERROR(IF(K20="",0,(N20+O20)-10),0) -> 590 | R20: =P20 * Q20 * (1 + 2.5%) / 1000000 -> 1.1883337 | S20: =R20*'RFQ_Matalan Carton'!$M$32 -> 1.2239838 | T20: =S20 -> 1.2239838 | U20: =I20*T20 -> 177.47765 | V20: =((T20*I20)-W20)*7.5% -> 11.979741 | W20: =S20*I20*10% -> 17.747765
A21: 46240 | B21: 46243 | D21: KDS IDR Ltd. | E21: KDS IDR Ltd. | F21: Transworld Packaging (BD) Ltd. | G21: C0989744 | H21: 7131103 | I21: 15 | J21: Ratio Carton | K21: C-Flute | L21: R-FPD | M21: {=IFERROR(_xlfn.SWITCH(L21,"R-FPA",495,"R-FPB",595,"R-FPC",595,"R-FPD",595,"Custom Carton","input L"),0)} -> 595 | N21: {=IFERROR(_xlfn.SWITCH(L21,"R-FPA",285,"R-FPB",285,"R-FPC",325,"R-FPD",380,"Custom Carton","input W"),0)} -> 380 | O21: 300 | P21: =IFERROR(IF(K21="",0,(M21+N21)*2+15),0) -> 1965 | Q21: =IFERROR(IF(K21="",0,(N21+O21)-10),0) -> 670 | R21: =P21 * Q21 * (1 + 2.5%) / 1000000 -> 1.3494637 | S21: =R21*'RFQ_Matalan Carton'!$M$32 -> 1.3899477 | T21: =S21 -> 1.3899477 | U21: =I21*T21 -> 20.849215 | V21: =((T21*I21)-W21)*7.5% -> 1.407322 | W21: =S21*I21*10% -> 2.0849215
A22: 46243 | B22: 46244 | D22: Design ARC Asia | E22: N.A.Z Bangladesh Ltd. | F22: Transworld Packaging (BD) Ltd. | G22: DHW6LBF031 | H22: 7132164 | I22: 317 | J22: Ratio Carton | K22: C-Flute | L22: Custom Carton | M22: 390 | N22: 350 | O22: 100 | P22: =IFERROR(IF(K22="",0,(M22+N22)*2+15),0) -> 1495 | Q22: =IFERROR(IF(K22="",0,(N22+O22)-10),0) -> 440 | R22: =P22 * Q22 * (1 + 2.5%) / 1000000 -> 0.674245 | S22: =R22*'RFQ_Matalan Carton'!$M$32 -> 0.69447235 | T22: =S22 -> 0.69447235 | U22: =I22*T22 -> 220.14773 | V22: =((T22*I22)-W22)*7.5% -> 14.859972 | W22: =S22*I22*10% -> 22.014773
A23: 46243 | B23: 46244 | D23: Design ARC Asia | E23: N.A.Z Bangladesh Ltd. | F23: Transworld Packaging (BD) Ltd. | G23: DHW6LBF031 | H23: 7132164 | I23: 317 | J23: Ratio Carton | K23: C-Flute | L23: Custom Carton | M23: 420 | N23: 370 | O23: 100 | P23: =IFERROR(IF(K23="",0,(M23+N23)*2+15),0) -> 1595 | Q23: =IFERROR(IF(K23="",0,(N23+O23)-10),0) -> 460 | R23: =P23 * Q23 * (1 + 2.5%) / 1000000 -> 0.7520425 | S23: =R23*'RFQ_Matalan Carton'!$M$32 -> 0.77460377 | T23: =S23 -> 0.77460377 | U23: =I23*T23 -> 245.5494 | V23: =((T23*I23)-W23)*7.5% -> 16.574584 | W23: =S23*I23*10% -> 24.55494
A24: 46243 | B24: 46244 | D24: Design ARC Asia | E24: N.A.Z Bangladesh Ltd. | F24: Transworld Packaging (BD) Ltd. | G24: DHW6LBF031 | H24: 7132164 | I24: 317 | J24: Ratio Carton | K24: C-Flute | L24: Custom Carton | M24: 480 | N24: 430 | O24: 100 | P24: =IFERROR(IF(K24="",0,(M24+N24)*2+15),0) -> 1835 | Q24: =IFERROR(IF(K24="",0,(N24+O24)-10),0) -> 520 | R24: =P24 * Q24 * (1 + 2.5%) / 1000000 -> 0.978055 | S24: =R24*'RFQ_Matalan Carton'!$M$32 -> 1.0073967 | T24: =S24 -> 1.0073967 | U24: =I24*T24 -> 319.34474 | V24: =((T24*I24)-W24)*7.5% -> 21.55577 | W24: =S24*I24*10% -> 31.934474
A25: 46245 | B25: 46247 | D25: Design ARC Asia | E25: N.A.Z Bangladesh Ltd. | F25: Transworld Packaging (BD) Ltd. | G25: DHW6DBF21A | H25: 7132915 | I25: 324 | J25: Ratio Carton | K25: C-Flute | L25: Custom Carton | M25: 400 | N25: 360 | O25: 100 | P25: =IFERROR(IF(K25="",0,(M25+N25)*2+15),0) -> 1535 | Q25: =IFERROR(IF(K25="",0,(N25+O25)-10),0) -> 450 | R25: =P25 * Q25 * (1 + 2.5%) / 1000000 -> 0.70801875 | S25: =R25*'RFQ_Matalan Carton'!$M$32 -> 0.72925931 | T25: =S25 -> 0.72925931 | U25: =I25*T25 -> 236.28002 | V25: =((T25*I25)-W25)*7.5% -> 15.948901 | W25: =S25*I25*10% -> 23.628002
A26: 46245 | B26: 46247 | D26: Design ARC Asia | E26: N.A.Z Bangladesh Ltd. | F26: Transworld Packaging (BD) Ltd. | G26: DHW6DBF21A | H26: 7132915 | I26: 323 | J26: Ratio Carton | K26: C-Flute | L26: Custom Carton | M26: 460 | N26: 420 | O26: 210 | P26: =IFERROR(IF(K26="",0,(M26+N26)*2+15),0) -> 1775 | Q26: =IFERROR(IF(K26="",0,(N26+O26)-10),0) -> 620 | R26: =P26 * Q26 * (1 + 2.5%) / 1000000 -> 1.1280125 | S26: =R26*'RFQ_Matalan Carton'!$M$32 -> 1.1618529 | T26: =S26 -> 1.1618529 | U26: =I26*T26 -> 375.27848 | V26: =((T26*I26)-W26)*7.5% -> 25.331297 | W26: =S26*I26*10% -> 37.527848
A27: 46245 | B27: 46247 | D27: Design ARC Asia | E27: N.A.Z Bangladesh Ltd. | F27: Transworld Packaging (BD) Ltd. | G27: SPS26BT02 | H27: 7132933 | I27: 299 | J27: Ratio Carton | K27: C-Flute | L27: Custom Carton | M27: 460 | N27: 420 | O27: 100 | P27: =IFERROR(IF(K27="",0,(M27+N27)*2+15),0) -> 1775 | Q27: =IFERROR(IF(K27="",0,(N27+O27)-10),0) -> 510 | R27: =P27 * Q27 * (1 + 2.5%) / 1000000 -> 0.92788125 | S27: =R27*'RFQ_Matalan Carton'!$M$32 -> 0.95571769 | T27: =S27 -> 0.95571769 | U27: =I27*T27 -> 285.75959 | V27: =((T27*I27)-W27)*7.5% -> 19.288772 | W27: =S27*I27*10% -> 28.575959
A28: 46245 | B28: 46247 | D28: Design ARC Asia | E28: N.A.Z Bangladesh Ltd. | F28: Transworld Packaging (BD) Ltd. | G28: SPS26BT02 | H28: 7132933 | I28: 293 | J28: Ratio Carton | K28: C-Flute | L28: Custom Carton | M28: 500 | N28: 420 | O28: 120 | P28: =IFERROR(IF(K28="",0,(M28+N28)*2+15),0) -> 1855 | Q28: =IFERROR(IF(K28="",0,(N28+O28)-10),0) -> 530 | R28: =P28 * Q28 * (1 + 2.5%) / 1000000 -> 1.0077287 | S28: =R28*'RFQ_Matalan Carton'!$M$32 -> 1.0379606 | T28: =S28 -> 1.0379606 | U28: =I28*T28 -> 304.12246 | V28: =((T28*I28)-W28)*7.5% -> 20.528266 | W28: =S28*I28*10% -> 30.412246
A29: 46247 | B29: 46249 | D29: Design ARC Asia | E29: N.A.Z Bangladesh Ltd. | F29: Transworld Packaging (BD) Ltd. | G29: GCW265TS04A | H29: 7134055 | I29: 301 | J29: Ratio Carton | K29: C-Flute | L29: Custom Carton | M29: 400 | N29: 300 | O29: 100 | P29: =IFERROR(IF(K29="",0,(M29+N29)*2+15),0) -> 1415 | Q29: =IFERROR(IF(K29="",0,(N29+O29)-10),0) -> 390 | R29: =P29 * Q29 * (1 + 2.5%) / 1000000 -> 0.56564625 | S29: =R29*'RFQ_Matalan Carton'!$M$32 -> 0.58261564 | T29: =S29 -> 0.58261564 | U29: =I29*T29 -> 175.36731 | V29: =((T29*I29)-W29)*7.5% -> 11.837293 | W29: =S29*I29*10% -> 17.536731
A30: 46247 | B30: 46249 | D30: Design ARC Asia | E30: N.A.Z Bangladesh Ltd. | F30: Transworld Packaging (BD) Ltd. | G30: GCW265TS04A | H30: 7134055 | I30: 301 | J30: Ratio Carton | K30: C-Flute | L30: Custom Carton | M30: 420 | N30: 360 | O30: 220 | P30: =IFERROR(IF(K30="",0,(M30+N30)*2+15),0) -> 1575 | Q30: =IFERROR(IF(K30="",0,(N30+O30)-10),0) -> 570 | R30: =P30 * Q30 * (1 + 2.5%) / 1000000 -> 0.92019375 | S30: =R30*'RFQ_Matalan Carton'!$M$32 -> 0.94779956 | T30: =S30 -> 0.94779956 | U30: =I30*T30 -> 285.28767 | V30: =((T30*I30)-W30)*7.5% -> 19.256918 | W30: =S30*I30*10% -> 28.528767
A31: 46247 | B31: 46249 | D31: Design ARC Asia | E31: N.A.Z Bangladesh Ltd. | F31: Transworld Packaging (BD) Ltd. | G31: DHW6DBF22A | H31: 7134646 | I31: 320 | J31: Ratio Carton | K31: C-Flute | L31: Custom Carton | M31: 380 | N31: 260 | O31: 100 | P31: =IFERROR(IF(K31="",0,(M31+N31)*2+15),0) -> 1295 | Q31: =IFERROR(IF(K31="",0,(N31+O31)-10),0) -> 350 | R31: =P31 * Q31 * (1 + 2.5%) / 1000000 -> 0.46458125 | S31: =R31*'RFQ_Matalan Carton'!$M$32 -> 0.47851869 | T31: =S31 -> 0.47851869 | U31: =I31*T31 -> 153.12598 | V31: =((T31*I31)-W31)*7.5% -> 10.336004 | W31: =S31*I31*10% -> 15.312598
A32: 46247 | B32: 46249 | D32: Design ARC Asia | E32: N.A.Z Bangladesh Ltd. | F32: Transworld Packaging (BD) Ltd. | G32: DHW6DBF22A | H32: 7134646 | I32: 320 | J32: Ratio Carton | K32: C-Flute | L32: Custom Carton | M32: 440 | N32: 330 | O32: 120 | P32: =IFERROR(IF(K32="",0,(M32+N32)*2+15),0) -> 1555 | Q32: =IFERROR(IF(K32="",0,(N32+O32)-10),0) -> 440 | R32: =P32 * Q32 * (1 + 2.5%) / 1000000 -> 0.701305 | S32: =R32*'RFQ_Matalan Carton'!$M$32 -> 0.72234415 | T32: =S32 -> 0.72234415 | U32: =I32*T32 -> 231.15013 | V32: =((T32*I32)-W32)*7.5% -> 15.602634 | W32: =S32*I32*10% -> 23.115013
A33: 46247 | B33: 46249 | D33: Design ARC Asia | E33: N.A.Z Bangladesh Ltd. | F33: Transworld Packaging (BD) Ltd. | G33: GCW25TS04A | H33: 7134668 | I33: 279 | J33: Ratio Carton | K33: C-Flute | L33: Custom Carton | M33: 300 | N33: 250 | O33: 100 | P33: =IFERROR(IF(K33="",0,(M33+N33)*2+15),0) -> 1115 | Q33: =IFERROR(IF(K33="",0,(N33+O33)-10),0) -> 340 | R33: =P33 * Q33 * (1 + 2.5%) / 1000000 -> 0.3885775 | S33: =R33*'RFQ_Matalan Carton'!$M$32 -> 0.40023482 | T33: =S33 -> 0.40023482 | U33: =I33*T33 -> 111.66552 | V33: =((T33*I33)-W33)*7.5% -> 7.5374223 | W33: =S33*I33*10% -> 11.166552
... A36: 46247 | B36: 46249 | D36: Design ARC Asia | E36: N.A.Z Bangladesh Ltd. | F36: Transworld Packaging (BD) Ltd. | G36: GCW26SE20A | H36: 7134857 | I36: 271 | J36: Ratio Carton | K36: C-Flute | L36: Custom Carton | M36: 500 | N36: 420 | O36: 230 | P36: =IFERROR(IF(K36="",0,(M36+N36)*2+15),0) -> 1855 | Q36: =IFERROR(IF(K36="",0,(N36+O36)-10),0) -> 640 | R36: =P36 * Q36 * (1 + 2.5%) / 1000000 -> 1.21688 | S36: =R36*'RFQ_Matalan Carton'!$M$32 -> 1.2533864 | T36: =S36 -> 1.2533864 | U36: =I36*T36 -> 339.66771 | V36: =((T36*I36)-W36)*7.5% -> 22.927571 | W36: =S36*I36*10% -> 33.966771
A37: 46250 | B37: 46251 | D37: KDS IDR Ltd. | E37: KDS IDR Ltd. | F37: Transworld Packaging (BD) Ltd. | G37: B0494456 | H37: 7135559 | I37: 290 | J37: Ratio Carton | K37: C-Flute | L37: R-FPD | M37: {=IFERROR(_xlfn.SWITCH(L37,"R-FPA",495,"R-FPB",595,"R-FPC",595,"R-FPD",595,"Custom Carton","input L"),0)} -> 595 | N37: {=IFERROR(_xlfn.SWITCH(L37,"R-FPA",285,"R-FPB",285,"R-FPC",325,"R-FPD",380,"Custom Carton","input W"),0)} -> 380 | O37: 100 | P37: =IFERROR(IF(K37="",0,(M37+N37)*2+15),0) -> 1965 | Q37: =IFERROR(IF(K37="",0,(N37+O37)-10),0) -> 470 | R37: =P37 * Q37 * (1 + 2.5%) / 1000000 -> 0.94663875 | S37: =R37*'RFQ_Matalan Carton'!$M$32 -> 0.97503791 | T37: =S37 -> 0.97503791 | U37: =I37*T37 -> 282.76099 | V37: =((T37*I37)-W37)*7.5% -> 19.086367 | W37: =S37*I37*10% -> 28.276099
A38: 46250 | B38: 46251 | D38: KDS IDR Ltd. | E38: KDS IDR Ltd. | F38: Transworld Packaging (BD) Ltd. | G38: B0494456 | H38: 7135559 | I38: 290 | J38: Ratio Carton | K38: C-Flute | L38: R-FPD | M38: {=IFERROR(_xlfn.SWITCH(L38,"R-FPA",495,"R-FPB",595,"R-FPC",595,"R-FPD",595,"Custom Carton","input L"),0)} -> 595 | N38: {=IFERROR(_xlfn.SWITCH(L38,"R-FPA",285,"R-FPB",285,"R-FPC",325,"R-FPD",380,"Custom Carton","input W"),0)} -> 380 | O38: 220 | P38: =IFERROR(IF(K38="",0,(M38+N38)*2+15),0) -> 1965 | Q38: =IFERROR(IF(K38="",0,(N38+O38)-10),0) -> 590 | R38: =P38 * Q38 * (1 + 2.5%) / 1000000 -> 1.1883337 | S38: =R38*'RFQ_Matalan Carton'!$M$32 -> 1.2239838 | T38: =S38 -> 1.2239838 | U38: =I38*T38 -> 354.95529 | V38: =((T38*I38)-W38)*7.5% -> 23.959482 | W38: =S38*I38*10% -> 35.495529
A39: 46250 | B39: 46251 | D39: KDS IDR Ltd. | E39: KDS IDR Ltd. | F39: Transworld Packaging (BD) Ltd. | G39: B0498208 | H39: 7135563 | I39: 310 | J39: Ratio Carton | K39: C-Flute | L39: R-FPC | M39: {=IFERROR(_xlfn.SWITCH(L39,"R-FPA",495,"R-FPB",595,"R-FPC",595,"R-FPD",595,"Custom Carton","input L"),0)} -> 595 | N39: {=IFERROR(_xlfn.SWITCH(L39,"R-FPA",285,"R-FPB",285,"R-FPC",325,"R-FPD",380,"Custom Carton","input W"),0)} -> 325 | O39: 100 | P39: =IFERROR(IF(K39="",0,(M39+N39)*2+15),0) -> 1855 | Q39: =IFERROR(IF(K39="",0,(N39+O39)-10),0) -> 415 | R39: =P39 * Q39 * (1 + 2.5%) / 1000000 -> 0.78907062 | S39: =R39*'RFQ_Matalan Carton'!$M$32 -> 0.81274274 | T39: =S39 -> 0.81274274 | U39: =I39*T39 -> 251.95025 | V39: =((T39*I39)-W39)*7.5% -> 17.006642 | W39: =S39*I39*10% -> 25.195025
A40: 46250 | B40: 46251 | D40: KDS IDR Ltd. | E40: KDS IDR Ltd. | F40: Transworld Packaging (BD) Ltd. | G40: B0498208 | H40: 7135563 | I40: 310 | J40: Ratio Carton | K40: C-Flute | L40: R-FPC | M40: {=IFERROR(_xlfn.SWITCH(L40,"R-FPA",495,"R-FPB",595,"R-FPC",595,"R-FPD",595,"Custom Carton","input L"),0)} -> 595 | N40: {=IFERROR(_xlfn.SWITCH(L40,"R-FPA",285,"R-FPB",285,"R-FPC",325,"R-FPD",380,"Custom Carton","input W"),0)} -> 325 | O40: 270 | P40: =IFERROR(IF(K40="",0,(M40+N40)*2+15),0) -> 1855 | Q40: =IFERROR(IF(K40="",0,(N40+O40)-10),0) -> 585 | R40: =P40 * Q40 * (1 + 2.5%) / 1000000 -> 1.1123044 | S40: =R40*'RFQ_Matalan Carton'!$M$32 -> 1.1456735 | T40: =S40 -> 1.1456735 | U40: =I40*T40 -> 355.15879 | V40: =((T40*I40)-W40)*7.5% -> 23.973218 | W40: =S40*I40*10% -> 35.515879
A41: 46250 | B41: 46251 | D41: KDS IDR Ltd. | E41: KDS IDR Ltd. | F41: Transworld Packaging (BD) Ltd. | G41: C0990206 | H41: 7135574 | I41: 300 | J41: Ratio Carton | K41: C-Flute | L41: R-FPC | M41: {=IFERROR(_xlfn.SWITCH(L41,"R-FPA",495,"R-FPB",595,"R-FPC",595,"R-FPD",595,"Custom Carton","input L"),0)} -> 595 | N41: {=IFERROR(_xlfn.SWITCH(L41,"R-FPA",285,"R-FPB",285,"R-FPC",325,"R-FPD",380,"Custom Carton","input W"),0)} -> 325 | O41: 100 | P41: =IFERROR(IF(K41="",0,(M41+N41)*2+15),0) -> 1855 | Q41: =IFERROR(IF(K41="",0,(N41+O41)-10),0) -> 415 | R41: =P41 * Q41 * (1 + 2.5%) / 1000000 -> 0.78907062 | S41: =R41*'RFQ_Matalan Carton'!$M$32 -> 0.81274274 | T41: =S41 -> 0.81274274 | U41: =I41*T41 -> 243.82282 | V41: =((T41*I41)-W41)*7.5% -> 16.458041 | W41: =S41*I41*10% -> 24.382282
A42: 46250 | B42: 46251 | D42: KDS IDR Ltd. | E42: KDS IDR Ltd. | F42: Transworld Packaging (BD) Ltd. | G42: C0990206 | H42: 7135574 | I42: 300 | J42: Ratio Carton | K42: C-Flute | L42: R-FPC | M42: {=IFERROR(_xlfn.SWITCH(L42,"R-FPA",495,"R-FPB",595,"R-FPC",595,"R-FPD",595,"Custom Carton","input L"),0)} -> 595 | N42: {=IFERROR(_xlfn.SWITCH(L42,"R-FPA",285,"R-FPB",285,"R-FPC",325,"R-FPD",380,"Custom Carton","input W"),0)} -> 325 | O42: 240 | P42: =IFERROR(IF(K42="",0,(M42+N42)*2+15),0) -> 1855 | Q42: =IFERROR(IF(K42="",0,(N42+O42)-10),0) -> 555 | R42: =P42 * Q42 * (1 + 2.5%) / 1000000 -> 1.0552631 | S42: =R42*'RFQ_Matalan Carton'!$M$32 -> 1.086921 | T42: =S42 -> 1.086921 | U42: =I42*T42 -> 326.07631 | V42: =((T42*I42)-W42)*7.5% -> 22.010151 | W42: =S42*I42*10% -> 32.607631
A43: 46250 | B43: 46251 | D43: KDS IDR Ltd. | E43: KDS IDR Ltd. | F43: Transworld Packaging (BD) Ltd. | G43: B0499058 | H43: 7136205 | I43: 520 | J43: Ratio Carton | K43: C-Flute | L43: R-FPD | M43: {=IFERROR(_xlfn.SWITCH(L43,"R-FPA",495,"R-FPB",595,"R-FPC",595,"R-FPD",595,"Custom Carton","input L"),0)} -> 595 | N43: {=IFERROR(_xlfn.SWITCH(L43,"R-FPA",285,"R-FPB",285,"R-FPC",325,"R-FPD",380,"Custom Carton","input W"),0)} -> 380 | O43: 100 | P43: =IFERROR(IF(K43="",0,(M43+N43)*2+15),0) -> 1965 | Q43: =IFERROR(IF(K43="",0,(N43+O43)-10),0) -> 470 | R43: =P43 * Q43 * (1 + 2.5%) / 1000000 -> 0.94663875 | S43: =R43*'RFQ_Matalan Carton'!$M$32 -> 0.97503791 | T43: =S43 -> 0.97503791 | U43: =I43*T43 -> 507.01971 | V43: =((T43*I43)-W43)*7.5% -> 34.223831 | W43: =S43*I43*10% -> 50.701971
A44: 46250 | B44: 46251 | D44: Radial International Unit2 Ltd | E44: Radial International Unit2 Ltd | F44: Transworld Packaging (BD) Ltd. | G44: ST.BE5B2,R-15517,J-458 | H44: 7136420 | I44: 6 | J44: Ratio Carton | K44: C-Flute | L44: Custom Carton | M44: 450 | N44: 260 | O44: 220 | P44: =IFERROR(IF(K44="",0,(M44+N44)*2+15),0) -> 1435 | Q44: =IFERROR(IF(K44="",0,(N44+O44)-10),0) -> 470 | R44: =P44 * Q44 * (1 + 2.5%) / 1000000 -> 0.69131125 | S44: =R44*'RFQ_Matalan Carton'!$M$32 -> 0.71205059 | T44: =S44 -> 0.71205059 | U44: =I44*T44 -> 4.2723035 | V44: =((T44*I44)-W44)*7.5% -> 0.28838049 | W44: =S44*I44*10% -> 0.42723035
A45: 46250 | B45: 46251 | D45: Radial International Unit2 Ltd | E45: Radial International Unit2 Ltd | F45: Transworld Packaging (BD) Ltd. | G45: ST.BE2S1,R-15560,J-496 | H45: 7136434 | I45: 4 | J45: Ratio Carton | K45: C-Flute | L45: Custom Carton | M45: 420 | N45: 280 | O45: 250 | P45: =IFERROR(IF(K45="",0,(M45+N45)*2+15),0) -> 1415 | Q45: =IFERROR(IF(K45="",0,(N45+O45)-10),0) -> 520 | R45: =P45 * Q45 * (1 + 2.5%) / 1000000 -> 0.754195 | S45: =R45*'RFQ_Matalan Carton'!$M$32 -> 0.77682085 | T45: =S45 -> 0.77682085 | U45: =I45*T45 -> 3.1072834 | V45: =((T45*I45)-W45)*7.5% -> 0.20974163 | W45: =S45*I45*10% -> 0.31072834
A46: 46252 | B46: 46258 | D46: Grand Apparels Design | E46: Virtual Bottom | F46: Transworld Packaging (BD) Ltd. | G46: F3071308 | H46: 7137458 | I46: 214 | J46: Ratio Carton | K46: C-Flute | L46: R-FPD | M46: {=IFERROR(_xlfn.SWITCH(L46,"R-FPA",495,"R-FPB",595,"R-FPC",595,"R-FPD",595,"Custom Carton","input L"),0)} -> 595 | N46: {=IFERROR(_xlfn.SWITCH(L46,"R-FPA",285,"R-FPB",285,"R-FPC",325,"R-FPD",380,"Custom Carton","input W"),0)} -> 380 | O46: 180 | P46: =IFERROR(IF(K46="",0,(M46+N46)*2+15),0) -> 1965 | Q46: =IFERROR(IF(K46="",0,(N46+O46)-10),0) -> 550 | R46: =P46 * Q46 * (1 + 2.5%) / 1000000 -> 1.1077687 | S46: =R46*'RFQ_Matalan Carton'!$M$32 -> 1.1410018 | T46: =S46 -> 1.1410018 | U46: =I46*T46 -> 244.17439 | V46: =((T46*I46)-W46)*7.5% -> 16.481771 | W46: =S46*I46*10% -> 24.417439
A47: 46252 | B47: 46258 | D47: Grand Apparels Design | E47: Virtual Bottom | F47: Transworld Packaging (BD) Ltd. | G47: F3071356 | H47: 7137463 | I47: 270 | J47: Ratio Carton | K47: C-Flute | L47: R-FPD | M47: {=IFERROR(_xlfn.SWITCH(L47,"R-FPA",495,"R-FPB",595,"R-FPC",595,"R-FPD",595,"Custom Carton","input L"),0)} -> 595 | N47: {=IFERROR(_xlfn.SWITCH(L47,"R-FPA",285,"R-FPB",285,"R-FPC",325,"R-FPD",380,"Custom Carton","input W"),0)} -> 380 | O47: 180 | P47: =IFERROR(IF(K47="",0,(M47+N47)*2+15),0) -> 1965 | Q47: =IFERROR(IF(K47="",0,(N47+O47)-10),0) -> 550 | R47: =P47 * Q47 * (1 + 2.5%) / 1000000 -> 1.1077687 | S47: =R47*'RFQ_Matalan Carton'!$M$32 -> 1.1410018 | T47: =S47 -> 1.1410018 | U47: =I47*T47 -> 308.07049 | V47: =((T47*I47)-W47)*7.5% -> 20.794758 | W47: =S47*I47*10% -> 30.807049
A48: 46253 | B48: 46256 | D48: Mouchak Knit Composite Ltd | E48: Mouchak Knit Composite Ltd | F48: Transworld Packaging (BD) Ltd. | G48: M2693003 | H48: 7137849 | I48: 445 | J48: Ratio Carton | K48: C-Flute | L48: Custom Carton | M48: 930 | N48: 500 | O48: 100 | P48: =IFERROR(IF(K48="",0,(M48+N48)*2+15),0) -> 2875 | Q48: =IFERROR(IF(K48="",0,(N48+O48)-10),0) -> 590 | R48: =P48 * Q48 * (1 + 2.5%) / 1000000 -> 1.7386562 | S48: =R48*'RFQ_Matalan Carton'!$M$32 -> 1.7908159 | T48: =S48 -> 1.7908159 | U48: =I48*T48 -> 796.91309 | V48: =((T48*I48)-W48)*7.5% -> 53.791634 | W48: =S48*I48*10% -> 79.691309
A49: 46253 | B49: 46256 | D49: Design ARC Asia | E49: N.A.Z Bangladesh Ltd. | F49: Transworld Packaging (BD) Ltd. | G49: DHW6LBF034-C1001979 | H49: 7138009 | I49: 237 | J49: Ratio Carton | K49: C-Flute | L49: Custom Carton | M49: 400 | N49: 300 | O49: 100 | P49: =IFERROR(IF(K49="",0,(M49+N49)*2+15),0) -> 1415 | Q49: =IFERROR(IF(K49="",0,(N49+O49)-10),0) -> 390 | R49: =P49 * Q49 * (1 + 2.5%) / 1000000 -> 0.56564625 | S49: =R49*'RFQ_Matalan Carton'!$M$32 -> 0.58261564 | T49: =S49 -> 0.58261564 | U49: =I49*T49 -> 138.07991 | V49: =((T49*I49)-W49)*7.5% -> 9.3203937 | W49: =S49*I49*10% -> 13.807991
A50: 46253 | B50: 46256 | D50: Design ARC Asia | E50: N.A.Z Bangladesh Ltd. | F50: Transworld Packaging (BD) Ltd. | G50: DHW6LBF034-C1001979 | H50: 7138009 | I50: 237 | J50: Ratio Carton | K50: C-Flute | L50: Custom Carton | M50: 400 | N50: 350 | O50: 100 | P50: =IFERROR(IF(K50="",0,(M50+N50)*2+15),0) -> 1515 | Q50: =IFERROR(IF(K50="",0,(N50+O50)-10),0) -> 440 | R50: =P50 * Q50 * (1 + 2.5%) / 1000000 -> 0.683265 | S50: =R50*'RFQ_Matalan Carton'!$M$32 -> 0.70376295 | T50: =S50 -> 0.70376295 | U50: =I50*T50 -> 166.79182 | V50: =((T50*I50)-W50)*7.5% -> 11.258448 | W50: =S50*I50*10% -> 16.679182
A51: 46253 | B51: 46256 | D51: Design ARC Asia | E51: N.A.Z Bangladesh Ltd. | F51: Transworld Packaging (BD) Ltd. | G51: DHW6LBF034-C1001979 | H51: 7138009 | I51: 237 | J51: Ratio Carton | K51: C-Flute | L51: Custom Carton | M51: 450 | N51: 400 | O51: 100 | P51: =IFERROR(IF(K51="",0,(M51+N51)*2+15),0) -> 1715 | Q51: =IFERROR(IF(K51="",0,(N51+O51)-10),0) -> 490 | R51: =P51 * Q51 * (1 + 2.5%) / 1000000 -> 0.86135875 | S51: =R51*'RFQ_Matalan Carton'!$M$32 -> 0.88719951 | T51: =S51 -> 0.88719951 | U51: =I51*T51 -> 210.26628 | V51: =((T51*I51)-W51)*7.5% -> 14.192974 | W51: =S51*I51*10% -> 21.026628
A52: 46256 | B52: 46260 | D52: Appollo Fashion Ltd. | E52: Appollo Knit Wear (BD) Ltd. | F52: Transworld Packaging (BD) Ltd. | G52: ETS7TTB02_900-6188+89 | H52: 7139598 | I52: 240 | J52: Ratio Carton | K52: C-Flute | L52: Custom Carton | M52: 300 | N52: 200 | O52: 100 | P52: =IFERROR(IF(K52="",0,(M52+N52)*2+15),0) -> 1015 | Q52: =IFERROR(IF(K52="",0,(N52+O52)-10),0) -> 290 | R52: =P52 * Q52 * (1 + 2.5%) / 1000000 -> 0.30170875 | S52: =R52*'RFQ_Matalan Carton'!$M$32 -> 0.31076001 | T52: =S52 -> 0.31076001 | U52: =I52*T52 -> 74.582403 | V52: =((T52*I52)-W52)*7.5% -> 5.0343122 | W52: =S52*I52*10% -> 7.4582403
A53: 46256 | B53: 46260 | D53: Appollo Fashion Ltd. | E53: Appollo Knit Wear (BD) Ltd. | F53: Transworld Packaging (BD) Ltd. | G53: ETS7TTB02_900-6188+89 | H53: 7139598 | I53: 240 | J53: Ratio Carton | K53: C-Flute | L53: Custom Carton | M53: 300 | N53: 280 | O53: 100 | P53: =IFERROR(IF(K53="",0,(M53+N53)*2+15),0) -> 1175 | Q53: =IFERROR(IF(K53="",0,(N53+O53)-10),0) -> 370 | R53: =P53 * Q53 * (1 + 2.5%) / 1000000 -> 0.44561875 | S53: =R53*'RFQ_Matalan Carton'!$M$32 -> 0.45898731 | T53: =S53 -> 0.45898731 | U53: =I53*T53 -> 110.15695 | V53: =((T53*I53)-W53)*7.5% -> 7.4355945 | W53: =S53*I53*10% -> 11.015695
A54: 46256 | B54: 46258 | D54: KDS IDR Ltd. | E54: KDS IDR Ltd. | F54: Transworld Packaging (BD) Ltd. | G54: G0521578 | H54: 7140093 | I54: 80 | J54: Ratio Carton | K54: C-Flute | L54: R-FPD | M54: {=IFERROR(_xlfn.SWITCH(L54,"R-FPA",495,"R-FPB",595,"R-FPC",595,"R-FPD",595,"Custom Carton","input L"),0)} -> 595 | N54: {=IFERROR(_xlfn.SWITCH(L54,"R-FPA",285,"R-FPB",285,"R-FPC",325,"R-FPD",380,"Custom Carton","input W"),0)} -> 380 | O54: 100 | P54: =IFERROR(IF(K54="",0,(M54+N54)*2+15),0) -> 1965 | Q54: =IFERROR(IF(K54="",0,(N54+O54)-10),0) -> 470 | R54: =P54 * Q54 * (1 + 2.5%) / 1000000 -> 0.94663875 | S54: =R54*'RFQ_Matalan Carton'!$M$32 -> 0.97503791 | T54: =S54 -> 0.97503791 | U54: =I54*T54 -> 78.003033 | V54: =((T54*I54)-W54)*7.5% -> 5.2652047 | W54: =S54*I54*10% -> 7.8003033
A55: 46256 | B55: 46258 | D55: KDS IDR Ltd. | E55: KDS IDR Ltd. | F55: Transworld Packaging (BD) Ltd. | G55: G0521578 | H55: 7140093 | I55: 80 | J55: Ratio Carton | K55: C-Flute | L55: R-FPD | M55: {=IFERROR(_xlfn.SWITCH(L55,"R-FPA",495,"R-FPB",595,"R-FPC",595,"R-FPD",595,"Custom Carton","input L"),0)} -> 595 | N55: {=IFERROR(_xlfn.SWITCH(L55,"R-FPA",285,"R-FPB",285,"R-FPC",325,"R-FPD",380,"Custom Carton","input W"),0)} -> 380 | O55: 220 | P55: =IFERROR(IF(K55="",0,(M55+N55)*2+15),0) -> 1965 | Q55: =IFERROR(IF(K55="",0,(N55+O55)-10),0) -> 590 | R55: =P55 * Q55 * (1 + 2.5%) / 1000000 -> 1.1883337 | S55: =R55*'RFQ_Matalan Carton'!$M$32 -> 1.2239838 | T55: =S55 -> 1.2239838 | U55: =I55*T55 -> 97.918701 | V55: =((T55*I55)-W55)*7.5% -> 6.6095123 | W55: =S55*I55*10% -> 9.7918701
A56: 46256 | B56: 46258 | D56: KDS IDR Ltd. | E56: KDS IDR Ltd. | F56: Transworld Packaging (BD) Ltd. | G56: C1008339 | H56: 7140107 | I56: 504 | J56: Ratio Carton | K56: C-Flute | L56: R-FPC | M56: {=IFERROR(_xlfn.SWITCH(L56,"R-FPA",495,"R-FPB",595,"R-FPC",595,"R-FPD",595,"Custom Carton","input L"),0)} -> 595 | N56: {=IFERROR(_xlfn.SWITCH(L56,"R-FPA",285,"R-FPB",285,"R-FPC",325,"R-FPD",380,"Custom Carton","input W"),0)} -> 325 | O56: 100 | P56: =IFERROR(IF(K56="",0,(M56+N56)*2+15),0) -> 1855 | Q56: =IFERROR(IF(K56="",0,(N56+O56)-10),0) -> 415 | R56: =P56 * Q56 * (1 + 2.5%) / 1000000 -> 0.78907062 | S56: =R56*'RFQ_Matalan Carton'!$M$32 -> 0.81274274 | T56: =S56 -> 0.81274274 | U56: =I56*T56 -> 409.62234 | V56: =((T56*I56)-W56)*7.5% -> 27.649508 | W56: =S56*I56*10% -> 40.962234
A57: 46256 | B57: 46258 | D57: KDS IDR Ltd. | E57: KDS IDR Ltd. | F57: Transworld Packaging (BD) Ltd. | G57: C1008339 | H57: 7140107 | I57: 510 | J57: Ratio Carton | K57: C-Flute | L57: R-FPD | M57: {=IFERROR(_xlfn.SWITCH(L57,"R-FPA",495,"R-FPB",595,"R-FPC",595,"R-FPD",595,"Custom Carton","input L"),0)} -> 595 | N57: {=IFERROR(_xlfn.SWITCH(L57,"R-FPA",285,"R-FPB",285,"R-FPC",325,"R-FPD",380,"Custom Carton","input W"),0)} -> 380 | O57: 220 | P57: =IFERROR(IF(K57="",0,(M57+N57)*2+15),0) -> 1965 | Q57: =IFERROR(IF(K57="",0,(N57+O57)-10),0) -> 590 | R57: =P57 * Q57 * (1 + 2.5%) / 1000000 -> 1.1883337 | S57: =R57*'RFQ_Matalan Carton'!$M$32 -> 1.2239838 | T57: =S57 -> 1.2239838 | U57: =I57*T57 -> 624.23172 | V57: =((T57*I57)-W57)*7.5% -> 42.135641 | W57: =S57*I57*10% -> 62.423172
A58: 46256 | B58: 46264 | D58: CONCORD VENTURES EXPORTS LLC | E58: Dhaka Garments & Washing Ltd. | F58: Transworld Packaging (BD) Ltd. | G58: Cigarette Jean S27 | H58: 7141433 | I58: 63 | J58: Ratio Carton | K58: C-Flute | L58: R-FPD | M58: {=IFERROR(_xlfn.SWITCH(L58,"R-FPA",495,"R-FPB",595,"R-FPC",595,"R-FPD",595,"Custom Carton","input L"),0)} -> 595 | N58: {=IFERROR(_xlfn.SWITCH(L58,"R-FPA",285,"R-FPB",285,"R-FPC",325,"R-FPD",380,"Custom Carton","input W"),0)} -> 380 | O58: 385 | P58: =IFERROR(IF(K58="",0,(M58+N58)*2+15),0) -> 1965 | Q58: =IFERROR(IF(K58="",0,(N58+O58)-10),0) -> 755 | R58: =P58 * Q58 * (1 + 2.5%) / 1000000 -> 1.5206644 | S58: =R58*'RFQ_Matalan Carton'!$M$32 -> 1.5662843 | T58: =S58 -> 1.5662843 | U58: =I58*T58 -> 98.675911 | V58: =((T58*I58)-W58)*7.5% -> 6.660624 | W58: =S58*I58*10% -> 9.8675911
A59: 46257 | B59: 46259 | D59: Design ARC Asia | E59: N.A.Z Bangladesh Ltd. | F59: Transworld Packaging (BD) Ltd. | G59: ASW26TB02AB-C1007145 | H59: 7141457 | I59: 115 | J59: Ratio Carton | K59: C-Flute | L59: Custom Carton | M59: 300 | N59: 280 | O59: 120 | P59: =IFERROR(IF(K59="",0,(M59+N59)*2+15),0) -> 1175 | Q59: =IFERROR(IF(K59="",0,(N59+O59)-10),0) -> 390 | R59: =P59 * Q59 * (1 + 2.5%) / 1000000 -> 0.46970625 | S59: =R59*'RFQ_Matalan Carton'!$M$32 -> 0.48379744 | T59: =S59 -> 0.48379744 | U59: =I59*T59 -> 55.636705 | V59: =((T59*I59)-W59)*7.5% -> 3.7554776 | W59: =S59*I59*10% -> 5.5636705
A60: 46257 | B60: 46259 | D60: Design ARC Asia | E60: N.A.Z Bangladesh Ltd. | F60: Transworld Packaging (BD) Ltd. | G60: ASW26TB02AB-C1007145 | H60: 7141457 | I60: 117 | J60: Ratio Carton | K60: C-Flute | L60: Custom Carton | M60: 540 | N60: 280 | O60: 180 | P60: =IFERROR(IF(K60="",0,(M60+N60)*2+15),0) -> 1655 | Q60: =IFERROR(IF(K60="",0,(N60+O60)-10),0) -> 450 | R60: =P60 * Q60 * (1 + 2.5%) / 1000000 -> 0.76336875 | S60: =R60*'RFQ_Matalan Carton'!$M$32 -> 0.78626981 | T60: =S60 -> 0.78626981 | U60: =I60*T60 -> 91.993568 | V60: =((T60*I60)-W60)*7.5% -> 6.2095658 | W60: =S60*I60*10% -> 9.1993568
A61: 46257 | B61: 46259 | D61: Design ARC Asia | E61: N.A.Z Bangladesh Ltd. | F61: Transworld Packaging (BD) Ltd. | G61: ASW26TB09AB-C1007195 | H61: 7141460 | I61: 234 | J61: Ratio Carton | K61: C-Flute | L61: Custom Carton | M61: 400 | N61: 350 | O61: 100 | P61: =IFERROR(IF(K61="",0,(M61+N61)*2+15),0) -> 1515 | Q61: =IFERROR(IF(K61="",0,(N61+O61)-10),0) -> 440 | R61: =P61 * Q61 * (1 + 2.5%) / 1000000 -> 0.683265 | S61: =R61*'RFQ_Matalan Carton'!$M$32 -> 0.70376295 | T61: =S61 -> 0.70376295 | U61: =I61*T61 -> 164.68053 | V61: =((T61*I61)-W61)*7.5% -> 11.115936 | W61: =S61*I61*10% -> 16.468053
A62: 46257 | B62: 46259 | D62: Design ARC Asia | E62: N.A.Z Bangladesh Ltd. | F62: Transworld Packaging (BD) Ltd. | G62: ASW26TB09AB-C1007195 | H62: 7141460 | I62: 236 | J62: Ratio Carton | K62: C-Flute | L62: Custom Carton | M62: 450 | N62: 400 | O62: 150 | P62: =IFERROR(IF(K62="",0,(M62+N62)*2+15),0) -> 1715 | Q62: =IFERROR(IF(K62="",0,(N62+O62)-10),0) -> 540 | R62: =P62 * Q62 * (1 + 2.5%) / 1000000 -> 0.9492525 | S62: =R62*'RFQ_Matalan Carton'!$M$32 -> 0.97773007 | T62: =S62 -> 0.97773007 | U62: =I62*T62 -> 230.7443 | V62: =((T62*I62)-W62)*7.5% -> 15.57524 | W62: =S62*I62*10% -> 23.07443
A63: 46257 | B63: 46259 | D63: Design ARC Asia | E63: N.A.Z Bangladesh Ltd. | F63: Transworld Packaging (BD) Ltd. | G63: ASS27TB02AB-C1007228 | H63: 7141463 | I63: 234 | J63: Ratio Carton | K63: C-Flute | L63: Custom Carton | M63: 380 | N63: 320 | O63: 100 | P63: =IFERROR(IF(K63="",0,(M63+N63)*2+15),0) -> 1415 | Q63: =IFERROR(IF(K63="",0,(N63+O63)-10),0) -> 410 | R63: =P63 * Q63 * (1 + 2.5%) / 1000000 -> 0.59465375 | S63: =R63*'RFQ_Matalan Carton'!$M$32 -> 0.61249336 | T63: =S63 -> 0.61249336 | U63: =I63*T63 -> 143.32345 | V63: =((T63*I63)-W63)*7.5% -> 9.6743327 | W63: =S63*I63*10% -> 14.332345
A64: 46257 | B64: 46259 | D64: Design ARC Asia | E64: N.A.Z Bangladesh Ltd. | F64: Transworld Packaging (BD) Ltd. | G64: ASS27TB02AB-C1007228 | H64: 7141463 | I64: 236 | J64: Ratio Carton | K64: C-Flute | L64: Custom Carton | M64: 450 | N64: 380 | O64: 120 | P64: =IFERROR(IF(K64="",0,(M64+N64)*2+15),0) -> 1675 | Q64: =IFERROR(IF(K64="",0,(N64+O64)-10),0) -> 490 | R64: =P64 * Q64 * (1 + 2.5%) / 1000000 -> 0.84126875 | S64: =R64*'RFQ_Matalan Carton'!$M$32 -> 0.86650681 | T64: =S64 -> 0.86650681 | U64: =I64*T64 -> 204.49561 | V64: =((T64*I64)-W64)*7.5% -> 13.803454 | W64: =S64*I64*10% -> 20.449561
A65: 46258 | B65: 46263 | D65: Grand Apparels Design | E65: Virtual Bottom | F65: Transworld Packaging (BD) Ltd. | G65: F3076619 | H65: 7141791 | I65: 270 | J65: Ratio Carton | K65: C-Flute | L65: R-FPC | M65: {=IFERROR(_xlfn.SWITCH(L65,"R-FPA",495,"R-FPB",595,"R-FPC",595,"R-FPD",595,"Custom Carton","input L"),0)} -> 595 | N65: {=IFERROR(_xlfn.SWITCH(L65,"R-FPA",285,"R-FPB",285,"R-FPC",325,"R-FPD",380,"Custom Carton","input W"),0)} -> 325 | O65: 375 | P65: =IFERROR(IF(K65="",0,(M65+N65)*2+15),0) -> 1855 | Q65: =IFERROR(IF(K65="",0,(N65+O65)-10),0) -> 690 | R65: =P65 * Q65 * (1 + 2.5%) / 1000000 -> 1.3119487 | S65: =R65*'RFQ_Matalan Carton'!$M$32 -> 1.3513072 | T65: =S65 -> 1.3513072 | U65: =I65*T65 -> 364.85295 | V65: =((T65*I65)-W65)*7.5% -> 24.627574 | W65: =S65*I65*10% -> 36.485295
A66: 46258 | B66: 46259 | D66: Design ARC Asia | E66: AR-Tex Composite Ltd. | F66: Transworld Packaging (BD) Ltd. | G66: F469109 | H66: 7142163 | I66: 1700 | J66: Ratio Carton | K66: C-Flute | L66: Custom Carton | M66: 320 | N66: 300 | O66: 200 | P66: =IFERROR(IF(K66="",0,(M66+N66)*2+15),0) -> 1255 | Q66: =IFERROR(IF(K66="",0,(N66+O66)-10),0) -> 490 | R66: =P66 * Q66 * (1 + 2.5%) / 1000000 -> 0.63032375 | S66: =R66*'RFQ_Matalan Carton'!$M$32 -> 0.64923346 | T66: =S66 -> 0.64923346 | U66: =I66*T66 -> 1103.6969 | V66: =((T66*I66)-W66)*7.5% -> 74.49954 | W66: =S66*I66*10% -> 110.36969
A67: 46258 | B67: 46259 | D67: Design ARC Asia | E67: AR-Tex Composite Ltd. | F67: Transworld Packaging (BD) Ltd. | G67: F469364 | H67: 7142176 | I67: 1400 | J67: Ratio Carton | K67: C-Flute | L67: R-FPB | M67: {=IFERROR(_xlfn.SWITCH(L67,"R-FPA",495,"R-FPB",595,"R-FPC",595,"R-FPD",595,"Custom Carton","input L"),0)} -> 595 | N67: {=IFERROR(_xlfn.SWITCH(L67,"R-FPA",285,"R-FPB",285,"R-FPC",325,"R-FPD",380,"Custom Carton","input W"),0)} -> 285 | O67: 120 | P67: =IFERROR(IF(K67="",0,(M67+N67)*2+15),0) -> 1775 | Q67: =IFERROR(IF(K67="",0,(N67+O67)-10),0) -> 395 | R67: =P67 * Q67 * (1 + 2.5%) / 1000000 -> 0.71865312 | S67: =R67*'RFQ_Matalan Carton'!$M$32 -> 0.74021272 | T67: =S67 -> 0.74021272 | U67: =I67*T67 -> 1036.2978 | V67: =((T67*I67)-W67)*7.5% -> 69.950102 | W67: =S67*I67*10% -> 103.62978
A68: 46259 | B68: 46260 | D68: KDS IDR Ltd. | E68: KDS IDR Ltd. | F68: Transworld Packaging (BD) Ltd. | G68: C1008695 | H68: 7142302 | I68: 681 | J68: Ratio Carton | K68: C-Flute | L68: R-FPC | M68: {=IFERROR(_xlfn.SWITCH(L68,"R-FPA",495,"R-FPB",595,"R-FPC",595,"R-FPD",595,"Custom Carton","input L"),0)} -> 595 | N68: {=IFERROR(_xlfn.SWITCH(L68,"R-FPA",285,"R-FPB",285,"R-FPC",325,"R-FPD",380,"Custom Carton","input W"),0)} -> 325 | O68: 100 | P68: =IFERROR(IF(K68="",0,(M68+N68)*2+15),0) -> 1855 | Q68: =IFERROR(IF(K68="",0,(N68+O68)-10),0) -> 415 | R68: =P68 * Q68 * (1 + 2.5%) / 1000000 -> 0.78907062 | S68: =R68*'RFQ_Matalan Carton'!$M$32 -> 0.81274274 | T68: =S68 -> 0.81274274 | U68: =I68*T68 -> 553.47781 | V68: =((T68*I68)-W68)*7.5% -> 37.359752 | W68: =S68*I68*10% -> 55.347781
A69: 46259 | B69: 46260 | D69: KDS IDR Ltd. | E69: KDS IDR Ltd. | F69: Transworld Packaging (BD) Ltd. | G69: C1008695 | H69: 7142302 | I69: 681 | J69: Ratio Carton | K69: C-Flute | L69: R-FPC | M69: {=IFERROR(_xlfn.SWITCH(L69,"R-FPA",495,"R-FPB",595,"R-FPC",595,"R-FPD",595,"Custom Carton","input L"),0)} -> 595 | N69: {=IFERROR(_xlfn.SWITCH(L69,"R-FPA",285,"R-FPB",285,"R-FPC",325,"R-FPD",380,"Custom Carton","input W"),0)} -> 325 | O69: 230 | P69: =IFERROR(IF(K69="",0,(M69+N69)*2+15),0) -> 1855 | Q69: =IFERROR(IF(K69="",0,(N69+O69)-10),0) -> 545 | R69: =P69 * Q69 * (1 + 2.5%) / 1000000 -> 1.0362494 | S69: =R69*'RFQ_Matalan Carton'!$M$32 -> 1.0673369 | T69: =S69 -> 1.0673369 | U69: =I69*T69 -> 726.8564 | V69: =((T69*I69)-W69)*7.5% -> 49.062807 | W69: =S69*I69*10% -> 72.68564
A70: 46259 | B70: 46260 | D70: KDS IDR Ltd. | E70: KDS IDR Ltd. | F70: Transworld Packaging (BD) Ltd. | G70: C1011314 | H70: 7142308 | I70: 225 | J70: Ratio Carton | K70: C-Flute | L70: R-FPC | M70: {=IFERROR(_xlfn.SWITCH(L70,"R-FPA",495,"R-FPB",595,"R-FPC",595,"R-FPD",595,"Custom Carton","input L"),0)} -> 595 | N70: {=IFERROR(_xlfn.SWITCH(L70,"R-FPA",285,"R-FPB",285,"R-FPC",325,"R-FPD",380,"Custom Carton","input W"),0)} -> 325 | O70: 100 | P70: =IFERROR(IF(K70="",0,(M70+N70)*2+15),0) -> 1855 | Q70: =IFERROR(IF(K70="",0,(N70+O70)-10),0) -> 415 | R70: =P70 * Q70 * (1 + 2.5%) / 1000000 -> 0.78907062 | S70: =R70*'RFQ_Matalan Carton'!$M$32 -> 0.81274274 | T70: =S70 -> 0.81274274 | U70: =I70*T70 -> 182.86712 | V70: =((T70*I70)-W70)*7.5% -> 12.34353 | W70: =S70*I70*10% -> 18.286712
A71: 46259 | B71: 46260 | D71: KDS IDR Ltd. | E71: KDS IDR Ltd. | F71: Transworld Packaging (BD) Ltd. | G71: C1008656 | H71: 7142334 | I71: 772 | J71: Ratio Carton | K71: C-Flute | L71: R-FPC | M71: {=IFERROR(_xlfn.SWITCH(L71,"R-FPA",495,"R-FPB",595,"R-FPC",595,"R-FPD",595,"Custom Carton","input L"),0)} -> 595 | N71: {=IFERROR(_xlfn.SWITCH(L71,"R-FPA",285,"R-FPB",285,"R-FPC",325,"R-FPD",380,"Custom Carton","input W"),0)} -> 325 | O71: 100 | P71: =IFERROR(IF(K71="",0,(M71+N71)*2+15),0) -> 1855 | Q71: =IFERROR(IF(K71="",0,(N71+O71)-10),0) -> 415 | R71: =P71 * Q71 * (1 + 2.5%) / 1000000 -> 0.78907062 | S71: =R71*'RFQ_Matalan Carton'!$M$32 -> 0.81274274 | T71: =S71 -> 0.81274274 | U71: =I71*T71 -> 627.4374 | V71: =((T71*I71)-W71)*7.5% -> 42.352024 | W71: =S71*I71*10% -> 62.74374
A72: 46259 | B72: 46260 | D72: KDS IDR Ltd. | E72: KDS IDR Ltd. | F72: Transworld Packaging (BD) Ltd. | G72: C1008656 | H72: 7142334 | I72: 771 | J72: Ratio Carton | K72: C-Flute | L72: R-FPC | M72: {=IFERROR(_xlfn.SWITCH(L72,"R-FPA",495,"R-FPB",595,"R-FPC",595,"R-FPD",595,"Custom Carton","input L"),0)} -> 595 | N72: {=IFERROR(_xlfn.SWITCH(L72,"R-FPA",285,"R-FPB",285,"R-FPC",325,"R-FPD",380,"Custom Carton","input W"),0)} -> 325 | O72: 240 | P72: =IFERROR(IF(K72="",0,(M72+N72)*2+15),0) -> 1855 | Q72: =IFERROR(IF(K72="",0,(N72+O72)-10),0) -> 555 | R72: =P72 * Q72 * (1 + 2.5%) / 1000000 -> 1.0552631 | S72: =R72*'RFQ_Matalan Carton'!$M$32 -> 1.086921 | T72: =S72 -> 1.086921 | U72: =I72*T72 -> 838.01611 | V72: =((T72*I72)-W72)*7.5% -> 56.566087 | W72: =S72*I72*10% -> 83.801611
A73: 46259 | B73: 46261 | D73: Radial International Unit2 Ltd | E73: Radial International Unit2 Ltd | F73: Transworld Packaging (BD) Ltd. | G73: ST.WM1,R-15390,L-355 | H73: 7142492 | I73: 258 | J73: Ratio Carton | K73: C-Flute | L73: Custom Carton | M73: 600 | N73: 280 | O73: 200 | P73: =IFERROR(IF(K73="",0,(M73+N73)*2+15),0) -> 1775 | Q73: =IFERROR(IF(K73="",0,(N73+O73)-10),0) -> 470 | R73: =P73 * Q73 * (1 + 2.5%) / 1000000 -> 0.85510625 | S73: =R73*'RFQ_Matalan Carton'!$M$32 -> 0.88075944 | T73: =S73 -> 0.88075944 | U73: =I73*T73 -> 227.23593 | V73: =((T73*I73)-W73)*7.5% -> 15.338426 | W73: =S73*I73*10% -> 22.723593
A74: 46259 | B74: 46261 | D74: Radial International Unit2 Ltd | E74: Radial International Unit2 Ltd | F74: Transworld Packaging (BD) Ltd. | G74: ST.WM3,R-15392,L-357 | H74: 7142495 | I74: 258 | J74: Ratio Carton | K74: C-Flute | L74: Custom Carton | M74: 600 | N74: 280 | O74: 200 | P74: =IFERROR(IF(K74="",0,(M74+N74)*2+15),0) -> 1775 | Q74: =IFERROR(IF(K74="",0,(N74+O74)-10),0) -> 470 | R74: =P74 * Q74 * (1 + 2.5%) / 1000000 -> 0.85510625 | S74: =R74*'RFQ_Matalan Carton'!$M$32 -> 0.88075944 | T74: =S74 -> 0.88075944 | U74: =I74*T74 -> 227.23593 | V74: =((T74*I74)-W74)*7.5% -> 15.338426 | W74: =S74*I74*10% -> 22.723593
A75: 46259 | B75: 46261 | D75: Radial International Unit2 Ltd | E75: Radial International Unit2 Ltd | F75: Transworld Packaging (BD) Ltd. | G75: ST.WM2,R-15391,L-356 | H75: 7142516 | I75: 258 | J75: Ratio Carton | K75: C-Flute | L75: Custom Carton | M75: 600 | N75: 280 | O75: 200 | P75: =IFERROR(IF(K75="",0,(M75+N75)*2+15),0) -> 1775 | Q75: =IFERROR(IF(K75="",0,(N75+O75)-10),0) -> 470 | R75: =P75 * Q75 * (1 + 2.5%) / 1000000 -> 0.85510625 | S75: =R75*'RFQ_Matalan Carton'!$M$32 -> 0.88075944 | T75: =S75 -> 0.88075944 | U75: =I75*T75 -> 227.23593 | V75: =((T75*I75)-W75)*7.5% -> 15.338426 | W75: =S75*I75*10% -> 22.723593
A76: 46259 | B76: 46260 | D76: KDS IDR Ltd. | E76: KDS IDR Ltd. | F76: Transworld Packaging (BD) Ltd. | G76: C1011278 | H76: 7142621 | I76: 220 | J76: Ratio Carton | K76: C-Flute | L76: R-FPC | M76: {=IFERROR(_xlfn.SWITCH(L76,"R-FPA",495,"R-FPB",595,"R-FPC",595,"R-FPD",595,"Custom Carton","input L"),0)} -> 595 | N76: {=IFERROR(_xlfn.SWITCH(L76,"R-FPA",285,"R-FPB",285,"R-FPC",325,"R-FPD",380,"Custom Carton","input W"),0)} -> 325 | O76: 100 | P76: =IFERROR(IF(K76="",0,(M76+N76)*2+15),0) -> 1855 | Q76: =IFERROR(IF(K76="",0,(N76+O76)-10),0) -> 415 | R76: =P76 * Q76 * (1 + 2.5%) / 1000000 -> 0.78907062 | S76: =R76*'RFQ_Matalan Carton'!$M$32 -> 0.81274274 | T76: =S76 -> 0.81274274 | U76: =I76*T76 -> 178.8034 | V76: =((T76*I76)-W76)*7.5% -> 12.06923 | W76: =S76*I76*10% -> 17.88034
A77: 46259 | B77: 46260 | D77: KDS IDR Ltd. | E77: KDS IDR Ltd. | F77: Transworld Packaging (BD) Ltd. | G77: C1008524 | H77: 7142904 | I77: 512 | J77: Ratio Carton | K77: C-Flute | L77: R-FPC | M77: {=IFERROR(_xlfn.SWITCH(L77,"R-FPA",495,"R-FPB",595,"R-FPC",595,"R-FPD",595,"Custom Carton","input L"),0)} -> 595 | N77: {=IFERROR(_xlfn.SWITCH(L77,"R-FPA",285,"R-FPB",285,"R-FPC",325,"R-FPD",380,"Custom Carton","input W"),0)} -> 325 | O77: 100 | P77: =IFERROR(IF(K77="",0,(M77+N77)*2+15),0) -> 1855 | Q77: =IFERROR(IF(K77="",0,(N77+O77)-10),0) -> 415 | R77: =P77 * Q77 * (1 + 2.5%) / 1000000 -> 0.78907062 | S77: =R77*'RFQ_Matalan Carton'!$M$32 -> 0.81274274 | T77: =S77 -> 0.81274274 | U77: =I77*T77 -> 416.12428 | V77: =((T77*I77)-W77)*7.5% -> 28.088389 | W77: =S77*I77*10% -> 41.612428
A78: 46259 | B78: 46260 | D78: KDS IDR Ltd. | E78: KDS IDR Ltd. | F78: Transworld Packaging (BD) Ltd. | G78: C1008524 | H78: 7142904 | I78: 512 | J78: Ratio Carton | K78: C-Flute | L78: R-FPC | M78: {=IFERROR(_xlfn.SWITCH(L78,"R-FPA",495,"R-FPB",595,"R-FPC",595,"R-FPD",595,"Custom Carton","input L"),0)} -> 595 | N78: {=IFERROR(_xlfn.SWITCH(L78,"R-FPA",285,"R-FPB",285,"R-FPC",325,"R-FPD",380,"Custom Carton","input W"),0)} -> 325 | O78: 150 | P78: =IFERROR(IF(K78="",0,(M78+N78)*2+15),0) -> 1855 | Q78: =IFERROR(IF(K78="",0,(N78+O78)-10),0) -> 465 | R78: =P78 * Q78 * (1 + 2.5%) / 1000000 -> 0.88413937 | S78: =R78*'RFQ_Matalan Carton'!$M$32 -> 0.91066356 | T78: =S78 -> 0.91066356 | U78: =I78*T78 -> 466.25974 | V78: =((T78*I78)-W78)*7.5% -> 31.472533 | W78: =S78*I78*10% -> 46.625974
A79: 46261 | B79: 46265 | D79: Appollo Fashion Ltd. | E79: Appollo Knit Wear (BD) Ltd. | F79: Transworld Packaging (BD) Ltd. | G79: ASS27OG02-900-6180 | H79: 7143417 | I79: 177 | J79: Ratio Carton | K79: C-Flute | L79: Custom Carton | M79: 640 | N79: 380 | O79: 100 | P79: =IFERROR(IF(K79="",0,(M79+N79)*2+15),0) -> 2055 | Q79: =IFERROR(IF(K79="",0,(N79+O79)-10),0) -> 470 | R79: =P79 * Q79 * (1 + 2.5%) / 1000000 -> 0.98999625 | S79: =R79*'RFQ_Matalan Carton'!$M$32 -> 1.0196961 | T79: =S79 -> 1.0196961 | U79: =I79*T79 -> 180.48622 | V79: =((T79*I79)-W79)*7.5% -> 12.18282 | W79: =S79*I79*10% -> 18.048622
A80: 46261 | B80: 46265 | D80: Appollo Fashion Ltd. | E80: Appollo Knit Wear (BD) Ltd. | F80: Transworld Packaging (BD) Ltd. | G80: ASS27TG02_900-6178+79RAT | H80: 7143437 | I80: 235 | J80: Ratio Carton | K80: C-Flute | L80: Custom Carton | M80: 750 | N80: 380 | O80: 100 | P80: =IFERROR(IF(K80="",0,(M80+N80)*2+15),0) -> 2275 | Q80: =IFERROR(IF(K80="",0,(N80+O80)-10),0) -> 470 | R80: =P80 * Q80 * (1 + 2.5%) / 1000000 -> 1.0959812 | S80: =R80*'RFQ_Matalan Carton'!$M$32 -> 1.1288607 | T80: =S80 -> 1.1288607 | U80: =I80*T80 -> 265.28226 | V80: =((T80*I80)-W80)*7.5% -> 17.906553 | W80: =S80*I80*10% -> 26.528226
A81: 46261 | B81: 46264 | D81: Design ARC Asia | E81: N.A.Z Bangladesh Ltd. | F81: Transworld Packaging (BD) Ltd. | G81: SLS27BN04AB-C1007773 | H81: 7143556 | I81: 184 | J81: Ratio Carton | K81: C-Flute | L81: Custom Carton | M81: 380 | N81: 340 | O81: 100 | P81: =IFERROR(IF(K81="",0,(M81+N81)*2+15),0) -> 1455 | Q81: =IFERROR(IF(K81="",0,(N81+O81)-10),0) -> 430 | R81: =P81 * Q81 * (1 + 2.5%) / 1000000 -> 0.64129125 | S81: =R81*'RFQ_Matalan Carton'!$M$32 -> 0.66052999 | T81: =S81 -> 0.66052999 | U81: =I81*T81 -> 121.53752 | V81: =((T81*I81)-W81)*7.5% -> 8.2037824 | W81: =S81*I81*10% -> 12.153752
A82: 46261 | B82: 46264 | D82: Design ARC Asia | E82: N.A.Z Bangladesh Ltd. | F82: Transworld Packaging (BD) Ltd. | G82: SLS27BN04AB-C1007773 | H82: 7143556 | I82: 184 | J82: Ratio Carton | K82: C-Flute | L82: Custom Carton | M82: 420 | N82: 360 | O82: 120 | P82: =IFERROR(IF(K82="",0,(M82+N82)*2+15),0) -> 1575 | Q82: =IFERROR(IF(K82="",0,(N82+O82)-10),0) -> 470 | R82: =P82 * Q82 * (1 + 2.5%) / 1000000 -> 0.75875625 | S82: =R82*'RFQ_Matalan Carton'!$M$32 -> 0.78151894 | T82: =S82 -> 0.78151894 | U82: =I82*T82 -> 143.79948 | V82: =((T82*I82)-W82)*7.5% -> 9.7064652 | W82: =S82*I82*10% -> 14.379948
A83: 46263 | B83: 46264 | D83: KDS IDR Ltd. | E83: KDS IDR Ltd. | F83: Transworld Packaging (BD) Ltd. | G83: G0519577 | H83: 7143859 | I83: 314 | J83: Ratio Carton | K83: C-Flute | L83: R-FPD | M83: {=IFERROR(_xlfn.SWITCH(L83,"R-FPA",495,"R-FPB",595,"R-FPC",595,"R-FPD",595,"Custom Carton","input L"),0)} -> 595 | N83: {=IFERROR(_xlfn.SWITCH(L83,"R-FPA",285,"R-FPB",285,"R-FPC",325,"R-FPD",380,"Custom Carton","input W"),0)} -> 380 | O83: 100 | P83: =IFERROR(IF(K83="",0,(M83+N83)*2+15),0) -> 1965 | Q83: =IFERROR(IF(K83="",0,(N83+O83)-10),0) -> 470 | R83: =P83 * Q83 * (1 + 2.5%) / 1000000 -> 0.94663875 | S83: =R83*'RFQ_Matalan Carton'!$M$32 -> 0.97503791 | T83: =S83 -> 0.97503791 | U83: =I83*T83 -> 306.1619 | V83: =((T83*I83)-W83)*7.5% -> 20.665929 | W83: =S83*I83*10% -> 30.61619
A84: 46263 | B84: 46264 | D84: KDS IDR Ltd. | E84: KDS IDR Ltd. | F84: Transworld Packaging (BD) Ltd. | G84: G0519577 | H84: 7143859 | I84: 816 | J84: Ratio Carton | K84: C-Flute | L84: R-FPD | M84: {=IFERROR(_xlfn.SWITCH(L84,"R-FPA",495,"R-FPB",595,"R-FPC",595,"R-FPD",595,"Custom Carton","input L"),0)} -> 595 | N84: {=IFERROR(_xlfn.SWITCH(L84,"R-FPA",285,"R-FPB",285,"R-FPC",325,"R-FPD",380,"Custom Carton","input W"),0)} -> 380 | O84: 120 | P84: =IFERROR(IF(K84="",0,(M84+N84)*2+15),0) -> 1965 | Q84: =IFERROR(IF(K84="",0,(N84+O84)-10),0) -> 490 | R84: =P84 * Q84 * (1 + 2.5%) / 1000000 -> 0.98692125 | S84: =R84*'RFQ_Matalan Carton'!$M$32 -> 1.0165289 | T84: =S84 -> 1.0165289 | U84: =I84*T84 -> 829.48757 | V84: =((T84*I84)-W84)*7.5% -> 55.990411 | W84: =S84*I84*10% -> 82.948757
A85: 46263 | B85: 46263 | D85: KDS IDR Ltd. | E85: KDS IDR Ltd. | F85: Transworld Packaging (BD) Ltd. | G85: G0521732 | H85: 7144252 | I85: 1661 | J85: Ratio Carton | K85: C-Flute | L85: R-FPD | M85: {=IFERROR(_xlfn.SWITCH(L85,"R-FPA",495,"R-FPB",595,"R-FPC",595,"R-FPD",595,"Custom Carton","input L"),0)} -> 595 | N85: {=IFERROR(_xlfn.SWITCH(L85,"R-FPA",285,"R-FPB",285,"R-FPC",325,"R-FPD",380,"Custom Carton","input W"),0)} -> 380 | O85: 110 | P85: =IFERROR(IF(K85="",0,(M85+N85)*2+15),0) -> 1965 | Q85: =IFERROR(IF(K85="",0,(N85+O85)-10),0) -> 480 | R85: =P85 * Q85 * (1 + 2.5%) / 1000000 -> 0.96678 | S85: =R85*'RFQ_Matalan Carton'!$M$32 -> 0.9957834 | T85: =S85 -> 0.9957834 | U85: =I85*T85 -> 1653.9962 | V85: =((T85*I85)-W85)*7.5% -> 111.64475 | W85: =S85*I85*10% -> 165.39962
A86: 46263 | B86: 46264 | D86: Design ARC Asia | E86: N.A.Z Bangladesh Ltd. | F86: Transworld Packaging (BD) Ltd. | G86: SLS27BN06-C1007758 | H86: 7144261 | I86: 296 | J86: Ratio Carton | K86: C-Flute | L86: Custom Carton | M86: 480 | N86: 400 | O86: 130 | P86: =IFERROR(IF(K86="",0,(M86+N86)*2+15),0) -> 1775 | Q86: =IFERROR(IF(K86="",0,(N86+O86)-10),0) -> 520 | R86: =P86 * Q86 * (1 + 2.5%) / 1000000 -> 0.946075 | S86: =R86*'RFQ_Matalan Carton'!$M$32 -> 0.97445725 | T86: =S86 -> 0.97445725 | U86: =I86*T86 -> 288.43935 | V86: =((T86*I86)-W86)*7.5% -> 19.469656 | W86: =S86*I86*10% -> 28.843935
A87: 46263 | B87: 46264 | D87: Design ARC Asia | E87: N.A.Z Bangladesh Ltd. | F87: Transworld Packaging (BD) Ltd. | G87: SLS27BN06-C1007758 | H87: 7144261 | I87: 296 | J87: Ratio Carton | K87: C-Flute | L87: Custom Carton | M87: 450 | N87: 350 | O87: 100 | P87: =IFERROR(IF(K87="",0,(M87+N87)*2+15),0) -> 1615 | Q87: =IFERROR(IF(K87="",0,(N87+O87)-10),0) -> 440 | R87: =P87 * Q87 * (1 + 2.5%) / 1000000 -> 0.728365 | S87: =R87*'RFQ_Matalan Carton'!$M$32 -> 0.75021595 | T87: =S87 -> 0.75021595 | U87: =I87*T87 -> 222.06392 | V87: =((T87*I87)-W87)*7.5% -> 14.989315 | W87: =S87*I87*10% -> 22.206392
A88: 46263 | B88: 46264 | D88: Design ARC Asia | E88: N.A.Z Bangladesh Ltd. | F88: Transworld Packaging (BD) Ltd. | G88: JWS27NW005-M2686580 | H88: 7144264 | I88: 324 | J88: Ratio Carton | K88: C-Flute | L88: Custom Carton | M88: 520 | N88: 360 | O88: 380 | P88: =IFERROR(IF(K88="",0,(M88+N88)*2+15),0) -> 1775 | Q88: =IFERROR(IF(K88="",0,(N88+O88)-10),0) -> 730 | R88: =P88 * Q88 * (1 + 2.5%) / 1000000 -> 1.3281437 | S88: =R88*'RFQ_Matalan Carton'!$M$32 -> 1.3679881 | T88: =S88 -> 1.3679881 | U88: =I88*T88 -> 443.22813 | V88: =((T88*I88)-W88)*7.5% -> 29.917899 | W88: =S88*I88*10% -> 44.322813
A89: 46263 | B89: 46264 | D89: Design ARC Asia | E89: N.A.Z Bangladesh Ltd. | F89: Transworld Packaging (BD) Ltd. | G89: ETS25NW012-M2688267 | H89: 7144267 | I89: 20 | J89: Ratio Carton | K89: C-Flute | L89: Custom Carton | M89: 480 | N89: 310 | O89: 160 | P89: =IFERROR(IF(K89="",0,(M89+N89)*2+15),0) -> 1595 | Q89: =IFERROR(IF(K89="",0,(N89+O89)-10),0) -> 460 | R89: =P89 * Q89 * (1 + 2.5%) / 1000000 -> 0.7520425 | S89: =R89*'RFQ_Matalan Carton'!$M$32 -> 0.77460377 | T89: =S89 -> 0.77460377 | U89: =I89*T89 -> 15.492075 | V89: =((T89*I89)-W89)*7.5% -> 1.0457151 | W89: =S89*I89*10% -> 1.5492075
A90: 46263 | B90: 46264 | D90: KDS IDR Ltd. | E90: KDS IDR Ltd. | F90: Transworld Packaging (BD) Ltd. | G90: G0520032 | H90: 7144647 | I90: 176 | J90: Ratio Carton | K90: C-Flute | L90: R-FPD | M90: {=IFERROR(_xlfn.SWITCH(L90,"R-FPA",495,"R-FPB",595,"R-FPC",595,"R-FPD",595,"Custom Carton","input L"),0)} -> 595 | N90: {=IFERROR(_xlfn.SWITCH(L90,"R-FPA",285,"R-FPB",285,"R-FPC",325,"R-FPD",380,"Custom Carton","input W"),0)} -> 380 | O90: 100 | P90: =IFERROR(IF(K90="",0,(M90+N90)*2+15),0) -> 1965 | Q90: =IFERROR(IF(K90="",0,(N90+O90)-10),0) -> 470 | R90: =P90 * Q90 * (1 + 2.5%) / 1000000 -> 0.94663875 | S90: =R90*'RFQ_Matalan Carton'!$M$32 -> 0.97503791 | T90: =S90 -> 0.97503791 | U90: =I90*T90 -> 171.60667 | V90: =((T90*I90)-W90)*7.5% -> 11.58345 | W90: =S90*I90*10% -> 17.160667
A91: 46263 | B91: 46264 | D91: KDS IDR Ltd. | E91: KDS IDR Ltd. | F91: Transworld Packaging (BD) Ltd. | G91: G0520032 | H91: 7144647 | I91: 176 | J91: Ratio Carton | K91: C-Flute | L91: R-FPD | M91: {=IFERROR(_xlfn.SWITCH(L91,"R-FPA",495,"R-FPB",595,"R-FPC",595,"R-FPD",595,"Custom Carton","input L"),0)} -> 595 | N91: {=IFERROR(_xlfn.SWITCH(L91,"R-FPA",285,"R-FPB",285,"R-FPC",325,"R-FPD",380,"Custom Carton","input W"),0)} -> 380 | O91: 130 | P91: =IFERROR(IF(K91="",0,(M91+N91)*2+15),0) -> 1965 | Q91: =IFERROR(IF(K91="",0,(N91+O91)-10),0) -> 500 | R91: =P91 * Q91 * (1 + 2.5%) / 1000000 -> 1.0070625 | S91: =R91*'RFQ_Matalan Carton'!$M$32 -> 1.0372744 | T91: =S91 -> 1.0372744 | U91: =I91*T91 -> 182.56029 | V91: =((T91*I91)-W91)*7.5% -> 12.32282 | W91: =S91*I91*10% -> 18.256029
A92: 46264 | B92: 46265 | D92: KDS IDR Ltd. | E92: KDS IDR Ltd. | F92: Transworld Packaging (BD) Ltd. | G92: C1018995 | H92: 7144726 | I92: 1110 | J92: Ratio Carton | K92: C-Flute | L92: R-FPA | M92: {=IFERROR(_xlfn.SWITCH(L92,"R-FPA",495,"R-FPB",595,"R-FPC",595,"R-FPD",595,"Custom Carton","input L"),0)} -> 495 | N92: {=IFERROR(_xlfn.SWITCH(L92,"R-FPA",285,"R-FPB",285,"R-FPC",325,"R-FPD",380,"Custom Carton","input W"),0)} -> 285 | O92: 100 | P92: =IFERROR(IF(K92="",0,(M92+N92)*2+15),0) -> 1575 | Q92: =IFERROR(IF(K92="",0,(N92+O92)-10),0) -> 375 | R92: =P92 * Q92 * (1 + 2.5%) / 1000000 -> 0.60539062 | S92: =R92*'RFQ_Matalan Carton'!$M$32 -> 0.62355234 | T92: =S92 -> 0.62355234 | U92: =I92*T92 -> 692.1431 | V92: =((T92*I92)-W92)*7.5% -> 46.719659 | W92: =S92*I92*10% -> 69.21431
A93: 46264 | B93: 46265 | D93: KDS IDR Ltd. | E93: KDS IDR Ltd. | F93: Transworld Packaging (BD) Ltd. | G93: C1018995 | H93: 7144726 | I93: 1106 | J93: Ratio Carton | K93: C-Flute | L93: R-FPA | M93: {=IFERROR(_xlfn.SWITCH(L93,"R-FPA",495,"R-FPB",595,"R-FPC",595,"R-FPD",595,"Custom Carton","input L"),0)} -> 495 | N93: {=IFERROR(_xlfn.SWITCH(L93,"R-FPA",285,"R-FPB",285,"R-FPC",325,"R-FPD",380,"Custom Carton","input W"),0)} -> 285 | O93: 180 | P93: =IFERROR(IF(K93="",0,(M93+N93)*2+15),0) -> 1575 | Q93: =IFERROR(IF(K93="",0,(N93+O93)-10),0) -> 455 | R93: =P93 * Q93 * (1 + 2.5%) / 1000000 -> 0.73454062 | S93: =R93*'RFQ_Matalan Carton'!$M$32 -> 0.75657684 | T93: =S93 -> 0.75657684 | U93: =I93*T93 -> 836.77399 | V93: =((T93*I93)-W93)*7.5% -> 56.482244 | W93: =S93*I93*10% -> 83.677399
A94: 46236 | B94: 46240 | D94: Design ARC Asia | E94: Confidance Knitwear Ltd. | F94: Uniglory Packaging Industries Ltd. | G94: TG03 | H94: 7128054 | I94: 260 | J94: Ratio Carton | K94: C-Flute | L94: Custom Carton | M94: 620 | N94: 320 | O94: 100 | P94: =IFERROR(IF(K94="",0,(M94+N94)*2+15),0) -> 1895 | Q94: =IFERROR(IF(K94="",0,(N94+O94)-10),0) -> 410 | R94: =P94 * Q94 * (1 + 2.5%) / 1000000 -> 0.79637375 | S94: =R94*'RFQ_Matalan Carton'!$M$32 -> 0.82026496 | T94: =S94 -> 0.82026496 | U94: =I94*T94 -> 213.26889 | V94: =((T94*I94)-W94)*7.5% -> 14.39565 | W94: =S94*I94*10% -> 21.326889
A95: 46236 | B95: 46240 | D95: Design ARC Asia | E95: Confidance Knitwear Ltd. | F95: Uniglory Packaging Industries Ltd. | G95: TG03 | H95: 7128054 | I95: 262 | J95: Ratio Carton | K95: C-Flute | L95: Custom Carton | M95: 800 | N95: 360 | O95: 120 | P95: =IFERROR(IF(K95="",0,(M95+N95)*2+15),0) -> 2335 | Q95: =IFERROR(IF(K95="",0,(N95+O95)-10),0) -> 470 | R95: =P95 * Q95 * (1 + 2.5%) / 1000000 -> 1.1248863 | S95: =R95*'RFQ_Matalan Carton'!$M$32 -> 1.1586328 | T95: =S95 -> 1.1586328 | U95: =I95*T95 -> 303.5618 | V95: =((T95*I95)-W95)*7.5% -> 20.490422 | W95: =S95*I95*10% -> 30.35618
A96: 46238 | B96: 46243 | D96: Design ARC Asia | E96: Confidance Knitwear Ltd. | F96: Uniglory Packaging Industries Ltd. | G96: TG01 | H96: 7129094 | I96: 120 | J96: Ratio Carton | K96: C-Flute | L96: Custom Carton | M96: 610 | N96: 380 | O96: 100 | P96: =IFERROR(IF(K96="",0,(M96+N96)*2+15),0) -> 1995 | Q96: =IFERROR(IF(K96="",0,(N96+O96)-10),0) -> 470 | R96: =P96 * Q96 * (1 + 2.5%) / 1000000 -> 0.96109125 | S96: =R96*'RFQ_Matalan Carton'!$M$32 -> 0.98992399 | T96: =S96 -> 0.98992399 | U96: =I96*T96 -> 118.79088 | V96: =((T96*I96)-W96)*7.5% -> 8.0183843 | W96: =S96*I96*10% -> 11.879088
A97: 46238 | B97: 46243 | D97: Design ARC Asia | E97: Confidance Knitwear Ltd. | F97: Uniglory Packaging Industries Ltd. | G97: TG01 | H97: 7129094 | I97: 122 | J97: Ratio Carton | K97: C-Flute | L97: Custom Carton | M97: 740 | N97: 420 | O97: 100 | P97: =IFERROR(IF(K97="",0,(M97+N97)*2+15),0) -> 2335 | Q97: =IFERROR(IF(K97="",0,(N97+O97)-10),0) -> 510 | R97: =P97 * Q97 * (1 + 2.5%) / 1000000 -> 1.2206212 | S97: =R97*'RFQ_Matalan Carton'!$M$32 -> 1.2572399 | T97: =S97 -> 1.2572399 | U97: =I97*T97 -> 153.38327 | V97: =((T97*I97)-W97)*7.5% -> 10.35337 | W97: =S97*I97*10% -> 15.338327
A98: 46240 | B98: 46243 | D98: Design ARC Asia | E98: Confidance Knitwear Ltd. | F98: Uniglory Packaging Industries Ltd. | G98: OB01 | H98: 7130506 | I98: 272 | J98: Ratio Carton | K98: C-Flute | L98: Custom Carton | M98: 900 | N98: 400 | O98: 100 | P98: =IFERROR(IF(K98="",0,(M98+N98)*2+15),0) -> 2615 | Q98: =IFERROR(IF(K98="",0,(N98+O98)-10),0) -> 490 | R98: =P98 * Q98 * (1 + 2.5%) / 1000000 -> 1.3133838 | S98: =R98*'RFQ_Matalan Carton'!$M$32 -> 1.3527853 | T98: =S98 -> 1.3527853 | U98: =I98*T98 -> 367.95759 | V98: =((T98*I98)-W98)*7.5% -> 24.837137 | W98: =S98*I98*10% -> 36.795759
A99: 46240 | B99: 46243 | D99: Design ARC Asia | E99: Confidance Knitwear Ltd. | F99: Uniglory Packaging Industries Ltd. | G99: OB01 | H99: 7130506 | I99: 272 | J99: Ratio Carton | K99: C-Flute | L99: Custom Carton | M99: 950 | N99: 470 | O99: 110 | P99: =IFERROR(IF(K99="",0,(M99+N99)*2+15),0) -> 2855 | Q99: =IFERROR(IF(K99="",0,(N99+O99)-10),0) -> 570 | R99: =P99 * Q99 * (1 + 2.5%) / 1000000 -> 1.6680337 | S99: =R99*'RFQ_Matalan Carton'!$M$32 -> 1.7180748 | T99: =S99 -> 1.7180748 | U99: =I99*T99 -> 467.31634 | V99: =((T99*I99)-W99)*7.5% -> 31.543853 | W99: =S99*I99*10% -> 46.731634
A100: 46243 | B100: 46244 | D100: Design ARC Asia | E100: AR-Tex Composite Ltd. | F100: Uniglory Packaging Industries Ltd. | G100: F476035 | H100: 7132064 | I100: 2026 | J100: Ratio Carton | K100: C-Flute | L100: R-FPB | M100: {=IFERROR(_xlfn.SWITCH(L100,"R-FPA",495,"R-FPB",595,"R-FPC",595,"R-FPD",595,"Custom Carton","input L"),0)} -> 595 | N100: {=IFERROR(_xlfn.SWITCH(L100,"R-FPA",285,"R-FPB",285,"R-FPC",325,"R-FPD",380,"Custom Carton","input W"),0)} -> 285 | O100: 170 | P100: =IFERROR(IF(K100="",0,(M100+N100)*2+15),0) -> 1775 | Q100: =IFERROR(IF(K100="",0,(N100+O100)-10),0) -> 445 | R100: =P100 * Q100 * (1 + 2.5%) / 1000000 -> 0.80962187 | S100: =R100*'RFQ_Matalan Carton'!$M$32 -> 0.83391053 | T100: =S100 -> 0.83391053 | U100: =I100*T100 -> 1689.5027 | V100: =((T100*I100)-W100)*7.5% -> 114.04143 | W100: =S100*I100*10% -> 168.95027
A101: 46246 | B101: 46247 | D101: KESKAN FZC | E101: H.B Knittex Ltd. | F101: Uniglory Packaging Industries Ltd. | G101: GCW26SE19AB | H101: 7132988 | I101: 291 | J101: Ratio Carton | K101: C-Flute | L101: R-FPC | M101: {=IFERROR(_xlfn.SWITCH(L101,"R-FPA",495,"R-FPB",595,"R-FPC",595,"R-FPD",595,"Custom Carton","input L"),0)} -> 595 | N101: {=IFERROR(_xlfn.SWITCH(L101,"R-FPA",285,"R-FPB",285,"R-FPC",325,"R-FPD",380,"Custom Carton","input W"),0)} -> 325 | O101: 100 | P101: =IFERROR(IF(K101="",0,(M101+N101)*2+15),0) -> 1855 | Q101: =IFERROR(IF(K101="",0,(N101+O101)-10),0) -> 415 | R101: =P101 * Q101 * (1 + 2.5%) / 1000000 -> 0.78907062 | S101: =R101*'RFQ_Matalan Carton'!$M$32 -> 0.81274274 | T101: =S101 -> 0.81274274 | U101: =I101*T101 -> 236.50814 | V101: =((T101*I101)-W101)*7.5% -> 15.964299 | W101: =S101*I101*10% -> 23.650814
A102: 46246 | B102: 46247 | D102: KESKAN FZC | E102: H.B Knittex Ltd. | F102: Uniglory Packaging Industries Ltd. | G102: GCW26SE19AB | H102: 7132988 | I102: 291 | J102: Ratio Carton | K102: C-Flute | L102: R-FPD | M102: {=IFERROR(_xlfn.SWITCH(L102,"R-FPA",495,"R-FPB",595,"R-FPC",595,"R-FPD",595,"Custom Carton","input L"),0)} -> 595 | N102: {=IFERROR(_xlfn.SWITCH(L102,"R-FPA",285,"R-FPB",285,"R-FPC",325,"R-FPD",380,"Custom Carton","input W"),0)} -> 380 | O102: 180 | P102: =IFERROR(IF(K102="",0,(M102+N102)*2+15),0) -> 1965 | Q102: =IFERROR(IF(K102="",0,(N102+O102)-10),0) -> 550 | R102: =P102 * Q102 * (1 + 2.5%) / 1000000 -> 1.1077687 | S102: =R102*'RFQ_Matalan Carton'!$M$32 -> 1.1410018 | T102: =S102 -> 1.1410018 | U102: =I102*T102 -> 332.03153 | V102: =((T102*I102)-W102)*7.5% -> 22.412128 | W102: =S102*I102*10% -> 33.203153
...

Sheet RFQ_Matalan Carton
A1: MATALAN SHIPPING CARTON RFQ | J1: Version: 1.2 | K1: 45968
A4: Quoted by: | B4: Bangladesh Estimated prices, but need to confirm with Pkg Suppliers | G4: NOTE:
A5: Supply to: | B5: Matalan Product Factories | G5: 1- Standard cartons from A1~D3 need to be quoted by each
A6: Delivery: | B6: EX-Works | G6: 2- The Price Calculator only for custom carton in RSC(Regular Slotted Carton, FEFCO-0201) style
A7: Payments | B7: Net 45 Days (end of month invoicing) | G7: 3- The results is EX-Works price with MOQ>=100pcs, (MOQ=Minimum Order Quantity)
A8: VAT: | B8: Included | G8: 4- Packaging Factory will charge a $20 fee for PO quantity less than MOQ=100; If printing is different on any line item, that is considered a unique PO quantity.
A9: MOQ/MDQ: | B9: 100
A10: Drawings: | B10: Attached Matalan standard carton drawings | G10: 5- Price rate will be reviewed every six months. Pricing to be advised no less than 30 days prior to the next 6 month term.
A11: Date: | B11: 46023
A13: STANDARD CARTON
A14: CTN# | B14: CARTON OUTSIDE DIMENSION(mm) | E14: CARTON STYLE | F14: PRINTING | G14: FLUTE TYPE | H14: ECT(lbs/in) | I14: BLANK SIZE(mm) | K14: AREA(sqm) | L14: MOQ | M14: EXW Price
B15: Length | C15: Width | D15: Height | I15: Length | J15: Width | M15: Contracted Prices with Nominated Supplier （USD,$) | N15: Final FOB Price （USD,$) | O15: Rebates % for Matalan | P15: Rebates $ for Matalan
A16: A1 | B16: 495 | C16: 285 | D16: 375 | E16: RSC(Regular Slotted Carton,FEFCO0201) with Trapezoid Perforation at one of the side panel, See attached drawings | F16: FLEXO 1C,BLACK | G16: BC-Flute | H16: 40 | I16: 1571 | J16: 644 | K16: =I16*J16/1000000 -> 1.011724 | L16: 100 | M16: 0.97 | N16: =M16+P16 -> 1.0185 | O16: 0.05 | P16: =M16*$O$16 -> 0.0485
A17: A2 | B17: 495 | C17: 285 | D17: 310 | I17: 1571 | J17: 579 | K17: =I17*J17/1000000 -> 0.909609 | L17: 100 | M17: 0.88 | N17: =M17+P17 -> 0.924 | P17: =M17*$O$16 -> 0.044
A18: A3 | B18: 495 | C18: 285 | D18: 260 | I18: 1571 | J18: 529 | K18: =I18*J18/1000000 -> 0.831059 | L18: 100 | M18: 0.81 | N18: =M18+P18 -> 0.8505 | P18: =M18*$O$16 -> 0.0405
A19: B1 | B19: 595 | C19: 285 | D19: 375 | I19: 1771 | J19: 644 | K19: =I19*J19/1000000 -> 1.140524 | L19: 100 | M19: 1.1 | N19: =M19+P19 -> 1.155 | P19: =M19*$O$16 -> 0.055
A20: B2 | B20: 595 | C20: 285 | D20: 310 | I20: 1771 | J20: 579 | K20: =I20*J20/1000000 -> 1.025409 | L20: 100 | M20: 0.99 | N20: =M20+P20 -> 1.0395 | P20: =M20*$O$16 -> 0.0495
A21: B3 | B21: 595 | C21: 285 | D21: 260 | I21: 1771 | J21: 529 | K21: =I21*J21/1000000 -> 0.936859 | L21: 100 | M21: 0.9 | N21: =M21+P21 -> 0.945 | P21: =M21*$O$16 -> 0.045
A22: C1 | B22: 595 | C22: 325 | D22: 375 | I22: 1851 | J22: 684 | K22: =I22*J22/1000000 -> 1.266084 | L22: 100 | M22: 1.22 | N22: =M22+P22 -> 1.281 | P22: =M22*$O$16 -> 0.061
A23: C2 | B23: 595 | C23: 325 | D23: 310 | I23: 1851 | J23: 619 | K23: =I23*J23/1000000 -> 1.145769 | L23: 100 | M23: 1.1 | N23: =M23+P23 -> 1.155 | P23: =M23*$O$16 -> 0.055
A24: C3 | B24: 595 | C24: 325 | D24: 260 | I24: 1851 | J24: 569 | K24: =I24*J24/1000000 -> 1.053219 | L24: 100 | M24: 1.02 | N24: =M24+P24 -> 1.071 | P24: =M24*$O$16 -> 0.051
A25: D1 | B25: 595 | C25: 380 | D25: 375 | I25: 1961 | J25: 739 | K25: =I25*J25/1000000 -> 1.449179 | L25: 100 | M25: 1.39 | N25: =M25+P25 -> 1.4595 | P25: =M25*$O$16 -> 0.0695
A26: D2 | B26: 595 | C26: 380 | D26: 310 | I26: 1961 | J26: 674 | K26: =I26*J26/1000000 -> 1.321714 | L26: 100 | M26: 1.27 | N26: =M26+P26 -> 1.3335 | P26: =M26*$O$16 -> 0.0635
A27: D3 | B27: 595 | C27: 380 | D27: 260 | I27: 1961 | J27: 624 | K27: =I27*J27/1000000 -> 1.223664 | L27: 100 | M27: 1.18 | N27: =M27+P27 -> 1.239 | P27: =M27*$O$16 -> 0.059
A29: RATIO & CUSTOM CARTON
A30: CTN# | B30: CARTON OUTSIDE DIMENSION(mm) | E30: CARTON STYLE | F30: PRINTING | G30: FLUTE TYPE | H30: ECT(lbs/in) | I30: BLANK SIZE(mm) | K30: AREA(sqm) | L30: MOQ | M30: EXW Price
B31: Length | C31: Width | D31: Height | I31: Length | J31: Width | M31: Contracted Prices with Nominated Supplier (USD,$)/ SQM | N31: Final FOB Price (USD,$) /SQM | O31: Rebates % for Matalan | P31: Rebates￥ for Matalan
A32: / | B32: / | C32: / | D32: / | E32: RSC(Regular Slotted Carton,FEFCO0201) | F32: FLEXO 1C,BLACK | G32: C-Flute | H32: 40 | I32: / | J32: / | K32: 1 | L32: 100 | M32: 1.03 | N32: =M32+P32 -> 1.133 | O32: 0.1 | P32: =M32*0.1 -> 0.103
H34: Click here>>> | M34: PRICE FORMULA FOR NORMAL RSC CARTON
M35: Price = Area * SqmPrice
M36: Area(C-Flute)=(2*L+2*W+15)*(H+W-10)/1000000

Sheet Carton Sizes Chart
A2: CTN# | B2: CARTON SIZE
B3: L | C3: W | D3: H | E3: EXW Price
A4: A1 | B4: 495 | C4: 285 | D4: 375 | E4: ='RFQ_Matalan Carton'!M16 -> 0.97
A5: A2 | B5: 495 | C5: 285 | D5: 310 | E5: ='RFQ_Matalan Carton'!M17 -> 0.88
A6: A3 | B6: 495 | C6: 285 | D6: 260 | E6: ='RFQ_Matalan Carton'!M18 -> 0.81
A7: B1 | B7: 595 | C7: 285 | D7: 375 | E7: ='RFQ_Matalan Carton'!M19 -> 1.1
A8: B2 | B8: 595 | C8: 285 | D8: 310 | E8: ='RFQ_Matalan Carton'!M20 -> 0.99
A9: B3 | B9: 595 | C9: 285 | D9: 260 | E9: ='RFQ_Matalan Carton'!M21 -> 0.9
A10: C1 | B10: 595 | C10: 325 | D10: 375 | E10: ='RFQ_Matalan Carton'!M22 -> 1.22
A11: C2 | B11: 595 | C11: 325 | D11: 310 | E11: ='RFQ_Matalan Carton'!M23 -> 1.1
A12: C3 | B12: 595 | C12: 325 | D12: 260 | E12: ='RFQ_Matalan Carton'!M24 -> 1.02
A13: D1 | B13: 595 | C13: 380 | D13: 375 | E13: ='RFQ_Matalan Carton'!M25 -> 1.39
A14: D2 | B14: 595 | C14: 380 | D14: 310 | E14: ='RFQ_Matalan Carton'!M26 -> 1.27
A15: D3 | B15: 595 | C15: 380 | D15: 260 | E15: ='RFQ_Matalan Carton'!M27 -> 1.18

Sheet Sheet1
G6: Pacd | H6: Mat
E7: Uniglory Packaging Industries Ltd. | F7: STD | G7: 3643.4789 | H7: 4794.0512
E8: Uniglory Packaging Industries Ltd. | F8: RTO | G8: 3625.0718 | H8: 5370.4768
G9: =SUM(G7:H8) -> 17433.079
E11: Transworld Packaging (BD) Ltd. | F11: STD | G11: 4014.2217 | H11: 5281.8706
E12: Transworld Packaging (BD) Ltd. | F12: RTO | G12: 5978.1913 | H12: 8856.5797
G13: =SUM(G11:H12) -> 24130.863
H15: =G13+G9 -> 41563.942
G23: Pacd | H23: Mat
E24: Transworld Packaging (BD) Ltd. | F24: STD | G24: 4014.2217 | H24: 5281.8706
E25: Uniglory Packaging Industries Ltd. | F25: STD | G25: 3643.4789 | H25: 4794.0512
G26: =SUM(G24:H25) -> 17733.622
E29: Transworld Packaging (BD) Ltd. | F29: RTO | G29: 5978.1913 | H29: 8856.5797
E30: Uniglory Packaging Industries Ltd. | F30: RTO | G30: 3625.0718 | H30: 5370.4768
G31: =SUM(G29:H30) -> 23830.32

Sheet Matalan Curstom CTN Price Cal
A1: MATALAN CUSTOM CARTON PRICE CALCULATOR | L1: Version: 1.3 | M1: 45980
A2: Color | B2: Note | D2: PRICE FORMULA FOR 0201 | I2: CONFIRGURATION
B3: Matalan/PACD Config | D3: Price = Area * SqmPrice | I3: Flute Type | J3: Caliper(MM) | L3: EXW(w/VAT,CNY/SQM) | M3: Exchange Rate, $1=?
B4: Supplier fill area | D4: Area(C-Flute)=(2*L+2*W+15)*(H+W-10)/1000000 | I4: C-Flute | J4: 4 | L4: ='RFQ_Matalan Carton'!N32 -> 1.133 | M4: ='RFQ_Matalan Carton'!O2 -> 0
B5: Fixed/Automatical-fill
B6: Carton Price Result
D7: NOTE:
D8: 1- Standard cartons from A1~D3 need to be quoted by each
D9: 2- The Price Calculator only for custom carton in RSC(Regular Slotted Carton, FEFCO-0201) style
D10: 3- The results is EX-Works price with MOQ>=200pcs, (MOQ=Minimum Order Quantity)
D11: 4- Packaging Factory will charge CNY 300.00 fee for PO quantity less than MOQ=200; If printing is different on any line item that is considered an unique PO quantity.
D12: 5- Price rate will be reviewed every six months. Pricing to be advised no less than 30 days prior to the next 6 month term.
A15: Item# | B15: Size | C15: Carton Style | D15: FLUTE | E15: Thickness (mm) | F15: Outside Dimension(MM) | I15: Blank Sizes(mm) | K15: Area(sqm) | L15: Carton's Unit Price (CNY,EXW w/VAT) | M15: (USD REF.) | N15: NOTE
F16: Length | G16: Width | H16: Height | I16: L | J16: W
A17: 123456 | B17: XL | C17: RSC - 0201 | D17: C-Flute | E17: =IFERROR(VLOOKUP(D17,$I$3:$J$5,2,FALSE),0) -> 4 | F17: 595 | G17: 285 | H17: 375 | I17: {=_xlfn.SWITCH(D17,"C-Flute",(F17+G17)*2+15,"BC-Flute",(F17+G17)*2+11,0)} -> 1775 | J17: {=_xlfn.SWITCH(D17,"C-Flute",(G17+H17)-10,"BC-Flute",(G17+H17)-16,0)} -> 650 | K17: =I17*J17*(1+10%)/1000000 -> 1.269125 | L17: =IFERROR(K17*IFERROR(VLOOKUP(D17,$I$3:$L$5,4,FALSE),"N/A"),0) -> 1.4379186 | M17: =IFERROR(L17/$M$4,0) -> 0
A18: 654321 | B18: M | C18: RSC - 0201 | D18: C-Flute | E18: =IFERROR(VLOOKUP(D18,$I$3:$J$5,2,FALSE),0) -> 4 | F18: 495 | G18: 285 | H18: 375 | I18: {=_xlfn.SWITCH(D18,"C-Flute",(F18+G18)*2+15,"BC-Flute",(F18+G18)*2+11,0)} -> 1575 | J18: {=_xlfn.SWITCH(D18,"C-Flute",(G18+H18)-10,"BC-Flute",(G18+H18)-16,0)} -> 650 | K18: =I18*J18*(1+10%)/1000000 -> 1.126125 | L18: =IFERROR(K18*IFERROR(VLOOKUP(D18,$I$3:$L$5,4,FALSE),"N/A"),0) -> 1.2758996 | M18: =IFERROR(L18/$M$4,0) -> 0
C19: RSC - 0201 | E19: =IFERROR(VLOOKUP(D19,$I$3:$J$5,2,FALSE),0) -> 0 | I19: {=_xlfn.SWITCH(D19,"C-Flute",(F19+G19)*2+15,"BC-Flute",(F19+G19)*2+11,0)} -> 0 | J19: {=_xlfn.SWITCH(D19,"C-Flute",(G19+H19)-10,"BC-Flute",(G19+H19)-16,0)} -> 0 | K19: =I19*J19*(1+10%)/1000000 -> 0 | L19: =IFERROR(K19*IFERROR(VLOOKUP(D19,$I$3:$L$5,4,FALSE),"N/A"),0) -> 0 | M19: =IFERROR(L19/$M$4,0) -> 0
C20: RSC - 0201 | E20: =IFERROR(VLOOKUP(D20,$I$3:$J$5,2,FALSE),0) -> 0 | I20: {=_xlfn.SWITCH(D20,"C-Flute",(F20+G20)*2+15,"BC-Flute",(F20+G20)*2+11,0)} -> 0 | J20: {=_xlfn.SWITCH(D20,"C-Flute",(G20+H20)-10,"BC-Flute",(G20+H20)-16,0)} -> 0 | K20: =I20*J20*(1+10%)/1000000 -> 0 | L20: =IFERROR(K20*IFERROR(VLOOKUP(D20,$I$3:$L$5,4,FALSE),"N/A"),0) -> 0 | M20: =IFERROR(L20/$M$4,0) -> 0
C21: RSC - 0201 | E21: =IFERROR(VLOOKUP(D21,$I$3:$J$5,2,FALSE),0) -> 0 | I21: {=_xlfn.SWITCH(D21,"C-Flute",(F21+G21)*2+15,"BC-Flute",(F21+G21)*2+11,0)} -> 0 | J21: {=_xlfn.SWITCH(D21,"C-Flute",(G21+H21)-10,"BC-Flute",(G21+H21)-16,0)} -> 0 | K21: =I21*J21*(1+10%)/1000000 -> 0 | L21: =IFERROR(K21*IFERROR(VLOOKUP(D21,$I$3:$L$5,4,FALSE),"N/A"),0) -> 0 | M21: =IFERROR(L21/$M$4,0) -> 0
C22: RSC - 0201 | E22: =IFERROR(VLOOKUP(D22,$I$3:$J$5,2,FALSE),0) -> 0 | I22: {=_xlfn.SWITCH(D22,"C-Flute",(F22+G22)*2+15,"BC-Flute",(F22+G22)*2+11,0)} -> 0 | J22: {=_xlfn.SWITCH(D22,"C-Flute",(G22+H22)-10,"BC-Flute",(G22+H22)-16,0)} -> 0 | K22: =I22*J22*(1+10%)/1000000 -> 0 | L22: =IFERROR(K22*IFERROR(VLOOKUP(D22,$I$3:$L$5,4,FALSE),"N/A"),0) -> 0 | M22: =IFERROR(L22/$M$4,0) -> 0
C23: RSC - 0201 | E23: =IFERROR(VLOOKUP(D23,$I$3:$J$5,2,FALSE),0) -> 0 | I23: {=_xlfn.SWITCH(D23,"C-Flute",(F23+G23)*2+15,"BC-Flute",(F23+G23)*2+11,0)} -> 0 | J23: {=_xlfn.SWITCH(D23,"C-Flute",(G23+H23)-10,"BC-Flute",(G23+H23)-16,0)} -> 0 | K23: =I23*J23*(1+10%)/1000000 -> 0 | L23: =IFERROR(K23*IFERROR(VLOOKUP(D23,$I$3:$L$5,4,FALSE),"N/A"),0) -> 0 | M23: =IFERROR(L23/$M$4,0) -> 0
C24: RSC - 0201 | E24: =IFERROR(VLOOKUP(D24,$I$3:$J$5,2,FALSE),0) -> 0 | I24: {=_xlfn.SWITCH(D24,"C-Flute",(F24+G24)*2+15,"BC-Flute",(F24+G24)*2+11,0)} -> 0 | J24: {=_xlfn.SWITCH(D24,"C-Flute",(G24+H24)-10,"BC-Flute",(G24+H24)-16,0)} -> 0 | K24: =I24*J24*(1+10%)/1000000 -> 0 | L24: =IFERROR(K24*IFERROR(VLOOKUP(D24,$I$3:$L$5,4,FALSE),"N/A"),0) -> 0 | M24: =IFERROR(L24/$M$4,0) -> 0
C25: RSC - 0201 | E25: =IFERROR(VLOOKUP(D25,$I$3:$J$5,2,FALSE),0) -> 0 | I25: {=_xlfn.SWITCH(D25,"C-Flute",(F25+G25)*2+15,"BC-Flute",(F25+G25)*2+11,0)} -> 0 | J25: {=_xlfn.SWITCH(D25,"C-Flute",(G25+H25)-10,"BC-Flute",(G25+H25)-16,0)} -> 0 | K25: =I25*J25*(1+10%)/1000000 -> 0 | L25: =IFERROR(K25*IFERROR(VLOOKUP(D25,$I$3:$L$5,4,FALSE),"N/A"),0) -> 0 | M25: =IFERROR(L25/$M$4,0) -> 0
C26: RSC - 0201 | E26: =IFERROR(VLOOKUP(D26,$I$3:$J$5,2,FALSE),0) -> 0 | I26: {=_xlfn.SWITCH(D26,"C-Flute",(F26+G26)*2+15,"BC-Flute",(F26+G26)*2+11,0)} -> 0 | J26: {=_xlfn.SWITCH(D26,"C-Flute",(G26+H26)-10,"BC-Flute",(G26+H26)-16,0)} -> 0 | K26: =I26*J26*(1+10%)/1000000 -> 0 | L26: =IFERROR(K26*IFERROR(VLOOKUP(D26,$I$3:$L$5,4,FALSE),"N/A"),0) -> 0 | M26: =IFERROR(L26/$M$4,0) -> 0
C27: RSC - 0201 | E27: =IFERROR(VLOOKUP(D27,$I$3:$J$5,2,FALSE),0) -> 0 | I27: {=_xlfn.SWITCH(D27,"C-Flute",(F27+G27)*2+15,"BC-Flute",(F27+G27)*2+11,0)} -> 0 | J27: {=_xlfn.SWITCH(D27,"C-Flute",(G27+H27)-10,"BC-Flute",(G27+H27)-16,0)} -> 0 | K27: =I27*J27*(1+10%)/1000000 -> 0 | L27: =IFERROR(K27*IFERROR(VLOOKUP(D27,$I$3:$L$5,4,FALSE),"N/A"),0) -> 0 | M27: =IFERROR(L27/$M$4,0) -> 0
C28: RSC - 0201 | E28: =IFERROR(VLOOKUP(D28,$I$3:$J$5,2,FALSE),0) -> 0 | I28: {=_xlfn.SWITCH(D28,"C-Flute",(F28+G28)*2+15,"BC-Flute",(F28+G28)*2+11,0)} -> 0 | J28: {=_xlfn.SWITCH(D28,"C-Flute",(G28+H28)-10,"BC-Flute",(G28+H28)-16,0)} -> 0 | K28: =I28*J28*(1+10%)/1000000 -> 0 | L28: =IFERROR(K28*IFERROR(VLOOKUP(D28,$I$3:$L$5,4,FALSE),"N/A"),0) -> 0 | M28: =IFERROR(L28/$M$4,0) -> 0
C29: RSC - 0201 | E29: =IFERROR(VLOOKUP(D29,$I$3:$J$5,2,FALSE),0) -> 0 | I29: {=_xlfn.SWITCH(D29,"C-Flute",(F29+G29)*2+15,"BC-Flute",(F29+G29)*2+11,0)} -> 0 | J29: {=_xlfn.SWITCH(D29,"C-Flute",(G29+H29)-10,"BC-Flute",(G29+H29)-16,0)} -> 0 | K29: =I29*J29*(1+10%)/1000000 -> 0 | L29: =IFERROR(K29*IFERROR(VLOOKUP(D29,$I$3:$L$5,4,FALSE),"N/A"),0) -> 0 | M29: =IFERROR(L29/$M$4,0) -> 0
C30: RSC - 0201 | E30: =IFERROR(VLOOKUP(D30,$I$3:$J$5,2,FALSE),0) -> 0 | I30: {=_xlfn.SWITCH(D30,"C-Flute",(F30+G30)*2+15,"BC-Flute",(F30+G30)*2+11,0)} -> 0 | J30: {=_xlfn.SWITCH(D30,"C-Flute",(G30+H30)-10,"BC-Flute",(G30+H30)-16,0)} -> 0 | K30: =I30*J30*(1+10%)/1000000 -> 0 | L30: =IFERROR(K30*IFERROR(VLOOKUP(D30,$I$3:$L$5,4,FALSE),"N/A"),0) -> 0 | M30: =IFERROR(L30/$M$4,0) -> 0
... C604: RSC - 0201 | E604: =IFERROR(VLOOKUP(D604,$I$3:$J$5,2,FALSE),0) -> 0 | I604: {=_xlfn.SWITCH(D604,"C-Flute",(F604+G604)*2+15,"BC-Flute",(F604+G604)*2+11,0)} -> 0 | J604: {=_xlfn.SWITCH(D604,"C-Flute",(G604+H604)-10,"BC-Flute",(G604+H604)-16,0)} -> 0 | K604: =I604*J604*(1+10%)/1000000 -> 0 | L604: =IFERROR(K604*IFERROR(VLOOKUP(D604,$I$3:$L$5,4,FALSE),"N/A"),0) -> 0 | M604: =IFERROR(L604/$M$4,0) -> 0
